[{"id":24358,"text":"\u0a2e\u0a03 \u0a6b \u0965","original":"\u0a2e\u0a03\u0a6b\u0965","melody_id":1,"author_id":2,"hymn":1451,"page":554,"line":1,"section":"Bihagara - Bihagara Ki Vaar","search":"\u0a2e","language_id":54,"translation":{"id":414070,"scripture_id":24358,"text":"Fifth Mehl:","language_id":13,"language":{"id":13,"language":"English","code":"en-US","script":"latn","direction":1,"accuracy":99}},"transliteration":{"id":535855,"scripture_id":24358,"text":"mah 5 .","language_id":69,"language":{"id":69,"language":"Latin","code":null,"script":"latn","direction":1,"accuracy":99}},"melody":{"id":1,"melody":"None","gurmukhi":"","description":"There is no melody or mood associated with this line, which may be because it is the preamble to the hymn, or is not meant to be read in any particular melody or mood"},"author":{"id":2,"author":"None","gurmukhi":"","description":"There is no author associated with this line, as it may be the preamble to the hymn"},"language":{"id":54,"language":"Gurmukhi","code":"pa","script":"guru","direction":1,"accuracy":99}},{"id":24359,"text":"\u0a18\u0a1f\u0a3f \u0a35\u0a38\u0a39\u0a3f \u0a1a\u0a30\u0a23\u0a3e\u0a30\u0a2c\u0a3f\u0a70\u0a26 \u0a30\u0a38\u0a28\u0a3e \u0a1c\u0a2a\u0a48 \u0a17\u0a41\u0a2a\u0a3e\u0a32 \u0965","original":"\u0a18\u0a1f\u0a3f\u0a35\u0a38\u0a39\u0a3f\u0a1a\u0a30\u0a23\u0a3e\u0a30\u0a2c\u0a3f\u0a70\u0a26\u0a30\u0a38\u0a28\u0a3e\u0a1c\u0a2a\u0a48\u0a17\u0a41\u0a2a\u0a3e\u0a32\u0965","melody_id":23,"author_id":4,"hymn":1451,"page":554,"line":1,"section":"Bihagara - Bihagara Ki Vaar","search":"\u0a18\u0a35\u0a1a\u0a30\u0a1c\u0a17","language_id":54,"translation":{"id":414087,"scripture_id":24359,"text":"Let the Lotus Feet of the Lord abide within your heart, and with your tongue, chant God's Name.","language_id":13,"language":{"id":13,"language":"English","code":"en-US","script":"latn","direction":1,"accuracy":99}},"transliteration":{"id":535877,"scripture_id":24359,"text":"ghat vasah charan\u0101rabind rasan\u0101 japai gup\u0101l .","language_id":69,"language":{"id":69,"language":"Latin","code":null,"script":"latn","direction":1,"accuracy":99}},"melody":{"id":23,"melody":"Bihagara","gurmukhi":"\u0a2c\u0a3f\u0a39\u0a3e\u0a17\u0a5c\u0a3e","description":"The mood of Bihagara is that of extreme sadness and pain, which gives rise to the need to find peace and understanding. The heightened emotional state of sadness is only harnessed by the craving for truth and meaning."},"author":{"id":4,"author":"Guru Arjan Dev","gurmukhi":"\u0a2e\u0a03 \u0a6b","description":"Guru Arjan Dev [1563 - 1606] was the fifth Guru of the Sikhs, born at Goindval. He was the youngest of the three sons of Guru Ram Das, the fourth Sikh Guru.<br\/><br\/>Guru Arjan Dev finished the construction of the Harimandir Sahib, the Golden Temple, and compiled the first Sikh scripture, known as the Adi Granth. Shortly after he became the first martyr of the Sikh religion, which formed a turning point in the development of the faith."},"language":{"id":54,"language":"Gurmukhi","code":"pa","script":"guru","direction":1,"accuracy":99}},{"id":24360,"text":"\u0a28\u0a3e\u0a28\u0a15 \u0a38\u0a4b \u0a2a\u0a4d\u0a30\u0a2d\u0a41 \u0a38\u0a3f\u0a2e\u0a30\u0a40\u0a10 \u0a24\u0a3f\u0a38\u0a41 \u0a26\u0a47\u0a39\u0a40 \u0a15\u0a09 \u0a2a\u0a3e\u0a32\u0a3f \u0965\u0a68\u0965","original":"\u0a28\u0a3e\u0a28\u0a15\u0a38\u0a4b\u0a2a\u0a4d\u0a30\u0a2d\u0a41\u0a38\u0a3f\u0a2e\u0a30\u0a40\u0a10\u0a24\u0a3f\u0a38\u0a41\u0a26\u0a47\u0a39\u0a40\u0a15\u0a09\u0a2a\u0a3e\u0a32\u0a3f\u0965\u0a68\u0965","melody_id":23,"author_id":4,"hymn":1451,"page":554,"line":1,"section":"Bihagara - Bihagara Ki Vaar","search":"\u0a28\u0a38\u0a2a\u0a38\u0a24\u0a26\u0a15\u0a2a","language_id":54,"translation":{"id":414104,"scripture_id":24360,"text":"O Nanak, meditate in remembrance on God, and nurture this body. ||2||","language_id":13,"language":{"id":13,"language":"English","code":"en-US","script":"latn","direction":1,"accuracy":99}},"transliteration":{"id":535899,"scripture_id":24360,"text":"n\u0101nak s\u014d prabh simar\u012bai tis d\u0113h\u012b kau p\u0101l .2.","language_id":69,"language":{"id":69,"language":"Latin","code":null,"script":"latn","direction":1,"accuracy":99}},"melody":{"id":23,"melody":"Bihagara","gurmukhi":"\u0a2c\u0a3f\u0a39\u0a3e\u0a17\u0a5c\u0a3e","description":"The mood of Bihagara is that of extreme sadness and pain, which gives rise to the need to find peace and understanding. The heightened emotional state of sadness is only harnessed by the craving for truth and meaning."},"author":{"id":4,"author":"Guru Arjan Dev","gurmukhi":"\u0a2e\u0a03 \u0a6b","description":"Guru Arjan Dev [1563 - 1606] was the fifth Guru of the Sikhs, born at Goindval. He was the youngest of the three sons of Guru Ram Das, the fourth Sikh Guru.<br\/><br\/>Guru Arjan Dev finished the construction of the Harimandir Sahib, the Golden Temple, and compiled the first Sikh scripture, known as the Adi Granth. Shortly after he became the first martyr of the Sikh religion, which formed a turning point in the development of the faith."},"language":{"id":54,"language":"Gurmukhi","code":"pa","script":"guru","direction":1,"accuracy":99}},{"id":24361,"text":"\u0a2a\u0a09\u0a5c\u0a40 \u0965","original":"\u0a2a\u0a09\u0a5c\u0a40\u0965","melody_id":1,"author_id":2,"hymn":1451,"page":554,"line":2,"section":"Bihagara - Bihagara Ki Vaar","search":"\u0a2a","language_id":54,"translation":{"id":414121,"scripture_id":24361,"text":"Pauree:","language_id":13,"language":{"id":13,"language":"English","code":"en-US","script":"latn","direction":1,"accuracy":99}},"transliteration":{"id":535921,"scripture_id":24361,"text":"paur\u012b .","language_id":69,"language":{"id":69,"language":"Latin","code":null,"script":"latn","direction":1,"accuracy":99}},"melody":{"id":1,"melody":"None","gurmukhi":"","description":"There is no melody or mood associated with this line, which may be because it is the preamble to the hymn, or is not meant to be read in any particular melody or mood"},"author":{"id":2,"author":"None","gurmukhi":"","description":"There is no author associated with this line, as it may be the preamble to the hymn"},"language":{"id":54,"language":"Gurmukhi","code":"pa","script":"guru","direction":1,"accuracy":99}},{"id":24362,"text":"\u0a06\u0a2a\u0a47 \u0a05\u0a20\u0a38\u0a20\u0a3f \u0a24\u0a40\u0a30\u0a25 \u0a15\u0a30\u0a24\u0a3e \u0a06\u0a2a\u0a3f \u0a15\u0a30\u0a47 \u0a07\u0a38\u0a28\u0a3e\u0a28\u0a41 \u0965","original":"\u0a06\u0a2a\u0a47\u0a05\u0a20\u0a38\u0a20\u0a3f\u0a24\u0a40\u0a30\u0a25\u0a15\u0a30\u0a24\u0a3e\u0a06\u0a2a\u0a3f\u0a15\u0a30\u0a47\u0a07\u0a38\u0a28\u0a3e\u0a28\u0a41\u0965","melody_id":23,"author_id":4,"hymn":1451,"page":554,"line":2,"section":"Bihagara - Bihagara Ki Vaar","search":"\u0a05\u0a05\u0a24\u0a15\u0a05\u0a15\u0a72","language_id":54,"translation":{"id":414138,"scripture_id":24362,"text":"The Creator Himself is the sixty-eight sacred places of pilgrimage; He Himself takes the cleansing bath in them.","language_id":13,"language":{"id":13,"language":"English","code":"en-US","script":"latn","direction":1,"accuracy":99}},"transliteration":{"id":535943,"scripture_id":24362,"text":"\u0101p\u0113 athasath t\u012brath karat\u0101 \u0101p kar\u0113 isan\u0101n .","language_id":69,"language":{"id":69,"language":"Latin","code":null,"script":"latn","direction":1,"accuracy":99}},"melody":{"id":23,"melody":"Bihagara","gurmukhi":"\u0a2c\u0a3f\u0a39\u0a3e\u0a17\u0a5c\u0a3e","description":"The mood of Bihagara is that of extreme sadness and pain, which gives rise to the need to find peace and understanding. The heightened emotional state of sadness is only harnessed by the craving for truth and meaning."},"author":{"id":4,"author":"Guru Arjan Dev","gurmukhi":"\u0a2e\u0a03 \u0a6b","description":"Guru Arjan Dev [1563 - 1606] was the fifth Guru of the Sikhs, born at Goindval. He was the youngest of the three sons of Guru Ram Das, the fourth Sikh Guru.<br\/><br\/>Guru Arjan Dev finished the construction of the Harimandir Sahib, the Golden Temple, and compiled the first Sikh scripture, known as the Adi Granth. Shortly after he became the first martyr of the Sikh religion, which formed a turning point in the development of the faith."},"language":{"id":54,"language":"Gurmukhi","code":"pa","script":"guru","direction":1,"accuracy":99}},{"id":24363,"text":"\u0a06\u0a2a\u0a47 \u0a38\u0a70\u0a1c\u0a2e\u0a3f \u0a35\u0a30\u0a24\u0a48 \u0a38\u0a4d\u0a35\u0a3e\u0a2e\u0a40 \u0a06\u0a2a\u0a3f \u0a1c\u0a2a\u0a3e\u0a07\u0a39\u0a3f \u0a28\u0a3e\u0a2e\u0a41 \u0965","original":"\u0a06\u0a2a\u0a47\u0a38\u0a70\u0a1c\u0a2e\u0a3f\u0a35\u0a30\u0a24\u0a48\u0a38\u0a4d\u0a35\u0a3e\u0a2e\u0a40\u0a06\u0a2a\u0a3f\u0a1c\u0a2a\u0a3e\u0a07\u0a39\u0a3f\u0a28\u0a3e\u0a2e\u0a41\u0965","melody_id":23,"author_id":4,"hymn":1451,"page":554,"line":2,"section":"Bihagara - Bihagara Ki Vaar","search":"\u0a05\u0a38\u0a35\u0a38\u0a05\u0a1c\u0a28","language_id":54,"translation":{"id":414155,"scripture_id":24363,"text":"He Himself practices austere self-discipline; the Lord Master Himself causes us to chant His Name.","language_id":13,"language":{"id":13,"language":"English","code":"en-US","script":"latn","direction":1,"accuracy":99}},"transliteration":{"id":535965,"scripture_id":24363,"text":"\u0101p\u0113 sanjam varatai sv\u0101m\u012b \u0101p jap\u0101ih n\u0101m .","language_id":69,"language":{"id":69,"language":"Latin","code":null,"script":"latn","direction":1,"accuracy":99}},"melody":{"id":23,"melody":"Bihagara","gurmukhi":"\u0a2c\u0a3f\u0a39\u0a3e\u0a17\u0a5c\u0a3e","description":"The mood of Bihagara is that of extreme sadness and pain, which gives rise to the need to find peace and understanding. The heightened emotional state of sadness is only harnessed by the craving for truth and meaning."},"author":{"id":4,"author":"Guru Arjan Dev","gurmukhi":"\u0a2e\u0a03 \u0a6b","description":"Guru Arjan Dev [1563 - 1606] was the fifth Guru of the Sikhs, born at Goindval. He was the youngest of the three sons of Guru Ram Das, the fourth Sikh Guru.<br\/><br\/>Guru Arjan Dev finished the construction of the Harimandir Sahib, the Golden Temple, and compiled the first Sikh scripture, known as the Adi Granth. Shortly after he became the first martyr of the Sikh religion, which formed a turning point in the development of the faith."},"language":{"id":54,"language":"Gurmukhi","code":"pa","script":"guru","direction":1,"accuracy":99}},{"id":24364,"text":"\u0a06\u0a2a\u0a3f \u0a26\u0a07\u0a06\u0a32\u0a41 \u0a39\u0a4b\u0a07 \u0a2d\u0a09 \u0a16\u0a70\u0a21\u0a28\u0a41 \u0a06\u0a2a\u0a3f \u0a15\u0a30\u0a48 \u0a38\u0a2d\u0a41 \u0a26\u0a3e\u0a28\u0a41 \u0965","original":"\u0a06\u0a2a\u0a3f\u0a26\u0a07\u0a06\u0a32\u0a41\u0a39\u0a4b\u0a07\u0a2d\u0a09\u0a16\u0a70\u0a21\u0a28\u0a41\u0a06\u0a2a\u0a3f\u0a15\u0a30\u0a48\u0a38\u0a2d\u0a41\u0a26\u0a3e\u0a28\u0a41\u0965","melody_id":23,"author_id":4,"hymn":1451,"page":554,"line":3,"section":"Bihagara - Bihagara Ki Vaar","search":"\u0a05\u0a26\u0a39\u0a2d\u0a16\u0a05\u0a15\u0a38\u0a26","language_id":54,"translation":{"id":414172,"scripture_id":24364,"text":"He Himself becomes merciful to us; the Destroyer of fear Himself gives in charity to all.","language_id":13,"language":{"id":13,"language":"English","code":"en-US","script":"latn","direction":1,"accuracy":99}},"transliteration":{"id":535987,"scripture_id":24364,"text":"\u0101p dai\u0101l h\u014di bhau khandan \u0101p karai sabh d\u0101n .","language_id":69,"language":{"id":69,"language":"Latin","code":null,"script":"latn","direction":1,"accuracy":99}},"melody":{"id":23,"melody":"Bihagara","gurmukhi":"\u0a2c\u0a3f\u0a39\u0a3e\u0a17\u0a5c\u0a3e","description":"The mood of Bihagara is that of extreme sadness and pain, which gives rise to the need to find peace and understanding. The heightened emotional state of sadness is only harnessed by the craving for truth and meaning."},"author":{"id":4,"author":"Guru Arjan Dev","gurmukhi":"\u0a2e\u0a03 \u0a6b","description":"Guru Arjan Dev [1563 - 1606] was the fifth Guru of the Sikhs, born at Goindval. He was the youngest of the three sons of Guru Ram Das, the fourth Sikh Guru.<br\/><br\/>Guru Arjan Dev finished the construction of the Harimandir Sahib, the Golden Temple, and compiled the first Sikh scripture, known as the Adi Granth. Shortly after he became the first martyr of the Sikh religion, which formed a turning point in the development of the faith."},"language":{"id":54,"language":"Gurmukhi","code":"pa","script":"guru","direction":1,"accuracy":99}},{"id":24365,"text":"\u0a1c\u0a3f\u0a38 \u0a28\u0a4b \u0a17\u0a41\u0a30\u0a2e\u0a41\u0a16\u0a3f \u0a06\u0a2a\u0a3f \u0a2c\u0a41\u0a1d\u0a3e\u0a0f \u0a38\u0a4b \u0a38\u0a26 \u0a39\u0a40 \u0a26\u0a30\u0a17\u0a39\u0a3f \u0a2a\u0a3e\u0a0f \u0a2e\u0a3e\u0a28\u0a41 \u0965","original":"\u0a1c\u0a3f\u0a38\u0a28\u0a4b\u0a17\u0a41\u0a30\u0a2e\u0a41\u0a16\u0a3f\u0a06\u0a2a\u0a3f\u0a2c\u0a41\u0a1d\u0a3e\u0a0f\u0a38\u0a4b\u0a38\u0a26\u0a39\u0a40\u0a26\u0a30\u0a17\u0a39\u0a3f\u0a2a\u0a3e\u0a0f\u0a2e\u0a3e\u0a28\u0a41\u0965","melody_id":23,"author_id":4,"hymn":1451,"page":554,"line":4,"section":"Bihagara - Bihagara Ki Vaar","search":"\u0a1c\u0a28\u0a17\u0a05\u0a2c\u0a38\u0a38\u0a39\u0a26\u0a2a\u0a2e","language_id":54,"translation":{"id":414189,"scripture_id":24365,"text":"One whom He has enlightened and made Gurmukh, ever obtains honor in His Court.","language_id":13,"language":{"id":13,"language":"English","code":"en-US","script":"latn","direction":1,"accuracy":99}},"transliteration":{"id":536009,"scripture_id":24365,"text":"jis n\u014d guramukh \u0101p bujh\u0101\u0113 s\u014d sad h\u012b daragah p\u0101\u0113 m\u0101n .","language_id":69,"language":{"id":69,"language":"Latin","code":null,"script":"latn","direction":1,"accuracy":99}},"melody":{"id":23,"melody":"Bihagara","gurmukhi":"\u0a2c\u0a3f\u0a39\u0a3e\u0a17\u0a5c\u0a3e","description":"The mood of Bihagara is that of extreme sadness and pain, which gives rise to the need to find peace and understanding. The heightened emotional state of sadness is only harnessed by the craving for truth and meaning."},"author":{"id":4,"author":"Guru Arjan Dev","gurmukhi":"\u0a2e\u0a03 \u0a6b","description":"Guru Arjan Dev [1563 - 1606] was the fifth Guru of the Sikhs, born at Goindval. He was the youngest of the three sons of Guru Ram Das, the fourth Sikh Guru.<br\/><br\/>Guru Arjan Dev finished the construction of the Harimandir Sahib, the Golden Temple, and compiled the first Sikh scripture, known as the Adi Granth. Shortly after he became the first martyr of the Sikh religion, which formed a turning point in the development of the faith."},"language":{"id":54,"language":"Gurmukhi","code":"pa","script":"guru","direction":1,"accuracy":99}},{"id":24366,"text":"\u0a1c\u0a3f\u0a38 \u0a26\u0a40 \u0a2a\u0a48\u0a1c \u0a30\u0a16\u0a48 \u0a39\u0a30\u0a3f \u0a38\u0a41\u0a06\u0a2e\u0a40 \u0a38\u0a4b \u0a38\u0a1a\u0a3e \u0a39\u0a30\u0a3f \u0a1c\u0a3e\u0a28\u0a41 \u0965\u0a67\u0a6a\u0965","original":"\u0a1c\u0a3f\u0a38\u0a26\u0a40\u0a2a\u0a48\u0a1c\u0a30\u0a16\u0a48\u0a39\u0a30\u0a3f\u0a38\u0a41\u0a06\u0a2e\u0a40\u0a38\u0a4b\u0a38\u0a1a\u0a3e\u0a39\u0a30\u0a3f\u0a1c\u0a3e\u0a28\u0a41\u0965\u0a67\u0a6a\u0965","melody_id":23,"author_id":4,"hymn":1451,"page":554,"line":4,"section":"Bihagara - Bihagara Ki Vaar","search":"\u0a1c\u0a26\u0a2a\u0a30\u0a39\u0a38\u0a38\u0a38\u0a39\u0a1c","language_id":54,"translation":{"id":414206,"scripture_id":24366,"text":"One whose honor the Lord Master has preserved, comes to know the True Lord. ||14||","language_id":13,"language":{"id":13,"language":"English","code":"en-US","script":"latn","direction":1,"accuracy":99}},"transliteration":{"id":536031,"scripture_id":24366,"text":"jis d\u012b paij rakhai har su\u0101m\u012b s\u014d sach\u0101 har j\u0101n .14.","language_id":69,"language":{"id":69,"language":"Latin","code":null,"script":"latn","direction":1,"accuracy":99}},"melody":{"id":23,"melody":"Bihagara","gurmukhi":"\u0a2c\u0a3f\u0a39\u0a3e\u0a17\u0a5c\u0a3e","description":"The mood of Bihagara is that of extreme sadness and pain, which gives rise to the need to find peace and understanding. The heightened emotional state of sadness is only harnessed by the craving for truth and meaning."},"author":{"id":4,"author":"Guru Arjan Dev","gurmukhi":"\u0a2e\u0a03 \u0a6b","description":"Guru Arjan Dev [1563 - 1606] was the fifth Guru of the Sikhs, born at Goindval. He was the youngest of the three sons of Guru Ram Das, the fourth Sikh Guru.<br\/><br\/>Guru Arjan Dev finished the construction of the Harimandir Sahib, the Golden Temple, and compiled the first Sikh scripture, known as the Adi Granth. Shortly after he became the first martyr of the Sikh religion, which formed a turning point in the development of the faith."},"language":{"id":54,"language":"Gurmukhi","code":"pa","script":"guru","direction":1,"accuracy":99}},{"id":24367,"text":"\u0a38\u0a32\u0a4b\u0a15\u0a41 \u0a2e\u0a03 \u0a69 \u0965","original":"\u0a38\u0a32\u0a4b\u0a15\u0a41\u0a2e\u0a03\u0a69\u0965","melody_id":1,"author_id":2,"hymn":1452,"page":554,"line":5,"section":"Bihagara - Bihagara Ki Vaar","search":"\u0a38\u0a2e","language_id":54,"translation":{"id":414223,"scripture_id":24367,"text":"Shalok, Third Mehl:","language_id":13,"language":{"id":13,"language":"English","code":"en-US","script":"latn","direction":1,"accuracy":99}},"transliteration":{"id":536053,"scripture_id":24367,"text":"sal\u014dk mah 3 .","language_id":69,"language":{"id":69,"language":"Latin","code":null,"script":"latn","direction":1,"accuracy":99}},"melody":{"id":1,"melody":"None","gurmukhi":"","description":"There is no melody or mood associated with this line, which may be because it is the preamble to the hymn, or is not meant to be read in any particular melody or mood"},"author":{"id":2,"author":"None","gurmukhi":"","description":"There is no author associated with this line, as it may be the preamble to the hymn"},"language":{"id":54,"language":"Gurmukhi","code":"pa","script":"guru","direction":1,"accuracy":99}},{"id":24368,"text":"\u0a28\u0a3e\u0a28\u0a15 \u0a2c\u0a3f\u0a28\u0a41 \u0a38\u0a24\u0a3f\u0a17\u0a41\u0a30 \u0a2d\u0a47\u0a1f\u0a47 \u0a1c\u0a17\u0a41 \u0a05\u0a70\u0a27\u0a41 \u0a39\u0a48 \u0a05\u0a70\u0a27\u0a47 \u0a15\u0a30\u0a2e \u0a15\u0a2e\u0a3e\u0a07 \u0965","original":"\u0a28\u0a3e\u0a28\u0a15\u0a2c\u0a3f\u0a28\u0a41\u0a38\u0a24\u0a3f\u0a17\u0a41\u0a30\u0a2d\u0a47\u0a1f\u0a47\u0a1c\u0a17\u0a41\u0a05\u0a70\u0a27\u0a41\u0a39\u0a48\u0a05\u0a70\u0a27\u0a47\u0a15\u0a30\u0a2e\u0a15\u0a2e\u0a3e\u0a07\u0965","melody_id":23,"author_id":5,"hymn":1452,"page":554,"line":5,"section":"Bihagara - Bihagara Ki Vaar","search":"\u0a28\u0a2c\u0a38\u0a2d\u0a1c\u0a05\u0a39\u0a05\u0a15\u0a15","language_id":54,"translation":{"id":414240,"scripture_id":24368,"text":"O Nanak, without meeting the True Guru, the world is blind, and it does blind deeds.","language_id":13,"language":{"id":13,"language":"English","code":"en-US","script":"latn","direction":1,"accuracy":99}},"transliteration":{"id":536075,"scripture_id":24368,"text":"n\u0101nak bin satigur bh\u0113t\u0113 jag andh hai andh\u0113 karam kam\u0101i .","language_id":69,"language":{"id":69,"language":"Latin","code":null,"script":"latn","direction":1,"accuracy":99}},"melody":{"id":23,"melody":"Bihagara","gurmukhi":"\u0a2c\u0a3f\u0a39\u0a3e\u0a17\u0a5c\u0a3e","description":"The mood of Bihagara is that of extreme sadness and pain, which gives rise to the need to find peace and understanding. The heightened emotional state of sadness is only harnessed by the craving for truth and meaning."},"author":{"id":5,"author":"Guru Amar Das","gurmukhi":"\u0a2e\u0a03 \u0a69","description":"Guru Amar Das [1479 - 1574] was the third Guru of the Sikhs, born at Basarke in Amritsar. His father, Tej Bhan and mother Bakht Kaur were orthodox Hindus. He became the oldest Sikh Guru.<br\/><\/br>Guru Amar Das put an end to tradition of sati, the burning of the widow on her husbands funeral pyre, and encouraged the remarriage of widows. He opened 22 preaching centres called Manjees and founded the town of Goindwal as the headquarters for the Sikh community."},"language":{"id":54,"language":"Gurmukhi","code":"pa","script":"guru","direction":1,"accuracy":99}},{"id":24369,"text":"\u0a38\u0a2c\u0a26\u0a48 \u0a38\u0a3f\u0a09 \u0a1a\u0a3f\u0a24\u0a41 \u0a28 \u0a32\u0a3e\u0a35\u0a08 \u0a1c\u0a3f\u0a24\u0a41 \u0a38\u0a41\u0a16\u0a41 \u0a35\u0a38\u0a48 \u0a2e\u0a28\u0a3f \u0a06\u0a07 \u0965","original":"\u0a38\u0a2c\u0a26\u0a48\u0a38\u0a3f\u0a09\u0a1a\u0a3f\u0a24\u0a41\u0a28\u0a32\u0a3e\u0a35\u0a08\u0a1c\u0a3f\u0a24\u0a41\u0a38\u0a41\u0a16\u0a41\u0a35\u0a38\u0a48\u0a2e\u0a28\u0a3f\u0a06\u0a07\u0965","melody_id":23,"author_id":5,"hymn":1452,"page":554,"line":5,"section":"Bihagara - Bihagara Ki Vaar","search":"\u0a38\u0a38\u0a1a\u0a28\u0a32\u0a1c\u0a38\u0a35\u0a2e\u0a05","language_id":54,"translation":{"id":414257,"scripture_id":24369,"text":"It does not focus its consciousness on the Word of the Shabad, which would bring peace to abide in the mind.","language_id":13,"language":{"id":13,"language":"English","code":"en-US","script":"latn","direction":1,"accuracy":99}},"transliteration":{"id":536097,"scripture_id":24369,"text":"sabadai siu chit n l\u0101va\u012b jit sukh vasai man \u0101i .","language_id":69,"language":{"id":69,"language":"Latin","code":null,"script":"latn","direction":1,"accuracy":99}},"melody":{"id":23,"melody":"Bihagara","gurmukhi":"\u0a2c\u0a3f\u0a39\u0a3e\u0a17\u0a5c\u0a3e","description":"The mood of Bihagara is that of extreme sadness and pain, which gives rise to the need to find peace and understanding. The heightened emotional state of sadness is only harnessed by the craving for truth and meaning."},"author":{"id":5,"author":"Guru Amar Das","gurmukhi":"\u0a2e\u0a03 \u0a69","description":"Guru Amar Das [1479 - 1574] was the third Guru of the Sikhs, born at Basarke in Amritsar. His father, Tej Bhan and mother Bakht Kaur were orthodox Hindus. He became the oldest Sikh Guru.<br\/><\/br>Guru Amar Das put an end to tradition of sati, the burning of the widow on her husbands funeral pyre, and encouraged the remarriage of widows. He opened 22 preaching centres called Manjees and founded the town of Goindwal as the headquarters for the Sikh community."},"language":{"id":54,"language":"Gurmukhi","code":"pa","script":"guru","direction":1,"accuracy":99}},{"id":24370,"text":"\u0a24\u0a3e\u0a2e\u0a38\u0a3f \u0a32\u0a17\u0a3e \u0a38\u0a26\u0a3e \u0a2b\u0a3f\u0a30\u0a48 \u0a05\u0a39\u0a3f\u0a28\u0a3f\u0a38\u0a3f \u0a1c\u0a32\u0a24\u0a41 \u0a2c\u0a3f\u0a39\u0a3e\u0a07 \u0965","original":"\u0a24\u0a3e\u0a2e\u0a38\u0a3f\u0a32\u0a17\u0a3e\u0a38\u0a26\u0a3e\u0a2b\u0a3f\u0a30\u0a48\u0a05\u0a39\u0a3f\u0a28\u0a3f\u0a38\u0a3f\u0a1c\u0a32\u0a24\u0a41\u0a2c\u0a3f\u0a39\u0a3e\u0a07\u0965","melody_id":23,"author_id":5,"hymn":1452,"page":554,"line":6,"section":"Bihagara - Bihagara Ki Vaar","search":"\u0a24\u0a32\u0a38\u0a2b\u0a05\u0a1c\u0a2c","language_id":54,"translation":{"id":414274,"scripture_id":24370,"text":"Always afflicted with the dark passions of low energy, it wanders around, passing its days and nights burning.","language_id":13,"language":{"id":13,"language":"English","code":"en-US","script":"latn","direction":1,"accuracy":99}},"transliteration":{"id":536119,"scripture_id":24370,"text":"t\u0101mas lag\u0101 sad\u0101 phirai ahinis jalat bih\u0101i .","language_id":69,"language":{"id":69,"language":"Latin","code":null,"script":"latn","direction":1,"accuracy":99}},"melody":{"id":23,"melody":"Bihagara","gurmukhi":"\u0a2c\u0a3f\u0a39\u0a3e\u0a17\u0a5c\u0a3e","description":"The mood of Bihagara is that of extreme sadness and pain, which gives rise to the need to find peace and understanding. The heightened emotional state of sadness is only harnessed by the craving for truth and meaning."},"author":{"id":5,"author":"Guru Amar Das","gurmukhi":"\u0a2e\u0a03 \u0a69","description":"Guru Amar Das [1479 - 1574] was the third Guru of the Sikhs, born at Basarke in Amritsar. His father, Tej Bhan and mother Bakht Kaur were orthodox Hindus. He became the oldest Sikh Guru.<br\/><\/br>Guru Amar Das put an end to tradition of sati, the burning of the widow on her husbands funeral pyre, and encouraged the remarriage of widows. He opened 22 preaching centres called Manjees and founded the town of Goindwal as the headquarters for the Sikh community."},"language":{"id":54,"language":"Gurmukhi","code":"pa","script":"guru","direction":1,"accuracy":99}},{"id":24371,"text":"\u0a1c\u0a4b \u0a24\u0a3f\u0a38\u0a41 \u0a2d\u0a3e\u0a35\u0a48 \u0a38\u0a4b \u0a25\u0a40\u0a10 \u0a15\u0a39\u0a23\u0a3e \u0a15\u0a3f\u0a1b\u0a42 \u0a28 \u0a1c\u0a3e\u0a07 \u0965\u0a67\u0965","original":"\u0a1c\u0a4b\u0a24\u0a3f\u0a38\u0a41\u0a2d\u0a3e\u0a35\u0a48\u0a38\u0a4b\u0a25\u0a40\u0a10\u0a15\u0a39\u0a23\u0a3e\u0a15\u0a3f\u0a1b\u0a42\u0a28\u0a1c\u0a3e\u0a07\u0965\u0a67\u0965","melody_id":23,"author_id":5,"hymn":1452,"page":554,"line":7,"section":"Bihagara - Bihagara Ki Vaar","search":"\u0a1c\u0a24\u0a2d\u0a38\u0a25\u0a15\u0a15\u0a28\u0a1c","language_id":54,"translation":{"id":414291,"scripture_id":24371,"text":"Whatever pleases Him, comes to pass; no one has any say in this. ||1||","language_id":13,"language":{"id":13,"language":"English","code":"en-US","script":"latn","direction":1,"accuracy":99}},"transliteration":{"id":536141,"scripture_id":24371,"text":"j\u014d tis bh\u0101vai s\u014d th\u012bai kahan\u0101 kish\u016b n j\u0101i .1.","language_id":69,"language":{"id":69,"language":"Latin","code":null,"script":"latn","direction":1,"accuracy":99}},"melody":{"id":23,"melody":"Bihagara","gurmukhi":"\u0a2c\u0a3f\u0a39\u0a3e\u0a17\u0a5c\u0a3e","description":"The mood of Bihagara is that of extreme sadness and pain, which gives rise to the need to find peace and understanding. The heightened emotional state of sadness is only harnessed by the craving for truth and meaning."},"author":{"id":5,"author":"Guru Amar Das","gurmukhi":"\u0a2e\u0a03 \u0a69","description":"Guru Amar Das [1479 - 1574] was the third Guru of the Sikhs, born at Basarke in Amritsar. His father, Tej Bhan and mother Bakht Kaur were orthodox Hindus. He became the oldest Sikh Guru.<br\/><\/br>Guru Amar Das put an end to tradition of sati, the burning of the widow on her husbands funeral pyre, and encouraged the remarriage of widows. He opened 22 preaching centres called Manjees and founded the town of Goindwal as the headquarters for the Sikh community."},"language":{"id":54,"language":"Gurmukhi","code":"pa","script":"guru","direction":1,"accuracy":99}},{"id":24372,"text":"\u0a2e\u0a03 \u0a69 \u0965","original":"\u0a2e\u0a03\u0a69\u0965","melody_id":1,"author_id":2,"hymn":1452,"page":554,"line":7,"section":"Bihagara - Bihagara Ki Vaar","search":"\u0a2e","language_id":54,"translation":{"id":414308,"scripture_id":24372,"text":"Third Mehl:","language_id":13,"language":{"id":13,"language":"English","code":"en-US","script":"latn","direction":1,"accuracy":99}},"transliteration":{"id":536163,"scripture_id":24372,"text":"mah 3 .","language_id":69,"language":{"id":69,"language":"Latin","code":null,"script":"latn","direction":1,"accuracy":99}},"melody":{"id":1,"melody":"None","gurmukhi":"","description":"There is no melody or mood associated with this line, which may be because it is the preamble to the hymn, or is not meant to be read in any particular melody or mood"},"author":{"id":2,"author":"None","gurmukhi":"","description":"There is no author associated with this line, as it may be the preamble to the hymn"},"language":{"id":54,"language":"Gurmukhi","code":"pa","script":"guru","direction":1,"accuracy":99}},{"id":24373,"text":"\u0a38\u0a24\u0a3f\u0a17\u0a41\u0a30\u0a42 \u0a2b\u0a41\u0a30\u0a2e\u0a3e\u0a07\u0a06 \u0a15\u0a3e\u0a30\u0a40 \u0a0f\u0a39 \u0a15\u0a30\u0a47\u0a39\u0a41 \u0965","original":"\u0a38\u0a24\u0a3f\u0a17\u0a41\u0a30\u0a42\u0a2b\u0a41\u0a30\u0a2e\u0a3e\u0a07\u0a06\u0a15\u0a3e\u0a30\u0a40\u0a0f\u0a39\u0a15\u0a30\u0a47\u0a39\u0a41\u0965","melody_id":23,"author_id":5,"hymn":1452,"page":554,"line":7,"section":"Bihagara - Bihagara Ki Vaar","search":"\u0a38\u0a2b\u0a15\u0a72\u0a15","language_id":54,"translation":{"id":414325,"scripture_id":24373,"text":"The True Guru has commanded us to do this:","language_id":13,"language":{"id":13,"language":"English","code":"en-US","script":"latn","direction":1,"accuracy":99}},"transliteration":{"id":536185,"scripture_id":24373,"text":"satigur\u016b phuram\u0101i\u0101 k\u0101r\u012b \u0113h kar\u0113h .","language_id":69,"language":{"id":69,"language":"Latin","code":null,"script":"latn","direction":1,"accuracy":99}},"melody":{"id":23,"melody":"Bihagara","gurmukhi":"\u0a2c\u0a3f\u0a39\u0a3e\u0a17\u0a5c\u0a3e","description":"The mood of Bihagara is that of extreme sadness and pain, which gives rise to the need to find peace and understanding. The heightened emotional state of sadness is only harnessed by the craving for truth and meaning."},"author":{"id":5,"author":"Guru Amar Das","gurmukhi":"\u0a2e\u0a03 \u0a69","description":"Guru Amar Das [1479 - 1574] was the third Guru of the Sikhs, born at Basarke in Amritsar. His father, Tej Bhan and mother Bakht Kaur were orthodox Hindus. He became the oldest Sikh Guru.<br\/><\/br>Guru Amar Das put an end to tradition of sati, the burning of the widow on her husbands funeral pyre, and encouraged the remarriage of widows. He opened 22 preaching centres called Manjees and founded the town of Goindwal as the headquarters for the Sikh community."},"language":{"id":54,"language":"Gurmukhi","code":"pa","script":"guru","direction":1,"accuracy":99}},{"id":24374,"text":"\u0a17\u0a41\u0a30\u0a42 \u0a26\u0a41\u0a06\u0a30\u0a48 \u0a39\u0a4b\u0a07 \u0a15\u0a48 \u0a38\u0a3e\u0a39\u0a3f\u0a2c\u0a41 \u0a38\u0a70\u0a2e\u0a3e\u0a32\u0a47\u0a39\u0a41 \u0965","original":"\u0a17\u0a41\u0a30\u0a42\u0a26\u0a41\u0a06\u0a30\u0a48\u0a39\u0a4b\u0a07\u0a15\u0a48\u0a38\u0a3e\u0a39\u0a3f\u0a2c\u0a41\u0a38\u0a70\u0a2e\u0a3e\u0a32\u0a47\u0a39\u0a41\u0965","melody_id":23,"author_id":5,"hymn":1452,"page":554,"line":7,"section":"Bihagara - Bihagara Ki Vaar","search":"\u0a17\u0a26\u0a39\u0a15\u0a38\u0a38","language_id":54,"translation":{"id":414342,"scripture_id":24374,"text":"through the Guru's Gate, meditate on the Lord Master.","language_id":13,"language":{"id":13,"language":"English","code":"en-US","script":"latn","direction":1,"accuracy":99}},"transliteration":{"id":536207,"scripture_id":24374,"text":"gur\u016b du\u0101rai h\u014di kai s\u0101hib sanm\u0101l\u0113h .","language_id":69,"language":{"id":69,"language":"Latin","code":null,"script":"latn","direction":1,"accuracy":99}},"melody":{"id":23,"melody":"Bihagara","gurmukhi":"\u0a2c\u0a3f\u0a39\u0a3e\u0a17\u0a5c\u0a3e","description":"The mood of Bihagara is that of extreme sadness and pain, which gives rise to the need to find peace and understanding. The heightened emotional state of sadness is only harnessed by the craving for truth and meaning."},"author":{"id":5,"author":"Guru Amar Das","gurmukhi":"\u0a2e\u0a03 \u0a69","description":"Guru Amar Das [1479 - 1574] was the third Guru of the Sikhs, born at Basarke in Amritsar. His father, Tej Bhan and mother Bakht Kaur were orthodox Hindus. He became the oldest Sikh Guru.<br\/><\/br>Guru Amar Das put an end to tradition of sati, the burning of the widow on her husbands funeral pyre, and encouraged the remarriage of widows. He opened 22 preaching centres called Manjees and founded the town of Goindwal as the headquarters for the Sikh community."},"language":{"id":54,"language":"Gurmukhi","code":"pa","script":"guru","direction":1,"accuracy":99}},{"id":24375,"text":"\u0a38\u0a3e\u0a39\u0a3f\u0a2c\u0a41 \u0a38\u0a26\u0a3e \u0a39\u0a1c\u0a42\u0a30\u0a3f \u0a39\u0a48 \u0a2d\u0a30\u0a2e\u0a48 \u0a15\u0a47 \u0a1b\u0a09\u0a5c \u0a15\u0a1f\u0a3f \u0a15\u0a48 \u0a05\u0a70\u0a24\u0a30\u0a3f \u0a1c\u0a4b\u0a24\u0a3f \u0a27\u0a30\u0a47\u0a39\u0a41 \u0965","original":"\u0a38\u0a3e\u0a39\u0a3f\u0a2c\u0a41\u0a38\u0a26\u0a3e\u0a39\u0a1c\u0a42\u0a30\u0a3f\u0a39\u0a48\u0a2d\u0a30\u0a2e\u0a48\u0a15\u0a47\u0a1b\u0a09\u0a5c\u0a15\u0a1f\u0a3f\u0a15\u0a48\u0a05\u0a70\u0a24\u0a30\u0a3f\u0a1c\u0a4b\u0a24\u0a3f\u0a27\u0a30\u0a47\u0a39\u0a41\u0965","melody_id":23,"author_id":5,"hymn":1452,"page":554,"line":8,"section":"Bihagara - Bihagara Ki Vaar","search":"\u0a38\u0a38\u0a39\u0a39\u0a2d\u0a15\u0a1b\u0a15\u0a15\u0a05\u0a1c\u0a27","language_id":54,"translation":{"id":414359,"scripture_id":24375,"text":"The Lord Master is ever-present. He tears away the veil of doubt, and installs His Light within the mind.","language_id":13,"language":{"id":13,"language":"English","code":"en-US","script":"latn","direction":1,"accuracy":99}},"transliteration":{"id":536229,"scripture_id":24375,"text":"s\u0101hib sad\u0101 haj\u016br hai bharamai k\u0113 shaur kat kai antar j\u014dt dhar\u0113h .","language_id":69,"language":{"id":69,"language":"Latin","code":null,"script":"latn","direction":1,"accuracy":99}},"melody":{"id":23,"melody":"Bihagara","gurmukhi":"\u0a2c\u0a3f\u0a39\u0a3e\u0a17\u0a5c\u0a3e","description":"The mood of Bihagara is that of extreme sadness and pain, which gives rise to the need to find peace and understanding. The heightened emotional state of sadness is only harnessed by the craving for truth and meaning."},"author":{"id":5,"author":"Guru Amar Das","gurmukhi":"\u0a2e\u0a03 \u0a69","description":"Guru Amar Das [1479 - 1574] was the third Guru of the Sikhs, born at Basarke in Amritsar. His father, Tej Bhan and mother Bakht Kaur were orthodox Hindus. He became the oldest Sikh Guru.<br\/><\/br>Guru Amar Das put an end to tradition of sati, the burning of the widow on her husbands funeral pyre, and encouraged the remarriage of widows. He opened 22 preaching centres called Manjees and founded the town of Goindwal as the headquarters for the Sikh community."},"language":{"id":54,"language":"Gurmukhi","code":"pa","script":"guru","direction":1,"accuracy":99}},{"id":24376,"text":"\u0a39\u0a30\u0a3f \u0a15\u0a3e \u0a28\u0a3e\u0a2e\u0a41 \u0a05\u0a70\u0a2e\u0a4d\u0a30\u0a3f\u0a24\u0a41 \u0a39\u0a48 \u0a26\u0a3e\u0a30\u0a42 \u0a0f\u0a39\u0a41 \u0a32\u0a3e\u0a0f\u0a39\u0a41 \u0965","original":"\u0a39\u0a30\u0a3f\u0a15\u0a3e\u0a28\u0a3e\u0a2e\u0a41\u0a05\u0a70\u0a2e\u0a4d\u0a30\u0a3f\u0a24\u0a41\u0a39\u0a48\u0a26\u0a3e\u0a30\u0a42\u0a0f\u0a39\u0a41\u0a32\u0a3e\u0a0f\u0a39\u0a41\u0965","melody_id":23,"author_id":5,"hymn":1452,"page":554,"line":9,"section":"Bihagara - Bihagara Ki Vaar","search":"\u0a39\u0a15\u0a28\u0a05\u0a39\u0a26\u0a72\u0a32","language_id":54,"translation":{"id":414376,"scripture_id":24376,"text":"The Name of the Lord is Ambrosial Nectar - take this healing medicine!","language_id":13,"language":{"id":13,"language":"English","code":"en-US","script":"latn","direction":1,"accuracy":99}},"transliteration":{"id":536251,"scripture_id":24376,"text":"har k\u0101 n\u0101m anmrit hai d\u0101r\u016b \u0113h l\u0101\u0113h .","language_id":69,"language":{"id":69,"language":"Latin","code":null,"script":"latn","direction":1,"accuracy":99}},"melody":{"id":23,"melody":"Bihagara","gurmukhi":"\u0a2c\u0a3f\u0a39\u0a3e\u0a17\u0a5c\u0a3e","description":"The mood of Bihagara is that of extreme sadness and pain, which gives rise to the need to find peace and understanding. The heightened emotional state of sadness is only harnessed by the craving for truth and meaning."},"author":{"id":5,"author":"Guru Amar Das","gurmukhi":"\u0a2e\u0a03 \u0a69","description":"Guru Amar Das [1479 - 1574] was the third Guru of the Sikhs, born at Basarke in Amritsar. His father, Tej Bhan and mother Bakht Kaur were orthodox Hindus. He became the oldest Sikh Guru.<br\/><\/br>Guru Amar Das put an end to tradition of sati, the burning of the widow on her husbands funeral pyre, and encouraged the remarriage of widows. He opened 22 preaching centres called Manjees and founded the town of Goindwal as the headquarters for the Sikh community."},"language":{"id":54,"language":"Gurmukhi","code":"pa","script":"guru","direction":1,"accuracy":99}},{"id":24377,"text":"\u0a38\u0a24\u0a3f\u0a17\u0a41\u0a30 \u0a15\u0a3e \u0a2d\u0a3e\u0a23\u0a3e \u0a1a\u0a3f\u0a24\u0a3f \u0a30\u0a16\u0a39\u0a41 \u0a38\u0a70\u0a1c\u0a2e\u0a41 \u0a38\u0a1a\u0a3e \u0a28\u0a47\u0a39\u0a41 \u0965","original":"\u0a38\u0a24\u0a3f\u0a17\u0a41\u0a30\u0a15\u0a3e\u0a2d\u0a3e\u0a23\u0a3e\u0a1a\u0a3f\u0a24\u0a3f\u0a30\u0a16\u0a39\u0a41\u0a38\u0a70\u0a1c\u0a2e\u0a41\u0a38\u0a1a\u0a3e\u0a28\u0a47\u0a39\u0a41\u0965","melody_id":23,"author_id":5,"hymn":1452,"page":554,"line":9,"section":"Bihagara - Bihagara Ki Vaar","search":"\u0a38\u0a15\u0a2d\u0a1a\u0a30\u0a38\u0a38\u0a28","language_id":54,"translation":{"id":414393,"scripture_id":24377,"text":"Enshrine the Will of the True Guru in your consciousness, and make the True Lord's Love your self-discipline.","language_id":13,"language":{"id":13,"language":"English","code":"en-US","script":"latn","direction":1,"accuracy":99}},"transliteration":{"id":536273,"scripture_id":24377,"text":"satigur k\u0101 bh\u0101n\u0101 chit rakhah sanjam sach\u0101 n\u0113h .","language_id":69,"language":{"id":69,"language":"Latin","code":null,"script":"latn","direction":1,"accuracy":99}},"melody":{"id":23,"melody":"Bihagara","gurmukhi":"\u0a2c\u0a3f\u0a39\u0a3e\u0a17\u0a5c\u0a3e","description":"The mood of Bihagara is that of extreme sadness and pain, which gives rise to the need to find peace and understanding. The heightened emotional state of sadness is only harnessed by the craving for truth and meaning."},"author":{"id":5,"author":"Guru Amar Das","gurmukhi":"\u0a2e\u0a03 \u0a69","description":"Guru Amar Das [1479 - 1574] was the third Guru of the Sikhs, born at Basarke in Amritsar. His father, Tej Bhan and mother Bakht Kaur were orthodox Hindus. He became the oldest Sikh Guru.<br\/><\/br>Guru Amar Das put an end to tradition of sati, the burning of the widow on her husbands funeral pyre, and encouraged the remarriage of widows. He opened 22 preaching centres called Manjees and founded the town of Goindwal as the headquarters for the Sikh community."},"language":{"id":54,"language":"Gurmukhi","code":"pa","script":"guru","direction":1,"accuracy":99}},{"id":24378,"text":"\u0a28\u0a3e\u0a28\u0a15 \u0a10\u0a25\u0a48 \u0a38\u0a41\u0a16\u0a48 \u0a05\u0a70\u0a26\u0a30\u0a3f \u0a30\u0a16\u0a38\u0a40 \u0a05\u0a17\u0a48 \u0a39\u0a30\u0a3f \u0a38\u0a3f\u0a09 \u0a15\u0a47\u0a32 \u0a15\u0a30\u0a47\u0a39\u0a41 \u0965\u0a68\u0965","original":"\u0a28\u0a3e\u0a28\u0a15\u0a10\u0a25\u0a48\u0a38\u0a41\u0a16\u0a48\u0a05\u0a70\u0a26\u0a30\u0a3f\u0a30\u0a16\u0a38\u0a40\u0a05\u0a17\u0a48\u0a39\u0a30\u0a3f\u0a38\u0a3f\u0a09\u0a15\u0a47\u0a32\u0a15\u0a30\u0a47\u0a39\u0a41\u0965\u0a68\u0965","melody_id":23,"author_id":5,"hymn":1452,"page":554,"line":9,"section":"Bihagara - Bihagara Ki Vaar","search":"\u0a28\u0a05\u0a38\u0a05\u0a30\u0a05\u0a39\u0a38\u0a15\u0a15","language_id":54,"translation":{"id":414410,"scripture_id":24378,"text":"O Nanak, you shall be kept in peace here, and hereafter, you shall celebrate with the Lord. ||2||","language_id":13,"language":{"id":13,"language":"English","code":"en-US","script":"latn","direction":1,"accuracy":99}},"transliteration":{"id":536295,"scripture_id":24378,"text":"n\u0101nak aithai sukhai andar rakhas\u012b agai har siu k\u0113l kar\u0113h .2.","language_id":69,"language":{"id":69,"language":"Latin","code":null,"script":"latn","direction":1,"accuracy":99}},"melody":{"id":23,"melody":"Bihagara","gurmukhi":"\u0a2c\u0a3f\u0a39\u0a3e\u0a17\u0a5c\u0a3e","description":"The mood of Bihagara is that of extreme sadness and pain, which gives rise to the need to find peace and understanding. The heightened emotional state of sadness is only harnessed by the craving for truth and meaning."},"author":{"id":5,"author":"Guru Amar Das","gurmukhi":"\u0a2e\u0a03 \u0a69","description":"Guru Amar Das [1479 - 1574] was the third Guru of the Sikhs, born at Basarke in Amritsar. His father, Tej Bhan and mother Bakht Kaur were orthodox Hindus. He became the oldest Sikh Guru.<br\/><\/br>Guru Amar Das put an end to tradition of sati, the burning of the widow on her husbands funeral pyre, and encouraged the remarriage of widows. He opened 22 preaching centres called Manjees and founded the town of Goindwal as the headquarters for the Sikh community."},"language":{"id":54,"language":"Gurmukhi","code":"pa","script":"guru","direction":1,"accuracy":99}},{"id":24379,"text":"\u0a2a\u0a09\u0a5c\u0a40 \u0965","original":"\u0a2a\u0a09\u0a5c\u0a40\u0965","melody_id":1,"author_id":2,"hymn":1452,"page":554,"line":10,"section":"Bihagara - Bihagara Ki Vaar","search":"\u0a2a","language_id":54,"translation":{"id":414427,"scripture_id":24379,"text":"Pauree:","language_id":13,"language":{"id":13,"language":"English","code":"en-US","script":"latn","direction":1,"accuracy":99}},"transliteration":{"id":536317,"scripture_id":24379,"text":"paur\u012b .","language_id":69,"language":{"id":69,"language":"Latin","code":null,"script":"latn","direction":1,"accuracy":99}},"melody":{"id":1,"melody":"None","gurmukhi":"","description":"There is no melody or mood associated with this line, which may be because it is the preamble to the hymn, or is not meant to be read in any particular melody or mood"},"author":{"id":2,"author":"None","gurmukhi":"","description":"There is no author associated with this line, as it may be the preamble to the hymn"},"language":{"id":54,"language":"Gurmukhi","code":"pa","script":"guru","direction":1,"accuracy":99}},{"id":24380,"text":"\u0a06\u0a2a\u0a47 \u0a2d\u0a3e\u0a30 \u0a05\u0a20\u0a3e\u0a30\u0a39 \u0a2c\u0a23\u0a38\u0a2a\u0a24\u0a3f \u0a06\u0a2a\u0a47 \u0a39\u0a40 \u0a2b\u0a32 \u0a32\u0a3e\u0a0f \u0965","original":"\u0a06\u0a2a\u0a47\u0a2d\u0a3e\u0a30\u0a05\u0a20\u0a3e\u0a30\u0a39\u0a2c\u0a23\u0a38\u0a2a\u0a24\u0a3f\u0a06\u0a2a\u0a47\u0a39\u0a40\u0a2b\u0a32\u0a32\u0a3e\u0a0f\u0965","melody_id":23,"author_id":5,"hymn":1452,"page":554,"line":10,"section":"Bihagara - Bihagara Ki Vaar","search":"\u0a05\u0a2d\u0a05\u0a2c\u0a05\u0a39\u0a2b\u0a32","language_id":54,"translation":{"id":414444,"scripture_id":24380,"text":"He Himself is the vast variety of Nature, and He Himself makes it bear fruit.","language_id":13,"language":{"id":13,"language":"English","code":"en-US","script":"latn","direction":1,"accuracy":99}},"transliteration":{"id":536339,"scripture_id":24380,"text":"\u0101p\u0113 bh\u0101r ath\u0101rah banasapat \u0101p\u0113 h\u012b phal l\u0101\u0113 .","language_id":69,"language":{"id":69,"language":"Latin","code":null,"script":"latn","direction":1,"accuracy":99}},"melody":{"id":23,"melody":"Bihagara","gurmukhi":"\u0a2c\u0a3f\u0a39\u0a3e\u0a17\u0a5c\u0a3e","description":"The mood of Bihagara is that of extreme sadness and pain, which gives rise to the need to find peace and understanding. The heightened emotional state of sadness is only harnessed by the craving for truth and meaning."},"author":{"id":5,"author":"Guru Amar Das","gurmukhi":"\u0a2e\u0a03 \u0a69","description":"Guru Amar Das [1479 - 1574] was the third Guru of the Sikhs, born at Basarke in Amritsar. His father, Tej Bhan and mother Bakht Kaur were orthodox Hindus. He became the oldest Sikh Guru.<br\/><\/br>Guru Amar Das put an end to tradition of sati, the burning of the widow on her husbands funeral pyre, and encouraged the remarriage of widows. He opened 22 preaching centres called Manjees and founded the town of Goindwal as the headquarters for the Sikh community."},"language":{"id":54,"language":"Gurmukhi","code":"pa","script":"guru","direction":1,"accuracy":99}},{"id":24381,"text":"\u0a06\u0a2a\u0a47 \u0a2e\u0a3e\u0a32\u0a40 \u0a06\u0a2a\u0a3f \u0a38\u0a2d\u0a41 \u0a38\u0a3f\u0a70\u0a1a\u0a48 \u0a06\u0a2a\u0a47 \u0a39\u0a40 \u0a2e\u0a41\u0a39\u0a3f \u0a2a\u0a3e\u0a0f \u0965","original":"\u0a06\u0a2a\u0a47\u0a2e\u0a3e\u0a32\u0a40\u0a06\u0a2a\u0a3f\u0a38\u0a2d\u0a41\u0a38\u0a3f\u0a70\u0a1a\u0a48\u0a06\u0a2a\u0a47\u0a39\u0a40\u0a2e\u0a41\u0a39\u0a3f\u0a2a\u0a3e\u0a0f\u0965","melody_id":23,"author_id":5,"hymn":1452,"page":554,"line":11,"section":"Bihagara - Bihagara Ki Vaar","search":"\u0a05\u0a2e\u0a05\u0a38\u0a38\u0a05\u0a39\u0a2e\u0a2a","language_id":54,"translation":{"id":414461,"scripture_id":24381,"text":"He Himself is the Gardener, He Himself irrigates all the plants, and He Himself puts them in His mouth.","language_id":13,"language":{"id":13,"language":"English","code":"en-US","script":"latn","direction":1,"accuracy":99}},"transliteration":{"id":536361,"scripture_id":24381,"text":"\u0101p\u0113 m\u0101l\u012b \u0101p sabh sinchai \u0101p\u0113 h\u012b muh p\u0101\u0113 .","language_id":69,"language":{"id":69,"language":"Latin","code":null,"script":"latn","direction":1,"accuracy":99}},"melody":{"id":23,"melody":"Bihagara","gurmukhi":"\u0a2c\u0a3f\u0a39\u0a3e\u0a17\u0a5c\u0a3e","description":"The mood of Bihagara is that of extreme sadness and pain, which gives rise to the need to find peace and understanding. The heightened emotional state of sadness is only harnessed by the craving for truth and meaning."},"author":{"id":5,"author":"Guru Amar Das","gurmukhi":"\u0a2e\u0a03 \u0a69","description":"Guru Amar Das [1479 - 1574] was the third Guru of the Sikhs, born at Basarke in Amritsar. His father, Tej Bhan and mother Bakht Kaur were orthodox Hindus. He became the oldest Sikh Guru.<br\/><\/br>Guru Amar Das put an end to tradition of sati, the burning of the widow on her husbands funeral pyre, and encouraged the remarriage of widows. He opened 22 preaching centres called Manjees and founded the town of Goindwal as the headquarters for the Sikh community."},"language":{"id":54,"language":"Gurmukhi","code":"pa","script":"guru","direction":1,"accuracy":99}},{"id":24382,"text":"\u0a06\u0a2a\u0a47 \u0a15\u0a30\u0a24\u0a3e \u0a06\u0a2a\u0a47 \u0a2d\u0a41\u0a17\u0a24\u0a3e \u0a06\u0a2a\u0a47 \u0a26\u0a47\u0a07 \u0a26\u0a3f\u0a35\u0a3e\u0a0f \u0965","original":"\u0a06\u0a2a\u0a47\u0a15\u0a30\u0a24\u0a3e\u0a06\u0a2a\u0a47\u0a2d\u0a41\u0a17\u0a24\u0a3e\u0a06\u0a2a\u0a47\u0a26\u0a47\u0a07\u0a26\u0a3f\u0a35\u0a3e\u0a0f\u0965","melody_id":23,"author_id":5,"hymn":1452,"page":554,"line":11,"section":"Bihagara - Bihagara Ki Vaar","search":"\u0a05\u0a15\u0a05\u0a2d\u0a05\u0a26\u0a26","language_id":54,"translation":{"id":414478,"scripture_id":24382,"text":"He Himself is the Creator, and He Himself is the Enjoyer; He Himself gives, and causes others to give.","language_id":13,"language":{"id":13,"language":"English","code":"en-US","script":"latn","direction":1,"accuracy":99}},"transliteration":{"id":536383,"scripture_id":24382,"text":"\u0101p\u0113 karat\u0101 \u0101p\u0113 bhugat\u0101 \u0101p\u0113 d\u0113i div\u0101\u0113 .","language_id":69,"language":{"id":69,"language":"Latin","code":null,"script":"latn","direction":1,"accuracy":99}},"melody":{"id":23,"melody":"Bihagara","gurmukhi":"\u0a2c\u0a3f\u0a39\u0a3e\u0a17\u0a5c\u0a3e","description":"The mood of Bihagara is that of extreme sadness and pain, which gives rise to the need to find peace and understanding. The heightened emotional state of sadness is only harnessed by the craving for truth and meaning."},"author":{"id":5,"author":"Guru Amar Das","gurmukhi":"\u0a2e\u0a03 \u0a69","description":"Guru Amar Das [1479 - 1574] was the third Guru of the Sikhs, born at Basarke in Amritsar. His father, Tej Bhan and mother Bakht Kaur were orthodox Hindus. He became the oldest Sikh Guru.<br\/><\/br>Guru Amar Das put an end to tradition of sati, the burning of the widow on her husbands funeral pyre, and encouraged the remarriage of widows. He opened 22 preaching centres called Manjees and founded the town of Goindwal as the headquarters for the Sikh community."},"language":{"id":54,"language":"Gurmukhi","code":"pa","script":"guru","direction":1,"accuracy":99}},{"id":24383,"text":"\u0a06\u0a2a\u0a47 \u0a38\u0a3e\u0a39\u0a3f\u0a2c\u0a41 \u0a06\u0a2a\u0a47 \u0a39\u0a48 \u0a30\u0a3e\u0a16\u0a3e \u0a06\u0a2a\u0a47 \u0a30\u0a39\u0a3f\u0a06 \u0a38\u0a2e\u0a3e\u0a0f \u0965","original":"\u0a06\u0a2a\u0a47\u0a38\u0a3e\u0a39\u0a3f\u0a2c\u0a41\u0a06\u0a2a\u0a47\u0a39\u0a48\u0a30\u0a3e\u0a16\u0a3e\u0a06\u0a2a\u0a47\u0a30\u0a39\u0a3f\u0a06\u0a38\u0a2e\u0a3e\u0a0f\u0965","melody_id":23,"author_id":5,"hymn":1452,"page":554,"line":12,"section":"Bihagara - Bihagara Ki Vaar","search":"\u0a05\u0a38\u0a05\u0a39\u0a30\u0a05\u0a30\u0a38","language_id":54,"translation":{"id":414495,"scripture_id":24383,"text":"He Himself is the Lord and Master, and He Himself is the Protector; He Himself is permeating and pervading everywhere.","language_id":13,"language":{"id":13,"language":"English","code":"en-US","script":"latn","direction":1,"accuracy":99}},"transliteration":{"id":536405,"scripture_id":24383,"text":"\u0101p\u0113 s\u0101hib \u0101p\u0113 hai r\u0101kh\u0101 \u0101p\u0113 rahi\u0101 sam\u0101\u0113 .","language_id":69,"language":{"id":69,"language":"Latin","code":null,"script":"latn","direction":1,"accuracy":99}},"melody":{"id":23,"melody":"Bihagara","gurmukhi":"\u0a2c\u0a3f\u0a39\u0a3e\u0a17\u0a5c\u0a3e","description":"The mood of Bihagara is that of extreme sadness and pain, which gives rise to the need to find peace and understanding. The heightened emotional state of sadness is only harnessed by the craving for truth and meaning."},"author":{"id":5,"author":"Guru Amar Das","gurmukhi":"\u0a2e\u0a03 \u0a69","description":"Guru Amar Das [1479 - 1574] was the third Guru of the Sikhs, born at Basarke in Amritsar. His father, Tej Bhan and mother Bakht Kaur were orthodox Hindus. He became the oldest Sikh Guru.<br\/><\/br>Guru Amar Das put an end to tradition of sati, the burning of the widow on her husbands funeral pyre, and encouraged the remarriage of widows. He opened 22 preaching centres called Manjees and founded the town of Goindwal as the headquarters for the Sikh community."},"language":{"id":54,"language":"Gurmukhi","code":"pa","script":"guru","direction":1,"accuracy":99}},{"id":24384,"text":"\u0a1c\u0a28\u0a41 \u0a28\u0a3e\u0a28\u0a15 \u0a35\u0a21\u0a3f\u0a06\u0a08 \u0a06\u0a16\u0a48 \u0a39\u0a30\u0a3f \u0a15\u0a30\u0a24\u0a47 \u0a15\u0a40 \u0a1c\u0a3f\u0a38 \u0a28\u0a4b \u0a24\u0a3f\u0a32\u0a41 \u0a28 \u0a24\u0a2e\u0a3e\u0a0f \u0965\u0a67\u0a6b\u0965","original":"\u0a1c\u0a28\u0a41\u0a28\u0a3e\u0a28\u0a15\u0a35\u0a21\u0a3f\u0a06\u0a08\u0a06\u0a16\u0a48\u0a39\u0a30\u0a3f\u0a15\u0a30\u0a24\u0a47\u0a15\u0a40\u0a1c\u0a3f\u0a38\u0a28\u0a4b\u0a24\u0a3f\u0a32\u0a41\u0a28\u0a24\u0a2e\u0a3e\u0a0f\u0965\u0a67\u0a6b\u0965","melody_id":23,"author_id":5,"hymn":1452,"page":554,"line":12,"section":"Bihagara - Bihagara Ki Vaar","search":"\u0a1c\u0a28\u0a35\u0a05\u0a39\u0a15\u0a15\u0a1c\u0a28\u0a24\u0a28\u0a24","language_id":54,"translation":{"id":414512,"scripture_id":24384,"text":"Servant Nanak speaks of the greatness of the Lord, the Creator, who has no greed at all. ||15||","language_id":13,"language":{"id":13,"language":"English","code":"en-US","script":"latn","direction":1,"accuracy":99}},"transliteration":{"id":536427,"scripture_id":24384,"text":"jan n\u0101nak vadi\u0101\u012b \u0101khai har karat\u0113 k\u012b jis n\u014d til n tam\u0101\u0113 .15.","language_id":69,"language":{"id":69,"language":"Latin","code":null,"script":"latn","direction":1,"accuracy":99}},"melody":{"id":23,"melody":"Bihagara","gurmukhi":"\u0a2c\u0a3f\u0a39\u0a3e\u0a17\u0a5c\u0a3e","description":"The mood of Bihagara is that of extreme sadness and pain, which gives rise to the need to find peace and understanding. The heightened emotional state of sadness is only harnessed by the craving for truth and meaning."},"author":{"id":5,"author":"Guru Amar Das","gurmukhi":"\u0a2e\u0a03 \u0a69","description":"Guru Amar Das [1479 - 1574] was the third Guru of the Sikhs, born at Basarke in Amritsar. His father, Tej Bhan and mother Bakht Kaur were orthodox Hindus. He became the oldest Sikh Guru.<br\/><\/br>Guru Amar Das put an end to tradition of sati, the burning of the widow on her husbands funeral pyre, and encouraged the remarriage of widows. He opened 22 preaching centres called Manjees and founded the town of Goindwal as the headquarters for the Sikh community."},"language":{"id":54,"language":"Gurmukhi","code":"pa","script":"guru","direction":1,"accuracy":99}},{"id":24385,"text":"\u0a38\u0a32\u0a4b\u0a15 \u0a2e\u0a03 \u0a69 \u0965","original":"\u0a38\u0a32\u0a4b\u0a15\u0a2e\u0a03\u0a69\u0965","melody_id":1,"author_id":2,"hymn":1453,"page":554,"line":13,"section":"Bihagara - Bihagara Ki Vaar","search":"\u0a38\u0a2e","language_id":54,"translation":{"id":414529,"scripture_id":24385,"text":"Shalok, Third Mehl:","language_id":13,"language":{"id":13,"language":"English","code":"en-US","script":"latn","direction":1,"accuracy":99}},"transliteration":{"id":536449,"scripture_id":24385,"text":"sal\u014dk mah 3 .","language_id":69,"language":{"id":69,"language":"Latin","code":null,"script":"latn","direction":1,"accuracy":99}},"melody":{"id":1,"melody":"None","gurmukhi":"","description":"There is no melody or mood associated with this line, which may be because it is the preamble to the hymn, or is not meant to be read in any particular melody or mood"},"author":{"id":2,"author":"None","gurmukhi":"","description":"There is no author associated with this line, as it may be the preamble to the hymn"},"language":{"id":54,"language":"Gurmukhi","code":"pa","script":"guru","direction":1,"accuracy":99}},{"id":24386,"text":"\u0a2e\u0a3e\u0a23\u0a38\u0a41 \u0a2d\u0a30\u0a3f\u0a06 \u0a06\u0a23\u0a3f\u0a06 \u0a2e\u0a3e\u0a23\u0a38\u0a41 \u0a2d\u0a30\u0a3f\u0a06 \u0a06\u0a07 \u0965","original":"\u0a2e\u0a3e\u0a23\u0a38\u0a41\u0a2d\u0a30\u0a3f\u0a06\u0a06\u0a23\u0a3f\u0a06\u0a2e\u0a3e\u0a23\u0a38\u0a41\u0a2d\u0a30\u0a3f\u0a06\u0a06\u0a07\u0965","melody_id":23,"author_id":5,"hymn":1453,"page":554,"line":13,"section":"Bihagara - Bihagara Ki Vaar","search":"\u0a2e\u0a2d\u0a05\u0a2e\u0a2d\u0a05","language_id":54,"translation":{"id":414546,"scripture_id":24386,"text":"One person brings a full bottle, and another fills his cup.","language_id":13,"language":{"id":13,"language":"English","code":"en-US","script":"latn","direction":1,"accuracy":99}},"transliteration":{"id":536471,"scripture_id":24386,"text":"m\u0101nas bhari\u0101 \u0101ni\u0101 m\u0101nas bhari\u0101 \u0101i .","language_id":69,"language":{"id":69,"language":"Latin","code":null,"script":"latn","direction":1,"accuracy":99}},"melody":{"id":23,"melody":"Bihagara","gurmukhi":"\u0a2c\u0a3f\u0a39\u0a3e\u0a17\u0a5c\u0a3e","description":"The mood of Bihagara is that of extreme sadness and pain, which gives rise to the need to find peace and understanding. The heightened emotional state of sadness is only harnessed by the craving for truth and meaning."},"author":{"id":5,"author":"Guru Amar Das","gurmukhi":"\u0a2e\u0a03 \u0a69","description":"Guru Amar Das [1479 - 1574] was the third Guru of the Sikhs, born at Basarke in Amritsar. His father, Tej Bhan and mother Bakht Kaur were orthodox Hindus. He became the oldest Sikh Guru.<br\/><\/br>Guru Amar Das put an end to tradition of sati, the burning of the widow on her husbands funeral pyre, and encouraged the remarriage of widows. He opened 22 preaching centres called Manjees and founded the town of Goindwal as the headquarters for the Sikh community."},"language":{"id":54,"language":"Gurmukhi","code":"pa","script":"guru","direction":1,"accuracy":99}},{"id":24387,"text":"\u0a1c\u0a3f\u0a24\u0a41 \u0a2a\u0a40\u0a24\u0a48 \u0a2e\u0a24\u0a3f \u0a26\u0a42\u0a30\u0a3f \u0a39\u0a4b\u0a07 \u0a2c\u0a30\u0a32\u0a41 \u0a2a\u0a35\u0a48 \u0a35\u0a3f\u0a1a\u0a3f \u0a06\u0a07 \u0965","original":"\u0a1c\u0a3f\u0a24\u0a41\u0a2a\u0a40\u0a24\u0a48\u0a2e\u0a24\u0a3f\u0a26\u0a42\u0a30\u0a3f\u0a39\u0a4b\u0a07\u0a2c\u0a30\u0a32\u0a41\u0a2a\u0a35\u0a48\u0a35\u0a3f\u0a1a\u0a3f\u0a06\u0a07\u0965","melody_id":23,"author_id":5,"hymn":1453,"page":554,"line":14,"section":"Bihagara - Bihagara Ki Vaar","search":"\u0a1c\u0a2a\u0a2e\u0a26\u0a39\u0a2c\u0a2a\u0a35\u0a05","language_id":54,"translation":{"id":414563,"scripture_id":24387,"text":"Drinking the wine, his intelligence departs, and madness enters his mind;","language_id":13,"language":{"id":13,"language":"English","code":"en-US","script":"latn","direction":1,"accuracy":99}},"transliteration":{"id":536493,"scripture_id":24387,"text":"jit p\u012btai mat d\u016br h\u014di baral pavai vich \u0101i .","language_id":69,"language":{"id":69,"language":"Latin","code":null,"script":"latn","direction":1,"accuracy":99}},"melody":{"id":23,"melody":"Bihagara","gurmukhi":"\u0a2c\u0a3f\u0a39\u0a3e\u0a17\u0a5c\u0a3e","description":"The mood of Bihagara is that of extreme sadness and pain, which gives rise to the need to find peace and understanding. The heightened emotional state of sadness is only harnessed by the craving for truth and meaning."},"author":{"id":5,"author":"Guru Amar Das","gurmukhi":"\u0a2e\u0a03 \u0a69","description":"Guru Amar Das [1479 - 1574] was the third Guru of the Sikhs, born at Basarke in Amritsar. His father, Tej Bhan and mother Bakht Kaur were orthodox Hindus. He became the oldest Sikh Guru.<br\/><\/br>Guru Amar Das put an end to tradition of sati, the burning of the widow on her husbands funeral pyre, and encouraged the remarriage of widows. He opened 22 preaching centres called Manjees and founded the town of Goindwal as the headquarters for the Sikh community."},"language":{"id":54,"language":"Gurmukhi","code":"pa","script":"guru","direction":1,"accuracy":99}},{"id":24388,"text":"\u0a06\u0a2a\u0a23\u0a3e \u0a2a\u0a30\u0a3e\u0a07\u0a06 \u0a28 \u0a2a\u0a1b\u0a3e\u0a23\u0a08 \u0a16\u0a38\u0a2e\u0a39\u0a41 \u0a27\u0a15\u0a47 \u0a16\u0a3e\u0a07 \u0965","original":"\u0a06\u0a2a\u0a23\u0a3e\u0a2a\u0a30\u0a3e\u0a07\u0a06\u0a28\u0a2a\u0a1b\u0a3e\u0a23\u0a08\u0a16\u0a38\u0a2e\u0a39\u0a41\u0a27\u0a15\u0a47\u0a16\u0a3e\u0a07\u0965","melody_id":23,"author_id":5,"hymn":1453,"page":554,"line":14,"section":"Bihagara - Bihagara Ki Vaar","search":"\u0a05\u0a2a\u0a28\u0a2a\u0a16\u0a27\u0a16","language_id":54,"translation":{"id":414580,"scripture_id":24388,"text":"he cannot distinguish between his own and others, and he is struck down by his Lord and Master.","language_id":13,"language":{"id":13,"language":"English","code":"en-US","script":"latn","direction":1,"accuracy":99}},"transliteration":{"id":536515,"scripture_id":24388,"text":"\u0101pan\u0101 par\u0101i\u0101 n pash\u0101na\u012b khasamah dhak\u0113 kh\u0101i .","language_id":69,"language":{"id":69,"language":"Latin","code":null,"script":"latn","direction":1,"accuracy":99}},"melody":{"id":23,"melody":"Bihagara","gurmukhi":"\u0a2c\u0a3f\u0a39\u0a3e\u0a17\u0a5c\u0a3e","description":"The mood of Bihagara is that of extreme sadness and pain, which gives rise to the need to find peace and understanding. The heightened emotional state of sadness is only harnessed by the craving for truth and meaning."},"author":{"id":5,"author":"Guru Amar Das","gurmukhi":"\u0a2e\u0a03 \u0a69","description":"Guru Amar Das [1479 - 1574] was the third Guru of the Sikhs, born at Basarke in Amritsar. His father, Tej Bhan and mother Bakht Kaur were orthodox Hindus. He became the oldest Sikh Guru.<br\/><\/br>Guru Amar Das put an end to tradition of sati, the burning of the widow on her husbands funeral pyre, and encouraged the remarriage of widows. He opened 22 preaching centres called Manjees and founded the town of Goindwal as the headquarters for the Sikh community."},"language":{"id":54,"language":"Gurmukhi","code":"pa","script":"guru","direction":1,"accuracy":99}},{"id":24389,"text":"\u0a1c\u0a3f\u0a24\u0a41 \u0a2a\u0a40\u0a24\u0a48 \u0a16\u0a38\u0a2e\u0a41 \u0a35\u0a3f\u0a38\u0a30\u0a48 \u0a26\u0a30\u0a17\u0a39 \u0a2e\u0a3f\u0a32\u0a48 \u0a38\u0a1c\u0a3e\u0a07 \u0965","original":"\u0a1c\u0a3f\u0a24\u0a41\u0a2a\u0a40\u0a24\u0a48\u0a16\u0a38\u0a2e\u0a41\u0a35\u0a3f\u0a38\u0a30\u0a48\u0a26\u0a30\u0a17\u0a39\u0a2e\u0a3f\u0a32\u0a48\u0a38\u0a1c\u0a3e\u0a07\u0965","melody_id":23,"author_id":5,"hymn":1453,"page":554,"line":15,"section":"Bihagara - Bihagara Ki Vaar","search":"\u0a1c\u0a2a\u0a16\u0a35\u0a26\u0a2e\u0a38","language_id":54,"translation":{"id":414597,"scripture_id":24389,"text":"Drinking it, he forgets his Lord and Master, and he is punished in the Court of the Lord.","language_id":13,"language":{"id":13,"language":"English","code":"en-US","script":"latn","direction":1,"accuracy":99}},"transliteration":{"id":536537,"scripture_id":24389,"text":"jit p\u012btai khasam visarai daragah milai saj\u0101i .","language_id":69,"language":{"id":69,"language":"Latin","code":null,"script":"latn","direction":1,"accuracy":99}},"melody":{"id":23,"melody":"Bihagara","gurmukhi":"\u0a2c\u0a3f\u0a39\u0a3e\u0a17\u0a5c\u0a3e","description":"The mood of Bihagara is that of extreme sadness and pain, which gives rise to the need to find peace and understanding. The heightened emotional state of sadness is only harnessed by the craving for truth and meaning."},"author":{"id":5,"author":"Guru Amar Das","gurmukhi":"\u0a2e\u0a03 \u0a69","description":"Guru Amar Das [1479 - 1574] was the third Guru of the Sikhs, born at Basarke in Amritsar. His father, Tej Bhan and mother Bakht Kaur were orthodox Hindus. He became the oldest Sikh Guru.<br\/><\/br>Guru Amar Das put an end to tradition of sati, the burning of the widow on her husbands funeral pyre, and encouraged the remarriage of widows. He opened 22 preaching centres called Manjees and founded the town of Goindwal as the headquarters for the Sikh community."},"language":{"id":54,"language":"Gurmukhi","code":"pa","script":"guru","direction":1,"accuracy":99}},{"id":24390,"text":"\u0a1d\u0a42\u0a20\u0a3e \u0a2e\u0a26\u0a41 \u0a2e\u0a42\u0a32\u0a3f \u0a28 \u0a2a\u0a40\u0a1a\u0a08 \u0a1c\u0a47 \u0a15\u0a3e \u0a2a\u0a3e\u0a30\u0a3f \u0a35\u0a38\u0a3e\u0a07 \u0965","original":"\u0a1d\u0a42\u0a20\u0a3e\u0a2e\u0a26\u0a41\u0a2e\u0a42\u0a32\u0a3f\u0a28\u0a2a\u0a40\u0a1a\u0a08\u0a1c\u0a47\u0a15\u0a3e\u0a2a\u0a3e\u0a30\u0a3f\u0a35\u0a38\u0a3e\u0a07\u0965","melody_id":23,"author_id":5,"hymn":1453,"page":554,"line":15,"section":"Bihagara - Bihagara Ki Vaar","search":"\u0a1d\u0a2e\u0a2e\u0a28\u0a2a\u0a1c\u0a15\u0a2a\u0a35","language_id":54,"translation":{"id":414614,"scripture_id":24390,"text":"Do not drink the false wine at all, if it is in your power.","language_id":13,"language":{"id":13,"language":"English","code":"en-US","script":"latn","direction":1,"accuracy":99}},"transliteration":{"id":536559,"scripture_id":24390,"text":"jh\u016bth\u0101 mad m\u016bl n p\u012bcha\u012b j\u0113 k\u0101 p\u0101r vas\u0101i .","language_id":69,"language":{"id":69,"language":"Latin","code":null,"script":"latn","direction":1,"accuracy":99}},"melody":{"id":23,"melody":"Bihagara","gurmukhi":"\u0a2c\u0a3f\u0a39\u0a3e\u0a17\u0a5c\u0a3e","description":"The mood of Bihagara is that of extreme sadness and pain, which gives rise to the need to find peace and understanding. The heightened emotional state of sadness is only harnessed by the craving for truth and meaning."},"author":{"id":5,"author":"Guru Amar Das","gurmukhi":"\u0a2e\u0a03 \u0a69","description":"Guru Amar Das [1479 - 1574] was the third Guru of the Sikhs, born at Basarke in Amritsar. His father, Tej Bhan and mother Bakht Kaur were orthodox Hindus. He became the oldest Sikh Guru.<br\/><\/br>Guru Amar Das put an end to tradition of sati, the burning of the widow on her husbands funeral pyre, and encouraged the remarriage of widows. He opened 22 preaching centres called Manjees and founded the town of Goindwal as the headquarters for the Sikh community."},"language":{"id":54,"language":"Gurmukhi","code":"pa","script":"guru","direction":1,"accuracy":99}},{"id":24391,"text":"\u0a28\u0a3e\u0a28\u0a15 \u0a28\u0a26\u0a30\u0a40 \u0a38\u0a1a\u0a41 \u0a2e\u0a26\u0a41 \u0a2a\u0a3e\u0a08\u0a10 \u0a38\u0a24\u0a3f\u0a17\u0a41\u0a30\u0a41 \u0a2e\u0a3f\u0a32\u0a48 \u0a1c\u0a3f\u0a38\u0a41 \u0a06\u0a07 \u0965","original":"\u0a28\u0a3e\u0a28\u0a15\u0a28\u0a26\u0a30\u0a40\u0a38\u0a1a\u0a41\u0a2e\u0a26\u0a41\u0a2a\u0a3e\u0a08\u0a10\u0a38\u0a24\u0a3f\u0a17\u0a41\u0a30\u0a41\u0a2e\u0a3f\u0a32\u0a48\u0a1c\u0a3f\u0a38\u0a41\u0a06\u0a07\u0965","melody_id":23,"author_id":5,"hymn":1453,"page":554,"line":16,"section":"Bihagara - Bihagara Ki Vaar","search":"\u0a28\u0a28\u0a38\u0a2e\u0a2a\u0a38\u0a2e\u0a1c\u0a05","language_id":54,"translation":{"id":414631,"scripture_id":24391,"text":"O Nanak, the True Guru comes and meets the mortal; by His Grace, one obtains the True Wine.","language_id":13,"language":{"id":13,"language":"English","code":"en-US","script":"latn","direction":1,"accuracy":99}},"transliteration":{"id":536581,"scripture_id":24391,"text":"n\u0101nak nadar\u012b sach mad p\u0101\u012bai satigur milai jis \u0101i .","language_id":69,"language":{"id":69,"language":"Latin","code":null,"script":"latn","direction":1,"accuracy":99}},"melody":{"id":23,"melody":"Bihagara","gurmukhi":"\u0a2c\u0a3f\u0a39\u0a3e\u0a17\u0a5c\u0a3e","description":"The mood of Bihagara is that of extreme sadness and pain, which gives rise to the need to find peace and understanding. The heightened emotional state of sadness is only harnessed by the craving for truth and meaning."},"author":{"id":5,"author":"Guru Amar Das","gurmukhi":"\u0a2e\u0a03 \u0a69","description":"Guru Amar Das [1479 - 1574] was the third Guru of the Sikhs, born at Basarke in Amritsar. His father, Tej Bhan and mother Bakht Kaur were orthodox Hindus. He became the oldest Sikh Guru.<br\/><\/br>Guru Amar Das put an end to tradition of sati, the burning of the widow on her husbands funeral pyre, and encouraged the remarriage of widows. He opened 22 preaching centres called Manjees and founded the town of Goindwal as the headquarters for the Sikh community."},"language":{"id":54,"language":"Gurmukhi","code":"pa","script":"guru","direction":1,"accuracy":99}},{"id":24392,"text":"\u0a38\u0a26\u0a3e \u0a38\u0a3e\u0a39\u0a3f\u0a2c \u0a15\u0a48 \u0a30\u0a70\u0a17\u0a3f \u0a30\u0a39\u0a48 \u0a2e\u0a39\u0a32\u0a40 \u0a2a\u0a3e\u0a35\u0a48 \u0a25\u0a3e\u0a09 \u0965\u0a67\u0965","original":"\u0a38\u0a26\u0a3e\u0a38\u0a3e\u0a39\u0a3f\u0a2c\u0a15\u0a48\u0a30\u0a70\u0a17\u0a3f\u0a30\u0a39\u0a48\u0a2e\u0a39\u0a32\u0a40\u0a2a\u0a3e\u0a35\u0a48\u0a25\u0a3e\u0a09\u0965\u0a67\u0965","melody_id":23,"author_id":5,"hymn":1453,"page":554,"line":16,"section":"Bihagara - Bihagara Ki Vaar","search":"\u0a38\u0a38\u0a15\u0a30\u0a30\u0a2e\u0a2a\u0a25","language_id":54,"translation":{"id":414648,"scripture_id":24392,"text":"He shall dwell forever in the Love of the Lord Master, and obtain a seat in the Mansion of His Presence. ||1||","language_id":13,"language":{"id":13,"language":"English","code":"en-US","script":"latn","direction":1,"accuracy":99}},"transliteration":{"id":536603,"scripture_id":24392,"text":"sad\u0101 s\u0101hib kai rang rahai mahal\u012b p\u0101vai th\u0101u .1.","language_id":69,"language":{"id":69,"language":"Latin","code":null,"script":"latn","direction":1,"accuracy":99}},"melody":{"id":23,"melody":"Bihagara","gurmukhi":"\u0a2c\u0a3f\u0a39\u0a3e\u0a17\u0a5c\u0a3e","description":"The mood of Bihagara is that of extreme sadness and pain, which gives rise to the need to find peace and understanding. The heightened emotional state of sadness is only harnessed by the craving for truth and meaning."},"author":{"id":5,"author":"Guru Amar Das","gurmukhi":"\u0a2e\u0a03 \u0a69","description":"Guru Amar Das [1479 - 1574] was the third Guru of the Sikhs, born at Basarke in Amritsar. His father, Tej Bhan and mother Bakht Kaur were orthodox Hindus. He became the oldest Sikh Guru.<br\/><\/br>Guru Amar Das put an end to tradition of sati, the burning of the widow on her husbands funeral pyre, and encouraged the remarriage of widows. He opened 22 preaching centres called Manjees and founded the town of Goindwal as the headquarters for the Sikh community."},"language":{"id":54,"language":"Gurmukhi","code":"pa","script":"guru","direction":1,"accuracy":99}},{"id":24393,"text":"\u0a2e\u0a03 \u0a69 \u0965","original":"\u0a2e\u0a03\u0a69\u0965","melody_id":1,"author_id":2,"hymn":1453,"page":554,"line":17,"section":"Bihagara - Bihagara Ki Vaar","search":"\u0a2e","language_id":54,"translation":{"id":414665,"scripture_id":24393,"text":"Third Mehl:","language_id":13,"language":{"id":13,"language":"English","code":"en-US","script":"latn","direction":1,"accuracy":99}},"transliteration":{"id":536625,"scripture_id":24393,"text":"mah 3 .","language_id":69,"language":{"id":69,"language":"Latin","code":null,"script":"latn","direction":1,"accuracy":99}},"melody":{"id":1,"melody":"None","gurmukhi":"","description":"There is no melody or mood associated with this line, which may be because it is the preamble to the hymn, or is not meant to be read in any particular melody or mood"},"author":{"id":2,"author":"None","gurmukhi":"","description":"There is no author associated with this line, as it may be the preamble to the hymn"},"language":{"id":54,"language":"Gurmukhi","code":"pa","script":"guru","direction":1,"accuracy":99}},{"id":24394,"text":"\u0a07\u0a39\u0a41 \u0a1c\u0a17\u0a24\u0a41 \u0a1c\u0a40\u0a35\u0a24\u0a41 \u0a2e\u0a30\u0a48 \u0a1c\u0a3e \u0a07\u0a38 \u0a28\u0a4b \u0a38\u0a4b\u0a1d\u0a40 \u0a39\u0a4b\u0a07 \u0965","original":"\u0a07\u0a39\u0a41\u0a1c\u0a17\u0a24\u0a41\u0a1c\u0a40\u0a35\u0a24\u0a41\u0a2e\u0a30\u0a48\u0a1c\u0a3e\u0a07\u0a38\u0a28\u0a4b\u0a38\u0a4b\u0a1d\u0a40\u0a39\u0a4b\u0a07\u0965","melody_id":23,"author_id":5,"hymn":1453,"page":554,"line":17,"section":"Bihagara - Bihagara Ki Vaar","search":"\u0a72\u0a1c\u0a1c\u0a2e\u0a1c\u0a72\u0a28\u0a38\u0a39","language_id":54,"translation":{"id":414682,"scripture_id":24394,"text":"When this world comes to understand, it remains dead while yet alive.","language_id":13,"language":{"id":13,"language":"English","code":"en-US","script":"latn","direction":1,"accuracy":99}},"transliteration":{"id":536647,"scripture_id":24394,"text":"ih jagat j\u012bvat marai j\u0101 is n\u014d s\u014djh\u012b h\u014di .","language_id":69,"language":{"id":69,"language":"Latin","code":null,"script":"latn","direction":1,"accuracy":99}},"melody":{"id":23,"melody":"Bihagara","gurmukhi":"\u0a2c\u0a3f\u0a39\u0a3e\u0a17\u0a5c\u0a3e","description":"The mood of Bihagara is that of extreme sadness and pain, which gives rise to the need to find peace and understanding. The heightened emotional state of sadness is only harnessed by the craving for truth and meaning."},"author":{"id":5,"author":"Guru Amar Das","gurmukhi":"\u0a2e\u0a03 \u0a69","description":"Guru Amar Das [1479 - 1574] was the third Guru of the Sikhs, born at Basarke in Amritsar. His father, Tej Bhan and mother Bakht Kaur were orthodox Hindus. He became the oldest Sikh Guru.<br\/><\/br>Guru Amar Das put an end to tradition of sati, the burning of the widow on her husbands funeral pyre, and encouraged the remarriage of widows. He opened 22 preaching centres called Manjees and founded the town of Goindwal as the headquarters for the Sikh community."},"language":{"id":54,"language":"Gurmukhi","code":"pa","script":"guru","direction":1,"accuracy":99}},{"id":24395,"text":"\u0a1c\u0a3e \u0a24\u0a3f\u0a28\u0a4d\u0a39\u0a3f \u0a38\u0a35\u0a3e\u0a32\u0a3f\u0a06 \u0a24\u0a3e\u0a02 \u0a38\u0a35\u0a3f \u0a30\u0a39\u0a3f\u0a06 \u0a1c\u0a17\u0a3e\u0a0f \u0a24\u0a3e\u0a02 \u0a38\u0a41\u0a27\u0a3f \u0a39\u0a4b\u0a07 \u0965","original":"\u0a1c\u0a3e\u0a24\u0a3f\u0a28\u0a4d\u0a39\u0a3f\u0a38\u0a35\u0a3e\u0a32\u0a3f\u0a06\u0a24\u0a3e\u0a02\u0a38\u0a35\u0a3f\u0a30\u0a39\u0a3f\u0a06\u0a1c\u0a17\u0a3e\u0a0f\u0a24\u0a3e\u0a02\u0a38\u0a41\u0a27\u0a3f\u0a39\u0a4b\u0a07\u0965","melody_id":23,"author_id":5,"hymn":1453,"page":554,"line":17,"section":"Bihagara - Bihagara Ki Vaar","search":"\u0a1c\u0a24\u0a38\u0a24\u0a38\u0a30\u0a1c\u0a24\u0a38\u0a39","language_id":54,"translation":{"id":414699,"scripture_id":24395,"text":"When the Lord puts him to sleep, he remains asleep; when He wakes him up, he regains consciousness.","language_id":13,"language":{"id":13,"language":"English","code":"en-US","script":"latn","direction":1,"accuracy":99}},"transliteration":{"id":536669,"scripture_id":24395,"text":"j\u0101 tinh sav\u0101li\u0101 t\u0101nh sav rahi\u0101 jag\u0101\u0113 t\u0101nh sudh h\u014di .","language_id":69,"language":{"id":69,"language":"Latin","code":null,"script":"latn","direction":1,"accuracy":99}},"melody":{"id":23,"melody":"Bihagara","gurmukhi":"\u0a2c\u0a3f\u0a39\u0a3e\u0a17\u0a5c\u0a3e","description":"The mood of Bihagara is that of extreme sadness and pain, which gives rise to the need to find peace and understanding. The heightened emotional state of sadness is only harnessed by the craving for truth and meaning."},"author":{"id":5,"author":"Guru Amar Das","gurmukhi":"\u0a2e\u0a03 \u0a69","description":"Guru Amar Das [1479 - 1574] was the third Guru of the Sikhs, born at Basarke in Amritsar. His father, Tej Bhan and mother Bakht Kaur were orthodox Hindus. He became the oldest Sikh Guru.<br\/><\/br>Guru Amar Das put an end to tradition of sati, the burning of the widow on her husbands funeral pyre, and encouraged the remarriage of widows. He opened 22 preaching centres called Manjees and founded the town of Goindwal as the headquarters for the Sikh community."},"language":{"id":54,"language":"Gurmukhi","code":"pa","script":"guru","direction":1,"accuracy":99}},{"id":24396,"text":"\u0a28\u0a3e\u0a28\u0a15 \u0a28\u0a26\u0a30\u0a3f \u0a15\u0a30\u0a47 \u0a1c\u0a47 \u0a06\u0a2a\u0a23\u0a40 \u0a38\u0a24\u0a3f\u0a17\u0a41\u0a30\u0a41 \u0a2e\u0a47\u0a32\u0a48 \u0a38\u0a4b\u0a07 \u0965","original":"\u0a28\u0a3e\u0a28\u0a15\u0a28\u0a26\u0a30\u0a3f\u0a15\u0a30\u0a47\u0a1c\u0a47\u0a06\u0a2a\u0a23\u0a40\u0a38\u0a24\u0a3f\u0a17\u0a41\u0a30\u0a41\u0a2e\u0a47\u0a32\u0a48\u0a38\u0a4b\u0a07\u0965","melody_id":23,"author_id":5,"hymn":1453,"page":554,"line":18,"section":"Bihagara - Bihagara Ki Vaar","search":"\u0a28\u0a28\u0a15\u0a1c\u0a05\u0a38\u0a2e\u0a38","language_id":54,"translation":{"id":414716,"scripture_id":24396,"text":"O Nanak, when the Lord casts His Glance of Grace, He causes him to meet the True Guru.","language_id":13,"language":{"id":13,"language":"English","code":"en-US","script":"latn","direction":1,"accuracy":99}},"transliteration":{"id":536691,"scripture_id":24396,"text":"n\u0101nak nadar kar\u0113 j\u0113 \u0101pan\u012b satigur m\u0113lai s\u014di .","language_id":69,"language":{"id":69,"language":"Latin","code":null,"script":"latn","direction":1,"accuracy":99}},"melody":{"id":23,"melody":"Bihagara","gurmukhi":"\u0a2c\u0a3f\u0a39\u0a3e\u0a17\u0a5c\u0a3e","description":"The mood of Bihagara is that of extreme sadness and pain, which gives rise to the need to find peace and understanding. The heightened emotional state of sadness is only harnessed by the craving for truth and meaning."},"author":{"id":5,"author":"Guru Amar Das","gurmukhi":"\u0a2e\u0a03 \u0a69","description":"Guru Amar Das [1479 - 1574] was the third Guru of the Sikhs, born at Basarke in Amritsar. His father, Tej Bhan and mother Bakht Kaur were orthodox Hindus. He became the oldest Sikh Guru.<br\/><\/br>Guru Amar Das put an end to tradition of sati, the burning of the widow on her husbands funeral pyre, and encouraged the remarriage of widows. He opened 22 preaching centres called Manjees and founded the town of Goindwal as the headquarters for the Sikh community."},"language":{"id":54,"language":"Gurmukhi","code":"pa","script":"guru","direction":1,"accuracy":99}},{"id":24397,"text":"\u0a17\u0a41\u0a30 \u0a2a\u0a4d\u0a30\u0a38\u0a3e\u0a26\u0a3f \u0a1c\u0a40\u0a35\u0a24\u0a41 \u0a2e\u0a30\u0a48 \u0a24\u0a3e \u0a2b\u0a3f\u0a30\u0a3f \u0a2e\u0a30\u0a23\u0a41 \u0a28 \u0a39\u0a4b\u0a07 \u0965\u0a68\u0965","original":"\u0a17\u0a41\u0a30\u0a2a\u0a4d\u0a30\u0a38\u0a3e\u0a26\u0a3f\u0a1c\u0a40\u0a35\u0a24\u0a41\u0a2e\u0a30\u0a48\u0a24\u0a3e\u0a2b\u0a3f\u0a30\u0a3f\u0a2e\u0a30\u0a23\u0a41\u0a28\u0a39\u0a4b\u0a07\u0965\u0a68\u0965","melody_id":23,"author_id":5,"hymn":1453,"page":554,"line":18,"section":"Bihagara - Bihagara Ki Vaar","search":"\u0a17\u0a2a\u0a1c\u0a2e\u0a24\u0a2b\u0a2e\u0a28\u0a39","language_id":54,"translation":{"id":414733,"scripture_id":24397,"text":"By Guru's Grace, remain dead while yet alive, and you shall not have to die again. ||2||","language_id":13,"language":{"id":13,"language":"English","code":"en-US","script":"latn","direction":1,"accuracy":99}},"transliteration":{"id":536713,"scripture_id":24397,"text":"gur pras\u0101d j\u012bvat marai t\u0101 phir maran n h\u014di .2.","language_id":69,"language":{"id":69,"language":"Latin","code":null,"script":"latn","direction":1,"accuracy":99}},"melody":{"id":23,"melody":"Bihagara","gurmukhi":"\u0a2c\u0a3f\u0a39\u0a3e\u0a17\u0a5c\u0a3e","description":"The mood of Bihagara is that of extreme sadness and pain, which gives rise to the need to find peace and understanding. The heightened emotional state of sadness is only harnessed by the craving for truth and meaning."},"author":{"id":5,"author":"Guru Amar Das","gurmukhi":"\u0a2e\u0a03 \u0a69","description":"Guru Amar Das [1479 - 1574] was the third Guru of the Sikhs, born at Basarke in Amritsar. His father, Tej Bhan and mother Bakht Kaur were orthodox Hindus. He became the oldest Sikh Guru.<br\/><\/br>Guru Amar Das put an end to tradition of sati, the burning of the widow on her husbands funeral pyre, and encouraged the remarriage of widows. He opened 22 preaching centres called Manjees and founded the town of Goindwal as the headquarters for the Sikh community."},"language":{"id":54,"language":"Gurmukhi","code":"pa","script":"guru","direction":1,"accuracy":99}},{"id":24398,"text":"\u0a2a\u0a09\u0a5c\u0a40 \u0965","original":"\u0a2a\u0a09\u0a5c\u0a40\u0965","melody_id":1,"author_id":2,"hymn":1453,"page":554,"line":19,"section":"Bihagara - Bihagara Ki Vaar","search":"\u0a2a","language_id":54,"translation":{"id":414750,"scripture_id":24398,"text":"Pauree: ","language_id":13,"language":{"id":13,"language":"English","code":"en-US","script":"latn","direction":1,"accuracy":99}},"transliteration":{"id":536735,"scripture_id":24398,"text":"paur\u012b .","language_id":69,"language":{"id":69,"language":"Latin","code":null,"script":"latn","direction":1,"accuracy":99}},"melody":{"id":1,"melody":"None","gurmukhi":"","description":"There is no melody or mood associated with this line, which may be because it is the preamble to the hymn, or is not meant to be read in any particular melody or mood"},"author":{"id":2,"author":"None","gurmukhi":"","description":"There is no author associated with this line, as it may be the preamble to the hymn"},"language":{"id":54,"language":"Gurmukhi","code":"pa","script":"guru","direction":1,"accuracy":99}},{"id":24399,"text":"\u0a1c\u0a3f\u0a38 \u0a26\u0a3e \u0a15\u0a40\u0a24\u0a3e \u0a38\u0a2d\u0a41 \u0a15\u0a3f\u0a1b\u0a41 \u0a39\u0a4b\u0a35\u0a48 \u0a24\u0a3f\u0a38 \u0a28\u0a4b \u0a2a\u0a30\u0a35\u0a3e\u0a39 \u0a28\u0a3e\u0a39\u0a40 \u0a15\u0a3f\u0a38\u0a48 \u0a15\u0a47\u0a30\u0a40 \u0965","original":"\u0a1c\u0a3f\u0a38\u0a26\u0a3e\u0a15\u0a40\u0a24\u0a3e\u0a38\u0a2d\u0a41\u0a15\u0a3f\u0a1b\u0a41\u0a39\u0a4b\u0a35\u0a48\u0a24\u0a3f\u0a38\u0a28\u0a4b\u0a2a\u0a30\u0a35\u0a3e\u0a39\u0a28\u0a3e\u0a39\u0a40\u0a15\u0a3f\u0a38\u0a48\u0a15\u0a47\u0a30\u0a40\u0965","melody_id":23,"author_id":5,"hymn":1453,"page":554,"line":19,"section":"Bihagara - Bihagara Ki Vaar","search":"\u0a1c\u0a26\u0a15\u0a38\u0a15\u0a39\u0a24\u0a28\u0a2a\u0a28\u0a15\u0a15","language_id":54,"translation":{"id":414767,"scripture_id":24399,"text":"By His doing, everything happens; what does He care for anyone else?","language_id":13,"language":{"id":13,"language":"English","code":"en-US","script":"latn","direction":1,"accuracy":99}},"transliteration":{"id":536757,"scripture_id":24399,"text":"jis d\u0101 k\u012bt\u0101 sabh kish h\u014dvai tis n\u014d parav\u0101h n\u0101h\u012b kisai k\u0113r\u012b .","language_id":69,"language":{"id":69,"language":"Latin","code":null,"script":"latn","direction":1,"accuracy":99}},"melody":{"id":23,"melody":"Bihagara","gurmukhi":"\u0a2c\u0a3f\u0a39\u0a3e\u0a17\u0a5c\u0a3e","description":"The mood of Bihagara is that of extreme sadness and pain, which gives rise to the need to find peace and understanding. The heightened emotional state of sadness is only harnessed by the craving for truth and meaning."},"author":{"id":5,"author":"Guru Amar Das","gurmukhi":"\u0a2e\u0a03 \u0a69","description":"Guru Amar Das [1479 - 1574] was the third Guru of the Sikhs, born at Basarke in Amritsar. His father, Tej Bhan and mother Bakht Kaur were orthodox Hindus. He became the oldest Sikh Guru.<br\/><\/br>Guru Amar Das put an end to tradition of sati, the burning of the widow on her husbands funeral pyre, and encouraged the remarriage of widows. He opened 22 preaching centres called Manjees and founded the town of Goindwal as the headquarters for the Sikh community."},"language":{"id":54,"language":"Gurmukhi","code":"pa","script":"guru","direction":1,"accuracy":99}},{"id":24400,"text":"\u0a39\u0a30\u0a3f \u0a1c\u0a40\u0a09 \u0a24\u0a47\u0a30\u0a3e \u0a26\u0a3f\u0a24\u0a3e \u0a38\u0a2d\u0a41 \u0a15\u0a4b \u0a16\u0a3e\u0a35\u0a48 \u0a38\u0a2d \u0a2e\u0a41\u0a39\u0a24\u0a3e\u0a1c\u0a40 \u0a15\u0a22\u0a48 \u0a24\u0a47\u0a30\u0a40 \u0965","original":"\u0a39\u0a30\u0a3f\u0a1c\u0a40\u0a09\u0a24\u0a47\u0a30\u0a3e\u0a26\u0a3f\u0a24\u0a3e\u0a38\u0a2d\u0a41\u0a15\u0a4b\u0a16\u0a3e\u0a35\u0a48\u0a38\u0a2d\u0a2e\u0a41\u0a39\u0a24\u0a3e\u0a1c\u0a40\u0a15\u0a22\u0a48\u0a24\u0a47\u0a30\u0a40\u0965","melody_id":23,"author_id":5,"hymn":1453,"page":554,"line":19,"section":"Bihagara - Bihagara Ki Vaar","search":"\u0a39\u0a1c\u0a24\u0a26\u0a38\u0a15\u0a16\u0a38\u0a2e\u0a15\u0a24","language_id":54,"translation":{"id":414784,"scripture_id":24400,"text":"O Dear Lord, everyone eats whatever You give - all are subservient to You.","language_id":13,"language":{"id":13,"language":"English","code":"en-US","script":"latn","direction":1,"accuracy":99}},"transliteration":{"id":536779,"scripture_id":24400,"text":"har j\u012bu t\u0113r\u0101 dit\u0101 sabh k\u014d kh\u0101vai sabh muhat\u0101j\u012b kadhai t\u0113r\u012b .","language_id":69,"language":{"id":69,"language":"Latin","code":null,"script":"latn","direction":1,"accuracy":99}},"melody":{"id":23,"melody":"Bihagara","gurmukhi":"\u0a2c\u0a3f\u0a39\u0a3e\u0a17\u0a5c\u0a3e","description":"The mood of Bihagara is that of extreme sadness and pain, which gives rise to the need to find peace and understanding. The heightened emotional state of sadness is only harnessed by the craving for truth and meaning."},"author":{"id":5,"author":"Guru Amar Das","gurmukhi":"\u0a2e\u0a03 \u0a69","description":"Guru Amar Das [1479 - 1574] was the third Guru of the Sikhs, born at Basarke in Amritsar. His father, Tej Bhan and mother Bakht Kaur were orthodox Hindus. He became the oldest Sikh Guru.<br\/><\/br>Guru Amar Das put an end to tradition of sati, the burning of the widow on her husbands funeral pyre, and encouraged the remarriage of widows. He opened 22 preaching centres called Manjees and founded the town of Goindwal as the headquarters for the Sikh community."},"language":{"id":54,"language":"Gurmukhi","code":"pa","script":"guru","direction":1,"accuracy":99}}]