[{"id":58361,"text":"\u0a24\u0a3e\u0a38\u0a41 \u0a2a\u0a1f\u0a70\u0a24\u0a30 \u0a28 \u0a2a\u0a41\u0a1c\u0a48 \u0a39\u0a30\u0a3f \u0a1c\u0a28 \u0a15\u0a40 \u0a2a\u0a28\u0a3f\u0a39\u0a3e\u0a30\u0a3f \u0965\u0a67\u0a6b\u0a6f\u0965","original":"\u0a24\u0a3e\u0a38\u0a41\u0a2a\u0a1f\u0a70\u0a24\u0a30\u0a28\u0a2a\u0a41\u0a1c\u0a48\u0a39\u0a30\u0a3f\u0a1c\u0a28\u0a15\u0a40\u0a2a\u0a28\u0a3f\u0a39\u0a3e\u0a30\u0a3f\u0965\u0a67\u0a6b\u0a6f\u0965","melody_id":1,"author_id":7,"hymn":3563,"page":1373,"line":1,"section":"Salok Bhagat Kabeer (Verses Of Saint Kabeer)","search":"\u0a24\u0a2a\u0a28\u0a2a\u0a39\u0a1c\u0a15\u0a2a","language_id":54,"translation":{"id":992121,"scripture_id":58361,"text":"But she is not equal to the water-carrier of the Lord's humble servant. ||159||","language_id":13,"language":{"id":13,"language":"English","code":"en-US","script":"latn","direction":1,"accuracy":99}},"transliteration":{"id":1283921,"scripture_id":58361,"text":"t\u0101s patantar n pujai har jan k\u012b panih\u0101r .159.","language_id":69,"language":{"id":69,"language":"Latin","code":null,"script":"latn","direction":1,"accuracy":99}},"melody":{"id":1,"melody":"None","gurmukhi":"","description":"There is no melody or mood associated with this line, which may be because it is the preamble to the hymn, or is not meant to be read in any particular melody or mood"},"author":{"id":7,"author":"Saint Kabir","gurmukhi":"\u0a2d\u0a17\u0a24 \u0a15\u0a2c\u0a40\u0a30","description":"Saint Kabir [1440 - 1518] was a Muslim mystic born in Varanasi in India, whose 541 hymns are included in the Guru Granth Sahib. His writings about God are full of love and devotion, very direct and striking in appeal.<br\/><br\/>The birth of Kabir remains to this day shrouded in mystery and legend. Authorities disagree on both when he was born and who his parents were. One legend proclaims a divine virginal birth. His mother was reputed to have been of the Brahman caste and to have become pregnant after a visit to a Hindu shrine.<br\/><br\/>Because she was unwed, she abandoned Kabir, who was found and adopted by a Muslim weaver. That his early life began as a Muslim there is no doubt, although he later became influenced by the Hindu ascetic, Ramananda, who he accepted as his Guru."},"language":{"id":54,"language":"Gurmukhi","code":"pa","script":"guru","direction":1,"accuracy":99}},{"id":58362,"text":"\u0a15\u0a2c\u0a40\u0a30 \u0a28\u0a4d\u0a30\u0a3f\u0a2a \u0a28\u0a3e\u0a30\u0a40 \u0a15\u0a3f\u0a09 \u0a28\u0a3f\u0a70\u0a26\u0a40\u0a10 \u0a15\u0a3f\u0a09 \u0a39\u0a30\u0a3f \u0a1a\u0a47\u0a30\u0a40 \u0a15\u0a09 \u0a2e\u0a3e\u0a28\u0a41 \u0965","original":"\u0a15\u0a2c\u0a40\u0a30\u0a28\u0a4d\u0a30\u0a3f\u0a2a\u0a28\u0a3e\u0a30\u0a40\u0a15\u0a3f\u0a09\u0a28\u0a3f\u0a70\u0a26\u0a40\u0a10\u0a15\u0a3f\u0a09\u0a39\u0a30\u0a3f\u0a1a\u0a47\u0a30\u0a40\u0a15\u0a09\u0a2e\u0a3e\u0a28\u0a41\u0965","melody_id":1,"author_id":7,"hymn":3563,"page":1373,"line":2,"section":"Salok Bhagat Kabeer (Verses Of Saint Kabeer)","search":"\u0a15\u0a28\u0a28\u0a15\u0a28\u0a15\u0a39\u0a1a\u0a15\u0a2e","language_id":54,"translation":{"id":992138,"scripture_id":58362,"text":"Kabeer, why do you slander the wife of the king? Why do you honor the slave of the Lord?","language_id":13,"language":{"id":13,"language":"English","code":"en-US","script":"latn","direction":1,"accuracy":99}},"transliteration":{"id":1283943,"scripture_id":58362,"text":"kab\u012br nrip n\u0101r\u012b kiu nind\u012bai kiu har ch\u0113r\u012b kau m\u0101n .","language_id":69,"language":{"id":69,"language":"Latin","code":null,"script":"latn","direction":1,"accuracy":99}},"melody":{"id":1,"melody":"None","gurmukhi":"","description":"There is no melody or mood associated with this line, which may be because it is the preamble to the hymn, or is not meant to be read in any particular melody or mood"},"author":{"id":7,"author":"Saint Kabir","gurmukhi":"\u0a2d\u0a17\u0a24 \u0a15\u0a2c\u0a40\u0a30","description":"Saint Kabir [1440 - 1518] was a Muslim mystic born in Varanasi in India, whose 541 hymns are included in the Guru Granth Sahib. His writings about God are full of love and devotion, very direct and striking in appeal.<br\/><br\/>The birth of Kabir remains to this day shrouded in mystery and legend. Authorities disagree on both when he was born and who his parents were. One legend proclaims a divine virginal birth. His mother was reputed to have been of the Brahman caste and to have become pregnant after a visit to a Hindu shrine.<br\/><br\/>Because she was unwed, she abandoned Kabir, who was found and adopted by a Muslim weaver. That his early life began as a Muslim there is no doubt, although he later became influenced by the Hindu ascetic, Ramananda, who he accepted as his Guru."},"language":{"id":54,"language":"Gurmukhi","code":"pa","script":"guru","direction":1,"accuracy":99}},{"id":58363,"text":"\u0a13\u0a39 \u0a2e\u0a3e\u0a02\u0a17 \u0a38\u0a35\u0a3e\u0a30\u0a48 \u0a2c\u0a3f\u0a16\u0a48 \u0a15\u0a09 \u0a13\u0a39 \u0a38\u0a3f\u0a2e\u0a30\u0a48 \u0a39\u0a30\u0a3f \u0a28\u0a3e\u0a2e\u0a41 \u0965\u0a67\u0a6c\u0a66\u0965","original":"\u0a13\u0a39\u0a2e\u0a3e\u0a02\u0a17\u0a38\u0a35\u0a3e\u0a30\u0a48\u0a2c\u0a3f\u0a16\u0a48\u0a15\u0a09\u0a13\u0a39\u0a38\u0a3f\u0a2e\u0a30\u0a48\u0a39\u0a30\u0a3f\u0a28\u0a3e\u0a2e\u0a41\u0965\u0a67\u0a6c\u0a66\u0965","melody_id":1,"author_id":7,"hymn":3563,"page":1373,"line":2,"section":"Salok Bhagat Kabeer (Verses Of Saint Kabeer)","search":"\u0a73\u0a2e\u0a38\u0a2c\u0a15\u0a73\u0a38\u0a39\u0a28","language_id":54,"translation":{"id":992155,"scripture_id":58363,"text":"Because one combs her hair for corruption, while the other remembers the Name of the Lord. ||160||","language_id":13,"language":{"id":13,"language":"English","code":"en-US","script":"latn","direction":1,"accuracy":99}},"transliteration":{"id":1283965,"scripture_id":58363,"text":"\u014dh m\u0101nhg sav\u0101rai bikhai kau \u014dh simarai har n\u0101m .160.","language_id":69,"language":{"id":69,"language":"Latin","code":null,"script":"latn","direction":1,"accuracy":99}},"melody":{"id":1,"melody":"None","gurmukhi":"","description":"There is no melody or mood associated with this line, which may be because it is the preamble to the hymn, or is not meant to be read in any particular melody or mood"},"author":{"id":7,"author":"Saint Kabir","gurmukhi":"\u0a2d\u0a17\u0a24 \u0a15\u0a2c\u0a40\u0a30","description":"Saint Kabir [1440 - 1518] was a Muslim mystic born in Varanasi in India, whose 541 hymns are included in the Guru Granth Sahib. His writings about God are full of love and devotion, very direct and striking in appeal.<br\/><br\/>The birth of Kabir remains to this day shrouded in mystery and legend. Authorities disagree on both when he was born and who his parents were. One legend proclaims a divine virginal birth. His mother was reputed to have been of the Brahman caste and to have become pregnant after a visit to a Hindu shrine.<br\/><br\/>Because she was unwed, she abandoned Kabir, who was found and adopted by a Muslim weaver. That his early life began as a Muslim there is no doubt, although he later became influenced by the Hindu ascetic, Ramananda, who he accepted as his Guru."},"language":{"id":54,"language":"Gurmukhi","code":"pa","script":"guru","direction":1,"accuracy":99}},{"id":58364,"text":"\u0a15\u0a2c\u0a40\u0a30 \u0a25\u0a42\u0a28\u0a40 \u0a2a\u0a3e\u0a08 \u0a25\u0a3f\u0a24\u0a3f \u0a2d\u0a08 \u0a38\u0a24\u0a3f\u0a17\u0a41\u0a30 \u0a2c\u0a70\u0a27\u0a40 \u0a27\u0a40\u0a30 \u0965","original":"\u0a15\u0a2c\u0a40\u0a30\u0a25\u0a42\u0a28\u0a40\u0a2a\u0a3e\u0a08\u0a25\u0a3f\u0a24\u0a3f\u0a2d\u0a08\u0a38\u0a24\u0a3f\u0a17\u0a41\u0a30\u0a2c\u0a70\u0a27\u0a40\u0a27\u0a40\u0a30\u0965","melody_id":1,"author_id":7,"hymn":3563,"page":1373,"line":3,"section":"Salok Bhagat Kabeer (Verses Of Saint Kabeer)","search":"\u0a15\u0a25\u0a2a\u0a25\u0a2d\u0a38\u0a2c\u0a27","language_id":54,"translation":{"id":992172,"scripture_id":58364,"text":"Kabeer, with the Support of the Lord's Pillar, I have become steady and stable.","language_id":13,"language":{"id":13,"language":"English","code":"en-US","script":"latn","direction":1,"accuracy":99}},"transliteration":{"id":1283987,"scripture_id":58364,"text":"kab\u012br th\u016bn\u012b p\u0101\u012b thit bha\u012b satigur bandh\u012b dh\u012br .","language_id":69,"language":{"id":69,"language":"Latin","code":null,"script":"latn","direction":1,"accuracy":99}},"melody":{"id":1,"melody":"None","gurmukhi":"","description":"There is no melody or mood associated with this line, which may be because it is the preamble to the hymn, or is not meant to be read in any particular melody or mood"},"author":{"id":7,"author":"Saint Kabir","gurmukhi":"\u0a2d\u0a17\u0a24 \u0a15\u0a2c\u0a40\u0a30","description":"Saint Kabir [1440 - 1518] was a Muslim mystic born in Varanasi in India, whose 541 hymns are included in the Guru Granth Sahib. His writings about God are full of love and devotion, very direct and striking in appeal.<br\/><br\/>The birth of Kabir remains to this day shrouded in mystery and legend. Authorities disagree on both when he was born and who his parents were. One legend proclaims a divine virginal birth. His mother was reputed to have been of the Brahman caste and to have become pregnant after a visit to a Hindu shrine.<br\/><br\/>Because she was unwed, she abandoned Kabir, who was found and adopted by a Muslim weaver. That his early life began as a Muslim there is no doubt, although he later became influenced by the Hindu ascetic, Ramananda, who he accepted as his Guru."},"language":{"id":54,"language":"Gurmukhi","code":"pa","script":"guru","direction":1,"accuracy":99}},{"id":58365,"text":"\u0a15\u0a2c\u0a40\u0a30 \u0a39\u0a40\u0a30\u0a3e \u0a2c\u0a28\u0a1c\u0a3f\u0a06 \u0a2e\u0a3e\u0a28 \u0a38\u0a30\u0a4b\u0a35\u0a30 \u0a24\u0a40\u0a30 \u0965\u0a67\u0a6c\u0a67\u0965","original":"\u0a15\u0a2c\u0a40\u0a30\u0a39\u0a40\u0a30\u0a3e\u0a2c\u0a28\u0a1c\u0a3f\u0a06\u0a2e\u0a3e\u0a28\u0a38\u0a30\u0a4b\u0a35\u0a30\u0a24\u0a40\u0a30\u0965\u0a67\u0a6c\u0a67\u0965","melody_id":1,"author_id":7,"hymn":3563,"page":1373,"line":3,"section":"Salok Bhagat Kabeer (Verses Of Saint Kabeer)","search":"\u0a15\u0a39\u0a2c\u0a2e\u0a38\u0a24","language_id":54,"translation":{"id":992189,"scripture_id":58365,"text":"The True Guru has given me courage. Kabeer, I have purchased the diamond, on the banks of the Mansarovar Lake. ||161||","language_id":13,"language":{"id":13,"language":"English","code":"en-US","script":"latn","direction":1,"accuracy":99}},"transliteration":{"id":1284009,"scripture_id":58365,"text":"kab\u012br h\u012br\u0101 banaji\u0101 m\u0101n sar\u014dvar t\u012br .161.","language_id":69,"language":{"id":69,"language":"Latin","code":null,"script":"latn","direction":1,"accuracy":99}},"melody":{"id":1,"melody":"None","gurmukhi":"","description":"There is no melody or mood associated with this line, which may be because it is the preamble to the hymn, or is not meant to be read in any particular melody or mood"},"author":{"id":7,"author":"Saint Kabir","gurmukhi":"\u0a2d\u0a17\u0a24 \u0a15\u0a2c\u0a40\u0a30","description":"Saint Kabir [1440 - 1518] was a Muslim mystic born in Varanasi in India, whose 541 hymns are included in the Guru Granth Sahib. His writings about God are full of love and devotion, very direct and striking in appeal.<br\/><br\/>The birth of Kabir remains to this day shrouded in mystery and legend. Authorities disagree on both when he was born and who his parents were. One legend proclaims a divine virginal birth. His mother was reputed to have been of the Brahman caste and to have become pregnant after a visit to a Hindu shrine.<br\/><br\/>Because she was unwed, she abandoned Kabir, who was found and adopted by a Muslim weaver. That his early life began as a Muslim there is no doubt, although he later became influenced by the Hindu ascetic, Ramananda, who he accepted as his Guru."},"language":{"id":54,"language":"Gurmukhi","code":"pa","script":"guru","direction":1,"accuracy":99}},{"id":58366,"text":"\u0a15\u0a2c\u0a40\u0a30 \u0a39\u0a30\u0a3f \u0a39\u0a40\u0a30\u0a3e \u0a1c\u0a28 \u0a1c\u0a09\u0a39\u0a30\u0a40 \u0a32\u0a47 \u0a15\u0a48 \u0a2e\u0a3e\u0a02\u0a21\u0a48 \u0a39\u0a3e\u0a1f \u0965","original":"\u0a15\u0a2c\u0a40\u0a30\u0a39\u0a30\u0a3f\u0a39\u0a40\u0a30\u0a3e\u0a1c\u0a28\u0a1c\u0a09\u0a39\u0a30\u0a40\u0a32\u0a47\u0a15\u0a48\u0a2e\u0a3e\u0a02\u0a21\u0a48\u0a39\u0a3e\u0a1f\u0965","melody_id":1,"author_id":7,"hymn":3563,"page":1373,"line":4,"section":"Salok Bhagat Kabeer (Verses Of Saint Kabeer)","search":"\u0a15\u0a39\u0a39\u0a1c\u0a1c\u0a32\u0a15\u0a2e\u0a39","language_id":54,"translation":{"id":992206,"scripture_id":58366,"text":"Kabeer, the Lord is the Diamond, and the Lord's humble servant is the jeweller who has set up his shop.","language_id":13,"language":{"id":13,"language":"English","code":"en-US","script":"latn","direction":1,"accuracy":99}},"transliteration":{"id":1284031,"scripture_id":58366,"text":"kab\u012br har h\u012br\u0101 jan jauhar\u012b l\u0113 kai m\u0101nhdai h\u0101t .","language_id":69,"language":{"id":69,"language":"Latin","code":null,"script":"latn","direction":1,"accuracy":99}},"melody":{"id":1,"melody":"None","gurmukhi":"","description":"There is no melody or mood associated with this line, which may be because it is the preamble to the hymn, or is not meant to be read in any particular melody or mood"},"author":{"id":7,"author":"Saint Kabir","gurmukhi":"\u0a2d\u0a17\u0a24 \u0a15\u0a2c\u0a40\u0a30","description":"Saint Kabir [1440 - 1518] was a Muslim mystic born in Varanasi in India, whose 541 hymns are included in the Guru Granth Sahib. His writings about God are full of love and devotion, very direct and striking in appeal.<br\/><br\/>The birth of Kabir remains to this day shrouded in mystery and legend. Authorities disagree on both when he was born and who his parents were. One legend proclaims a divine virginal birth. His mother was reputed to have been of the Brahman caste and to have become pregnant after a visit to a Hindu shrine.<br\/><br\/>Because she was unwed, she abandoned Kabir, who was found and adopted by a Muslim weaver. That his early life began as a Muslim there is no doubt, although he later became influenced by the Hindu ascetic, Ramananda, who he accepted as his Guru."},"language":{"id":54,"language":"Gurmukhi","code":"pa","script":"guru","direction":1,"accuracy":99}},{"id":58367,"text":"\u0a1c\u0a2c \u0a39\u0a40 \u0a2a\u0a3e\u0a08\u0a05\u0a39\u0a3f \u0a2a\u0a3e\u0a30\u0a16\u0a42 \u0a24\u0a2c \u0a39\u0a40\u0a30\u0a28 \u0a15\u0a40 \u0a38\u0a3e\u0a1f \u0965\u0a67\u0a6c\u0a68\u0965","original":"\u0a1c\u0a2c\u0a39\u0a40\u0a2a\u0a3e\u0a08\u0a05\u0a39\u0a3f\u0a2a\u0a3e\u0a30\u0a16\u0a42\u0a24\u0a2c\u0a39\u0a40\u0a30\u0a28\u0a15\u0a40\u0a38\u0a3e\u0a1f\u0965\u0a67\u0a6c\u0a68\u0965","melody_id":1,"author_id":7,"hymn":3563,"page":1373,"line":4,"section":"Salok Bhagat Kabeer (Verses Of Saint Kabeer)","search":"\u0a1c\u0a39\u0a2a\u0a2a\u0a24\u0a39\u0a15\u0a38","language_id":54,"translation":{"id":992223,"scripture_id":58367,"text":"As soon as an appraiser is found, the price of the jewel is set. ||162||","language_id":13,"language":{"id":13,"language":"English","code":"en-US","script":"latn","direction":1,"accuracy":99}},"transliteration":{"id":1284053,"scripture_id":58367,"text":"jab h\u012b p\u0101\u012bah p\u0101rakh\u016b tab h\u012bran k\u012b s\u0101t .162.","language_id":69,"language":{"id":69,"language":"Latin","code":null,"script":"latn","direction":1,"accuracy":99}},"melody":{"id":1,"melody":"None","gurmukhi":"","description":"There is no melody or mood associated with this line, which may be because it is the preamble to the hymn, or is not meant to be read in any particular melody or mood"},"author":{"id":7,"author":"Saint Kabir","gurmukhi":"\u0a2d\u0a17\u0a24 \u0a15\u0a2c\u0a40\u0a30","description":"Saint Kabir [1440 - 1518] was a Muslim mystic born in Varanasi in India, whose 541 hymns are included in the Guru Granth Sahib. His writings about God are full of love and devotion, very direct and striking in appeal.<br\/><br\/>The birth of Kabir remains to this day shrouded in mystery and legend. Authorities disagree on both when he was born and who his parents were. One legend proclaims a divine virginal birth. His mother was reputed to have been of the Brahman caste and to have become pregnant after a visit to a Hindu shrine.<br\/><br\/>Because she was unwed, she abandoned Kabir, who was found and adopted by a Muslim weaver. That his early life began as a Muslim there is no doubt, although he later became influenced by the Hindu ascetic, Ramananda, who he accepted as his Guru."},"language":{"id":54,"language":"Gurmukhi","code":"pa","script":"guru","direction":1,"accuracy":99}},{"id":58368,"text":"\u0a15\u0a2c\u0a40\u0a30 \u0a15\u0a3e\u0a2e \u0a2a\u0a30\u0a47 \u0a39\u0a30\u0a3f \u0a38\u0a3f\u0a2e\u0a30\u0a40\u0a10 \u0a10\u0a38\u0a3e \u0a38\u0a3f\u0a2e\u0a30\u0a39\u0a41 \u0a28\u0a3f\u0a24 \u0965","original":"\u0a15\u0a2c\u0a40\u0a30\u0a15\u0a3e\u0a2e\u0a2a\u0a30\u0a47\u0a39\u0a30\u0a3f\u0a38\u0a3f\u0a2e\u0a30\u0a40\u0a10\u0a10\u0a38\u0a3e\u0a38\u0a3f\u0a2e\u0a30\u0a39\u0a41\u0a28\u0a3f\u0a24\u0965","melody_id":1,"author_id":7,"hymn":3563,"page":1373,"line":5,"section":"Salok Bhagat Kabeer (Verses Of Saint Kabeer)","search":"\u0a15\u0a15\u0a2a\u0a39\u0a38\u0a05\u0a38\u0a28","language_id":54,"translation":{"id":992240,"scripture_id":58368,"text":"Kabeer, you remember the Lord in meditation, only when the need arises. You should remember Him all the time.","language_id":13,"language":{"id":13,"language":"English","code":"en-US","script":"latn","direction":1,"accuracy":99}},"transliteration":{"id":1284075,"scripture_id":58368,"text":"kab\u012br k\u0101m par\u0113 har simar\u012bai ais\u0101 simarah nit .","language_id":69,"language":{"id":69,"language":"Latin","code":null,"script":"latn","direction":1,"accuracy":99}},"melody":{"id":1,"melody":"None","gurmukhi":"","description":"There is no melody or mood associated with this line, which may be because it is the preamble to the hymn, or is not meant to be read in any particular melody or mood"},"author":{"id":7,"author":"Saint Kabir","gurmukhi":"\u0a2d\u0a17\u0a24 \u0a15\u0a2c\u0a40\u0a30","description":"Saint Kabir [1440 - 1518] was a Muslim mystic born in Varanasi in India, whose 541 hymns are included in the Guru Granth Sahib. His writings about God are full of love and devotion, very direct and striking in appeal.<br\/><br\/>The birth of Kabir remains to this day shrouded in mystery and legend. Authorities disagree on both when he was born and who his parents were. One legend proclaims a divine virginal birth. His mother was reputed to have been of the Brahman caste and to have become pregnant after a visit to a Hindu shrine.<br\/><br\/>Because she was unwed, she abandoned Kabir, who was found and adopted by a Muslim weaver. That his early life began as a Muslim there is no doubt, although he later became influenced by the Hindu ascetic, Ramananda, who he accepted as his Guru."},"language":{"id":54,"language":"Gurmukhi","code":"pa","script":"guru","direction":1,"accuracy":99}},{"id":58369,"text":"\u0a05\u0a2e\u0a30\u0a3e \u0a2a\u0a41\u0a30 \u0a2c\u0a3e\u0a38\u0a3e \u0a15\u0a30\u0a39\u0a41 \u0a39\u0a30\u0a3f \u0a17\u0a07\u0a06 \u0a2c\u0a39\u0a4b\u0a30\u0a48 \u0a2c\u0a3f\u0a24 \u0965\u0a67\u0a6c\u0a69\u0965","original":"\u0a05\u0a2e\u0a30\u0a3e\u0a2a\u0a41\u0a30\u0a2c\u0a3e\u0a38\u0a3e\u0a15\u0a30\u0a39\u0a41\u0a39\u0a30\u0a3f\u0a17\u0a07\u0a06\u0a2c\u0a39\u0a4b\u0a30\u0a48\u0a2c\u0a3f\u0a24\u0965\u0a67\u0a6c\u0a69\u0965","melody_id":1,"author_id":7,"hymn":3563,"page":1373,"line":5,"section":"Salok Bhagat Kabeer (Verses Of Saint Kabeer)","search":"\u0a05\u0a2a\u0a2c\u0a15\u0a39\u0a17\u0a2c\u0a2c","language_id":54,"translation":{"id":992257,"scripture_id":58369,"text":"You shall dwell in the city of immortality, and the Lord shall restore the wealth you lost. ||163||","language_id":13,"language":{"id":13,"language":"English","code":"en-US","script":"latn","direction":1,"accuracy":99}},"transliteration":{"id":1284097,"scripture_id":58369,"text":"amar\u0101 pur b\u0101s\u0101 karah har gai\u0101 bah\u014drai bit .163.","language_id":69,"language":{"id":69,"language":"Latin","code":null,"script":"latn","direction":1,"accuracy":99}},"melody":{"id":1,"melody":"None","gurmukhi":"","description":"There is no melody or mood associated with this line, which may be because it is the preamble to the hymn, or is not meant to be read in any particular melody or mood"},"author":{"id":7,"author":"Saint Kabir","gurmukhi":"\u0a2d\u0a17\u0a24 \u0a15\u0a2c\u0a40\u0a30","description":"Saint Kabir [1440 - 1518] was a Muslim mystic born in Varanasi in India, whose 541 hymns are included in the Guru Granth Sahib. His writings about God are full of love and devotion, very direct and striking in appeal.<br\/><br\/>The birth of Kabir remains to this day shrouded in mystery and legend. Authorities disagree on both when he was born and who his parents were. One legend proclaims a divine virginal birth. His mother was reputed to have been of the Brahman caste and to have become pregnant after a visit to a Hindu shrine.<br\/><br\/>Because she was unwed, she abandoned Kabir, who was found and adopted by a Muslim weaver. That his early life began as a Muslim there is no doubt, although he later became influenced by the Hindu ascetic, Ramananda, who he accepted as his Guru."},"language":{"id":54,"language":"Gurmukhi","code":"pa","script":"guru","direction":1,"accuracy":99}},{"id":58370,"text":"\u0a15\u0a2c\u0a40\u0a30 \u0a38\u0a47\u0a35\u0a3e \u0a15\u0a09 \u0a26\u0a41\u0a07 \u0a2d\u0a32\u0a47 \u0a0f\u0a15\u0a41 \u0a38\u0a70\u0a24\u0a41 \u0a07\u0a15\u0a41 \u0a30\u0a3e\u0a2e\u0a41 \u0965","original":"\u0a15\u0a2c\u0a40\u0a30\u0a38\u0a47\u0a35\u0a3e\u0a15\u0a09\u0a26\u0a41\u0a07\u0a2d\u0a32\u0a47\u0a0f\u0a15\u0a41\u0a38\u0a70\u0a24\u0a41\u0a07\u0a15\u0a41\u0a30\u0a3e\u0a2e\u0a41\u0965","melody_id":1,"author_id":7,"hymn":3563,"page":1373,"line":6,"section":"Salok Bhagat Kabeer (Verses Of Saint Kabeer)","search":"\u0a15\u0a38\u0a15\u0a26\u0a2d\u0a72\u0a38\u0a72\u0a30","language_id":54,"translation":{"id":992274,"scripture_id":58370,"text":"Kabeer, it is good to perform selfless service for two - the Saints and the Lord.","language_id":13,"language":{"id":13,"language":"English","code":"en-US","script":"latn","direction":1,"accuracy":99}},"transliteration":{"id":1284119,"scripture_id":58370,"text":"kab\u012br s\u0113v\u0101 kau dui bhal\u0113 \u0113k sant ik r\u0101m .","language_id":69,"language":{"id":69,"language":"Latin","code":null,"script":"latn","direction":1,"accuracy":99}},"melody":{"id":1,"melody":"None","gurmukhi":"","description":"There is no melody or mood associated with this line, which may be because it is the preamble to the hymn, or is not meant to be read in any particular melody or mood"},"author":{"id":7,"author":"Saint Kabir","gurmukhi":"\u0a2d\u0a17\u0a24 \u0a15\u0a2c\u0a40\u0a30","description":"Saint Kabir [1440 - 1518] was a Muslim mystic born in Varanasi in India, whose 541 hymns are included in the Guru Granth Sahib. His writings about God are full of love and devotion, very direct and striking in appeal.<br\/><br\/>The birth of Kabir remains to this day shrouded in mystery and legend. Authorities disagree on both when he was born and who his parents were. One legend proclaims a divine virginal birth. His mother was reputed to have been of the Brahman caste and to have become pregnant after a visit to a Hindu shrine.<br\/><br\/>Because she was unwed, she abandoned Kabir, who was found and adopted by a Muslim weaver. That his early life began as a Muslim there is no doubt, although he later became influenced by the Hindu ascetic, Ramananda, who he accepted as his Guru."},"language":{"id":54,"language":"Gurmukhi","code":"pa","script":"guru","direction":1,"accuracy":99}},{"id":58371,"text":"\u0a30\u0a3e\u0a2e\u0a41 \u0a1c\u0a41 \u0a26\u0a3e\u0a24\u0a3e \u0a2e\u0a41\u0a15\u0a24\u0a3f \u0a15\u0a4b \u0a38\u0a70\u0a24\u0a41 \u0a1c\u0a2a\u0a3e\u0a35\u0a48 \u0a28\u0a3e\u0a2e\u0a41 \u0965\u0a67\u0a6c\u0a6a\u0965","original":"\u0a30\u0a3e\u0a2e\u0a41\u0a1c\u0a41\u0a26\u0a3e\u0a24\u0a3e\u0a2e\u0a41\u0a15\u0a24\u0a3f\u0a15\u0a4b\u0a38\u0a70\u0a24\u0a41\u0a1c\u0a2a\u0a3e\u0a35\u0a48\u0a28\u0a3e\u0a2e\u0a41\u0965\u0a67\u0a6c\u0a6a\u0965","melody_id":1,"author_id":7,"hymn":3563,"page":1373,"line":6,"section":"Salok Bhagat Kabeer (Verses Of Saint Kabeer)","search":"\u0a30\u0a1c\u0a26\u0a2e\u0a15\u0a38\u0a1c\u0a28","language_id":54,"translation":{"id":992291,"scripture_id":58371,"text":"The Lord is the Giver of liberation, and the Saint inspires us to chant the Naam. ||164||","language_id":13,"language":{"id":13,"language":"English","code":"en-US","script":"latn","direction":1,"accuracy":99}},"transliteration":{"id":1284141,"scripture_id":58371,"text":"r\u0101m j d\u0101t\u0101 mukat k\u014d sant jap\u0101vai n\u0101m .164.","language_id":69,"language":{"id":69,"language":"Latin","code":null,"script":"latn","direction":1,"accuracy":99}},"melody":{"id":1,"melody":"None","gurmukhi":"","description":"There is no melody or mood associated with this line, which may be because it is the preamble to the hymn, or is not meant to be read in any particular melody or mood"},"author":{"id":7,"author":"Saint Kabir","gurmukhi":"\u0a2d\u0a17\u0a24 \u0a15\u0a2c\u0a40\u0a30","description":"Saint Kabir [1440 - 1518] was a Muslim mystic born in Varanasi in India, whose 541 hymns are included in the Guru Granth Sahib. His writings about God are full of love and devotion, very direct and striking in appeal.<br\/><br\/>The birth of Kabir remains to this day shrouded in mystery and legend. Authorities disagree on both when he was born and who his parents were. One legend proclaims a divine virginal birth. His mother was reputed to have been of the Brahman caste and to have become pregnant after a visit to a Hindu shrine.<br\/><br\/>Because she was unwed, she abandoned Kabir, who was found and adopted by a Muslim weaver. That his early life began as a Muslim there is no doubt, although he later became influenced by the Hindu ascetic, Ramananda, who he accepted as his Guru."},"language":{"id":54,"language":"Gurmukhi","code":"pa","script":"guru","direction":1,"accuracy":99}},{"id":58372,"text":"\u0a15\u0a2c\u0a40\u0a30 \u0a1c\u0a3f\u0a39 \u0a2e\u0a3e\u0a30\u0a17\u0a3f \u0a2a\u0a70\u0a21\u0a3f\u0a24 \u0a17\u0a0f \u0a2a\u0a3e\u0a1b\u0a48 \u0a2a\u0a30\u0a40 \u0a2c\u0a39\u0a40\u0a30 \u0965","original":"\u0a15\u0a2c\u0a40\u0a30\u0a1c\u0a3f\u0a39\u0a2e\u0a3e\u0a30\u0a17\u0a3f\u0a2a\u0a70\u0a21\u0a3f\u0a24\u0a17\u0a0f\u0a2a\u0a3e\u0a1b\u0a48\u0a2a\u0a30\u0a40\u0a2c\u0a39\u0a40\u0a30\u0965","melody_id":1,"author_id":7,"hymn":3563,"page":1373,"line":7,"section":"Salok Bhagat Kabeer (Verses Of Saint Kabeer)","search":"\u0a15\u0a1c\u0a2e\u0a2a\u0a17\u0a2a\u0a2a\u0a2c","language_id":54,"translation":{"id":992308,"scripture_id":58372,"text":"Kabeer, the crowds follow the path which the Pandits, the religious scholars, have taken.","language_id":13,"language":{"id":13,"language":"English","code":"en-US","script":"latn","direction":1,"accuracy":99}},"transliteration":{"id":1284163,"scripture_id":58372,"text":"kab\u012br jih m\u0101rag pandit ga\u0113 p\u0101shai par\u012b bah\u012br .","language_id":69,"language":{"id":69,"language":"Latin","code":null,"script":"latn","direction":1,"accuracy":99}},"melody":{"id":1,"melody":"None","gurmukhi":"","description":"There is no melody or mood associated with this line, which may be because it is the preamble to the hymn, or is not meant to be read in any particular melody or mood"},"author":{"id":7,"author":"Saint Kabir","gurmukhi":"\u0a2d\u0a17\u0a24 \u0a15\u0a2c\u0a40\u0a30","description":"Saint Kabir [1440 - 1518] was a Muslim mystic born in Varanasi in India, whose 541 hymns are included in the Guru Granth Sahib. His writings about God are full of love and devotion, very direct and striking in appeal.<br\/><br\/>The birth of Kabir remains to this day shrouded in mystery and legend. Authorities disagree on both when he was born and who his parents were. One legend proclaims a divine virginal birth. His mother was reputed to have been of the Brahman caste and to have become pregnant after a visit to a Hindu shrine.<br\/><br\/>Because she was unwed, she abandoned Kabir, who was found and adopted by a Muslim weaver. That his early life began as a Muslim there is no doubt, although he later became influenced by the Hindu ascetic, Ramananda, who he accepted as his Guru."},"language":{"id":54,"language":"Gurmukhi","code":"pa","script":"guru","direction":1,"accuracy":99}},{"id":58373,"text":"\u0a07\u0a15 \u0a05\u0a35\u0a18\u0a1f \u0a18\u0a3e\u0a1f\u0a40 \u0a30\u0a3e\u0a2e \u0a15\u0a40 \u0a24\u0a3f\u0a39 \u0a1a\u0a5c\u0a3f \u0a30\u0a39\u0a3f\u0a13 \u0a15\u0a2c\u0a40\u0a30 \u0965\u0a67\u0a6c\u0a6b\u0965","original":"\u0a07\u0a15\u0a05\u0a35\u0a18\u0a1f\u0a18\u0a3e\u0a1f\u0a40\u0a30\u0a3e\u0a2e\u0a15\u0a40\u0a24\u0a3f\u0a39\u0a1a\u0a5c\u0a3f\u0a30\u0a39\u0a3f\u0a13\u0a15\u0a2c\u0a40\u0a30\u0965\u0a67\u0a6c\u0a6b\u0965","melody_id":1,"author_id":7,"hymn":3563,"page":1373,"line":7,"section":"Salok Bhagat Kabeer (Verses Of Saint Kabeer)","search":"\u0a72\u0a05\u0a18\u0a30\u0a15\u0a24\u0a1a\u0a30\u0a15","language_id":54,"translation":{"id":992325,"scripture_id":58373,"text":"There is a difficult and treacherous cliff on that path to the Lord; Kabeer is climbing that cliff. ||165||","language_id":13,"language":{"id":13,"language":"English","code":"en-US","script":"latn","direction":1,"accuracy":99}},"transliteration":{"id":1284185,"scripture_id":58373,"text":"ik avaghat gh\u0101t\u012b r\u0101m k\u012b tih char rahi\u014d kab\u012br .165.","language_id":69,"language":{"id":69,"language":"Latin","code":null,"script":"latn","direction":1,"accuracy":99}},"melody":{"id":1,"melody":"None","gurmukhi":"","description":"There is no melody or mood associated with this line, which may be because it is the preamble to the hymn, or is not meant to be read in any particular melody or mood"},"author":{"id":7,"author":"Saint Kabir","gurmukhi":"\u0a2d\u0a17\u0a24 \u0a15\u0a2c\u0a40\u0a30","description":"Saint Kabir [1440 - 1518] was a Muslim mystic born in Varanasi in India, whose 541 hymns are included in the Guru Granth Sahib. His writings about God are full of love and devotion, very direct and striking in appeal.<br\/><br\/>The birth of Kabir remains to this day shrouded in mystery and legend. Authorities disagree on both when he was born and who his parents were. One legend proclaims a divine virginal birth. His mother was reputed to have been of the Brahman caste and to have become pregnant after a visit to a Hindu shrine.<br\/><br\/>Because she was unwed, she abandoned Kabir, who was found and adopted by a Muslim weaver. That his early life began as a Muslim there is no doubt, although he later became influenced by the Hindu ascetic, Ramananda, who he accepted as his Guru."},"language":{"id":54,"language":"Gurmukhi","code":"pa","script":"guru","direction":1,"accuracy":99}},{"id":58374,"text":"\u0a15\u0a2c\u0a40\u0a30 \u0a26\u0a41\u0a28\u0a40\u0a06 \u0a15\u0a47 \u0a26\u0a4b\u0a16\u0a47 \u0a2e\u0a42\u0a06 \u0a1a\u0a3e\u0a32\u0a24 \u0a15\u0a41\u0a32 \u0a15\u0a40 \u0a15\u0a3e\u0a28\u0a3f \u0965","original":"\u0a15\u0a2c\u0a40\u0a30\u0a26\u0a41\u0a28\u0a40\u0a06\u0a15\u0a47\u0a26\u0a4b\u0a16\u0a47\u0a2e\u0a42\u0a06\u0a1a\u0a3e\u0a32\u0a24\u0a15\u0a41\u0a32\u0a15\u0a40\u0a15\u0a3e\u0a28\u0a3f\u0965","melody_id":1,"author_id":7,"hymn":3563,"page":1373,"line":8,"section":"Salok Bhagat Kabeer (Verses Of Saint Kabeer)","search":"\u0a15\u0a26\u0a15\u0a26\u0a2e\u0a1a\u0a15\u0a15\u0a15","language_id":54,"translation":{"id":992342,"scripture_id":58374,"text":"Kabeer, the mortal dies of his worldly troubles and pain, after worrying about his family.","language_id":13,"language":{"id":13,"language":"English","code":"en-US","script":"latn","direction":1,"accuracy":99}},"transliteration":{"id":1284207,"scripture_id":58374,"text":"kab\u012br dun\u012b\u0101 k\u0113 d\u014dkh\u0113 m\u016b\u0101 ch\u0101lat kul k\u012b k\u0101n .","language_id":69,"language":{"id":69,"language":"Latin","code":null,"script":"latn","direction":1,"accuracy":99}},"melody":{"id":1,"melody":"None","gurmukhi":"","description":"There is no melody or mood associated with this line, which may be because it is the preamble to the hymn, or is not meant to be read in any particular melody or mood"},"author":{"id":7,"author":"Saint Kabir","gurmukhi":"\u0a2d\u0a17\u0a24 \u0a15\u0a2c\u0a40\u0a30","description":"Saint Kabir [1440 - 1518] was a Muslim mystic born in Varanasi in India, whose 541 hymns are included in the Guru Granth Sahib. His writings about God are full of love and devotion, very direct and striking in appeal.<br\/><br\/>The birth of Kabir remains to this day shrouded in mystery and legend. Authorities disagree on both when he was born and who his parents were. One legend proclaims a divine virginal birth. His mother was reputed to have been of the Brahman caste and to have become pregnant after a visit to a Hindu shrine.<br\/><br\/>Because she was unwed, she abandoned Kabir, who was found and adopted by a Muslim weaver. That his early life began as a Muslim there is no doubt, although he later became influenced by the Hindu ascetic, Ramananda, who he accepted as his Guru."},"language":{"id":54,"language":"Gurmukhi","code":"pa","script":"guru","direction":1,"accuracy":99}},{"id":58375,"text":"\u0a24\u0a2c \u0a15\u0a41\u0a32\u0a41 \u0a15\u0a3f\u0a38 \u0a15\u0a3e \u0a32\u0a3e\u0a1c\u0a38\u0a40 \u0a1c\u0a2c \u0a32\u0a47 \u0a27\u0a30\u0a39\u0a3f \u0a2e\u0a38\u0a3e\u0a28\u0a3f \u0965\u0a67\u0a6c\u0a6c\u0965","original":"\u0a24\u0a2c\u0a15\u0a41\u0a32\u0a41\u0a15\u0a3f\u0a38\u0a15\u0a3e\u0a32\u0a3e\u0a1c\u0a38\u0a40\u0a1c\u0a2c\u0a32\u0a47\u0a27\u0a30\u0a39\u0a3f\u0a2e\u0a38\u0a3e\u0a28\u0a3f\u0965\u0a67\u0a6c\u0a6c\u0965","melody_id":1,"author_id":7,"hymn":3563,"page":1373,"line":8,"section":"Salok Bhagat Kabeer (Verses Of Saint Kabeer)","search":"\u0a24\u0a15\u0a15\u0a15\u0a32\u0a1c\u0a32\u0a27\u0a2e","language_id":54,"translation":{"id":992359,"scripture_id":58375,"text":"Whose family is dishonored, when he is placed on the funeral pyre? ||166||","language_id":13,"language":{"id":13,"language":"English","code":"en-US","script":"latn","direction":1,"accuracy":99}},"transliteration":{"id":1284229,"scripture_id":58375,"text":"tab kul kis k\u0101 l\u0101jas\u012b jab l\u0113 dharah mas\u0101n .166.","language_id":69,"language":{"id":69,"language":"Latin","code":null,"script":"latn","direction":1,"accuracy":99}},"melody":{"id":1,"melody":"None","gurmukhi":"","description":"There is no melody or mood associated with this line, which may be because it is the preamble to the hymn, or is not meant to be read in any particular melody or mood"},"author":{"id":7,"author":"Saint Kabir","gurmukhi":"\u0a2d\u0a17\u0a24 \u0a15\u0a2c\u0a40\u0a30","description":"Saint Kabir [1440 - 1518] was a Muslim mystic born in Varanasi in India, whose 541 hymns are included in the Guru Granth Sahib. His writings about God are full of love and devotion, very direct and striking in appeal.<br\/><br\/>The birth of Kabir remains to this day shrouded in mystery and legend. Authorities disagree on both when he was born and who his parents were. One legend proclaims a divine virginal birth. His mother was reputed to have been of the Brahman caste and to have become pregnant after a visit to a Hindu shrine.<br\/><br\/>Because she was unwed, she abandoned Kabir, who was found and adopted by a Muslim weaver. That his early life began as a Muslim there is no doubt, although he later became influenced by the Hindu ascetic, Ramananda, who he accepted as his Guru."},"language":{"id":54,"language":"Gurmukhi","code":"pa","script":"guru","direction":1,"accuracy":99}},{"id":58376,"text":"\u0a15\u0a2c\u0a40\u0a30 \u0a21\u0a42\u0a2c\u0a39\u0a3f\u0a17\u0a4b \u0a30\u0a47 \u0a2c\u0a3e\u0a2a\u0a41\u0a30\u0a47 \u0a2c\u0a39\u0a41 \u0a32\u0a4b\u0a17\u0a28 \u0a15\u0a40 \u0a15\u0a3e\u0a28\u0a3f \u0965","original":"\u0a15\u0a2c\u0a40\u0a30\u0a21\u0a42\u0a2c\u0a39\u0a3f\u0a17\u0a4b\u0a30\u0a47\u0a2c\u0a3e\u0a2a\u0a41\u0a30\u0a47\u0a2c\u0a39\u0a41\u0a32\u0a4b\u0a17\u0a28\u0a15\u0a40\u0a15\u0a3e\u0a28\u0a3f\u0965","melody_id":1,"author_id":7,"hymn":3563,"page":1373,"line":9,"section":"Salok Bhagat Kabeer (Verses Of Saint Kabeer)","search":"\u0a15\u0a21\u0a30\u0a2c\u0a2c\u0a32\u0a15\u0a15","language_id":54,"translation":{"id":992376,"scripture_id":58376,"text":"Kabeer, you shall drown, you wretched being, from worrying about what other people think.","language_id":13,"language":{"id":13,"language":"English","code":"en-US","script":"latn","direction":1,"accuracy":99}},"transliteration":{"id":1284251,"scripture_id":58376,"text":"kab\u012br d\u016bbahig\u014d r\u0113 b\u0101pur\u0113 bah l\u014dgan k\u012b k\u0101n .","language_id":69,"language":{"id":69,"language":"Latin","code":null,"script":"latn","direction":1,"accuracy":99}},"melody":{"id":1,"melody":"None","gurmukhi":"","description":"There is no melody or mood associated with this line, which may be because it is the preamble to the hymn, or is not meant to be read in any particular melody or mood"},"author":{"id":7,"author":"Saint Kabir","gurmukhi":"\u0a2d\u0a17\u0a24 \u0a15\u0a2c\u0a40\u0a30","description":"Saint Kabir [1440 - 1518] was a Muslim mystic born in Varanasi in India, whose 541 hymns are included in the Guru Granth Sahib. His writings about God are full of love and devotion, very direct and striking in appeal.<br\/><br\/>The birth of Kabir remains to this day shrouded in mystery and legend. Authorities disagree on both when he was born and who his parents were. One legend proclaims a divine virginal birth. His mother was reputed to have been of the Brahman caste and to have become pregnant after a visit to a Hindu shrine.<br\/><br\/>Because she was unwed, she abandoned Kabir, who was found and adopted by a Muslim weaver. That his early life began as a Muslim there is no doubt, although he later became influenced by the Hindu ascetic, Ramananda, who he accepted as his Guru."},"language":{"id":54,"language":"Gurmukhi","code":"pa","script":"guru","direction":1,"accuracy":99}},{"id":58377,"text":"\u0a2a\u0a3e\u0a30\u0a4b\u0a38\u0a40 \u0a15\u0a47 \u0a1c\u0a4b \u0a39\u0a42\u0a06 \u0a24\u0a42 \u0a05\u0a2a\u0a28\u0a47 \u0a2d\u0a40 \u0a1c\u0a3e\u0a28\u0a41 \u0965\u0a67\u0a6c\u0a6d\u0965","original":"\u0a2a\u0a3e\u0a30\u0a4b\u0a38\u0a40\u0a15\u0a47\u0a1c\u0a4b\u0a39\u0a42\u0a06\u0a24\u0a42\u0a05\u0a2a\u0a28\u0a47\u0a2d\u0a40\u0a1c\u0a3e\u0a28\u0a41\u0965\u0a67\u0a6c\u0a6d\u0965","melody_id":1,"author_id":7,"hymn":3563,"page":1373,"line":10,"section":"Salok Bhagat Kabeer (Verses Of Saint Kabeer)","search":"\u0a2a\u0a15\u0a1c\u0a39\u0a24\u0a05\u0a2d\u0a1c","language_id":54,"translation":{"id":992393,"scripture_id":58377,"text":"You know that whatever happens to your neighbors, will also happen to you. ||167||","language_id":13,"language":{"id":13,"language":"English","code":"en-US","script":"latn","direction":1,"accuracy":99}},"transliteration":{"id":1284273,"scripture_id":58377,"text":"p\u0101r\u014ds\u012b k\u0113 j\u014d h\u016b\u0101 t\u016b apan\u0113 bh\u012b j\u0101n .167.","language_id":69,"language":{"id":69,"language":"Latin","code":null,"script":"latn","direction":1,"accuracy":99}},"melody":{"id":1,"melody":"None","gurmukhi":"","description":"There is no melody or mood associated with this line, which may be because it is the preamble to the hymn, or is not meant to be read in any particular melody or mood"},"author":{"id":7,"author":"Saint Kabir","gurmukhi":"\u0a2d\u0a17\u0a24 \u0a15\u0a2c\u0a40\u0a30","description":"Saint Kabir [1440 - 1518] was a Muslim mystic born in Varanasi in India, whose 541 hymns are included in the Guru Granth Sahib. His writings about God are full of love and devotion, very direct and striking in appeal.<br\/><br\/>The birth of Kabir remains to this day shrouded in mystery and legend. Authorities disagree on both when he was born and who his parents were. One legend proclaims a divine virginal birth. His mother was reputed to have been of the Brahman caste and to have become pregnant after a visit to a Hindu shrine.<br\/><br\/>Because she was unwed, she abandoned Kabir, who was found and adopted by a Muslim weaver. That his early life began as a Muslim there is no doubt, although he later became influenced by the Hindu ascetic, Ramananda, who he accepted as his Guru."},"language":{"id":54,"language":"Gurmukhi","code":"pa","script":"guru","direction":1,"accuracy":99}},{"id":58378,"text":"\u0a15\u0a2c\u0a40\u0a30 \u0a2d\u0a32\u0a40 \u0a2e\u0a27\u0a42\u0a15\u0a30\u0a40 \u0a28\u0a3e\u0a28\u0a3e \u0a2c\u0a3f\u0a27\u0a3f \u0a15\u0a4b \u0a28\u0a3e\u0a1c\u0a41 \u0965","original":"\u0a15\u0a2c\u0a40\u0a30\u0a2d\u0a32\u0a40\u0a2e\u0a27\u0a42\u0a15\u0a30\u0a40\u0a28\u0a3e\u0a28\u0a3e\u0a2c\u0a3f\u0a27\u0a3f\u0a15\u0a4b\u0a28\u0a3e\u0a1c\u0a41\u0965","melody_id":1,"author_id":7,"hymn":3563,"page":1373,"line":10,"section":"Salok Bhagat Kabeer (Verses Of Saint Kabeer)","search":"\u0a15\u0a2d\u0a2e\u0a28\u0a2c\u0a15\u0a28","language_id":54,"translation":{"id":992410,"scripture_id":58378,"text":"Kabeer, even dry bread, made of various grains, is good.","language_id":13,"language":{"id":13,"language":"English","code":"en-US","script":"latn","direction":1,"accuracy":99}},"transliteration":{"id":1284295,"scripture_id":58378,"text":"kab\u012br bhal\u012b madh\u016bkar\u012b n\u0101n\u0101 bidh k\u014d n\u0101j .","language_id":69,"language":{"id":69,"language":"Latin","code":null,"script":"latn","direction":1,"accuracy":99}},"melody":{"id":1,"melody":"None","gurmukhi":"","description":"There is no melody or mood associated with this line, which may be because it is the preamble to the hymn, or is not meant to be read in any particular melody or mood"},"author":{"id":7,"author":"Saint Kabir","gurmukhi":"\u0a2d\u0a17\u0a24 \u0a15\u0a2c\u0a40\u0a30","description":"Saint Kabir [1440 - 1518] was a Muslim mystic born in Varanasi in India, whose 541 hymns are included in the Guru Granth Sahib. His writings about God are full of love and devotion, very direct and striking in appeal.<br\/><br\/>The birth of Kabir remains to this day shrouded in mystery and legend. Authorities disagree on both when he was born and who his parents were. One legend proclaims a divine virginal birth. His mother was reputed to have been of the Brahman caste and to have become pregnant after a visit to a Hindu shrine.<br\/><br\/>Because she was unwed, she abandoned Kabir, who was found and adopted by a Muslim weaver. That his early life began as a Muslim there is no doubt, although he later became influenced by the Hindu ascetic, Ramananda, who he accepted as his Guru."},"language":{"id":54,"language":"Gurmukhi","code":"pa","script":"guru","direction":1,"accuracy":99}},{"id":58379,"text":"\u0a26\u0a3e\u0a35\u0a3e \u0a15\u0a3e\u0a39\u0a42 \u0a15\u0a4b \u0a28\u0a39\u0a40 \u0a2c\u0a21\u0a3e \u0a26\u0a47\u0a38\u0a41 \u0a2c\u0a21 \u0a30\u0a3e\u0a1c\u0a41 \u0965\u0a67\u0a6c\u0a6e\u0965","original":"\u0a26\u0a3e\u0a35\u0a3e\u0a15\u0a3e\u0a39\u0a42\u0a15\u0a4b\u0a28\u0a39\u0a40\u0a2c\u0a21\u0a3e\u0a26\u0a47\u0a38\u0a41\u0a2c\u0a21\u0a30\u0a3e\u0a1c\u0a41\u0965\u0a67\u0a6c\u0a6e\u0965","melody_id":1,"author_id":7,"hymn":3563,"page":1373,"line":10,"section":"Salok Bhagat Kabeer (Verses Of Saint Kabeer)","search":"\u0a26\u0a15\u0a15\u0a28\u0a2c\u0a26\u0a2c\u0a30","language_id":54,"translation":{"id":992427,"scripture_id":58379,"text":"No one brags about it, throughout the vast country and great empire. ||168||","language_id":13,"language":{"id":13,"language":"English","code":"en-US","script":"latn","direction":1,"accuracy":99}},"transliteration":{"id":1284317,"scripture_id":58379,"text":"d\u0101v\u0101 k\u0101h\u016b k\u014d nah\u012b bad\u0101 d\u0113s bad r\u0101j .168.","language_id":69,"language":{"id":69,"language":"Latin","code":null,"script":"latn","direction":1,"accuracy":99}},"melody":{"id":1,"melody":"None","gurmukhi":"","description":"There is no melody or mood associated with this line, which may be because it is the preamble to the hymn, or is not meant to be read in any particular melody or mood"},"author":{"id":7,"author":"Saint Kabir","gurmukhi":"\u0a2d\u0a17\u0a24 \u0a15\u0a2c\u0a40\u0a30","description":"Saint Kabir [1440 - 1518] was a Muslim mystic born in Varanasi in India, whose 541 hymns are included in the Guru Granth Sahib. His writings about God are full of love and devotion, very direct and striking in appeal.<br\/><br\/>The birth of Kabir remains to this day shrouded in mystery and legend. Authorities disagree on both when he was born and who his parents were. One legend proclaims a divine virginal birth. His mother was reputed to have been of the Brahman caste and to have become pregnant after a visit to a Hindu shrine.<br\/><br\/>Because she was unwed, she abandoned Kabir, who was found and adopted by a Muslim weaver. That his early life began as a Muslim there is no doubt, although he later became influenced by the Hindu ascetic, Ramananda, who he accepted as his Guru."},"language":{"id":54,"language":"Gurmukhi","code":"pa","script":"guru","direction":1,"accuracy":99}},{"id":58380,"text":"\u0a15\u0a2c\u0a40\u0a30 \u0a26\u0a3e\u0a35\u0a48 \u0a26\u0a3e\u0a1d\u0a28\u0a41 \u0a39\u0a4b\u0a24\u0a41 \u0a39\u0a48 \u0a28\u0a3f\u0a30\u0a26\u0a3e\u0a35\u0a48 \u0a30\u0a39\u0a48 \u0a28\u0a3f\u0a38\u0a70\u0a15 \u0965","original":"\u0a15\u0a2c\u0a40\u0a30\u0a26\u0a3e\u0a35\u0a48\u0a26\u0a3e\u0a1d\u0a28\u0a41\u0a39\u0a4b\u0a24\u0a41\u0a39\u0a48\u0a28\u0a3f\u0a30\u0a26\u0a3e\u0a35\u0a48\u0a30\u0a39\u0a48\u0a28\u0a3f\u0a38\u0a70\u0a15\u0965","melody_id":1,"author_id":7,"hymn":3563,"page":1373,"line":11,"section":"Salok Bhagat Kabeer (Verses Of Saint Kabeer)","search":"\u0a15\u0a26\u0a26\u0a39\u0a39\u0a28\u0a30\u0a28","language_id":54,"translation":{"id":992444,"scripture_id":58380,"text":"Kabeer, those who brag, shall burn. Those who do not brag remain carefree.","language_id":13,"language":{"id":13,"language":"English","code":"en-US","script":"latn","direction":1,"accuracy":99}},"transliteration":{"id":1284339,"scripture_id":58380,"text":"kab\u012br d\u0101vai d\u0101jhan h\u014dt hai nirad\u0101vai rahai nisank .","language_id":69,"language":{"id":69,"language":"Latin","code":null,"script":"latn","direction":1,"accuracy":99}},"melody":{"id":1,"melody":"None","gurmukhi":"","description":"There is no melody or mood associated with this line, which may be because it is the preamble to the hymn, or is not meant to be read in any particular melody or mood"},"author":{"id":7,"author":"Saint Kabir","gurmukhi":"\u0a2d\u0a17\u0a24 \u0a15\u0a2c\u0a40\u0a30","description":"Saint Kabir [1440 - 1518] was a Muslim mystic born in Varanasi in India, whose 541 hymns are included in the Guru Granth Sahib. His writings about God are full of love and devotion, very direct and striking in appeal.<br\/><br\/>The birth of Kabir remains to this day shrouded in mystery and legend. Authorities disagree on both when he was born and who his parents were. One legend proclaims a divine virginal birth. His mother was reputed to have been of the Brahman caste and to have become pregnant after a visit to a Hindu shrine.<br\/><br\/>Because she was unwed, she abandoned Kabir, who was found and adopted by a Muslim weaver. That his early life began as a Muslim there is no doubt, although he later became influenced by the Hindu ascetic, Ramananda, who he accepted as his Guru."},"language":{"id":54,"language":"Gurmukhi","code":"pa","script":"guru","direction":1,"accuracy":99}},{"id":58381,"text":"\u0a1c\u0a4b \u0a1c\u0a28\u0a41 \u0a28\u0a3f\u0a30\u0a26\u0a3e\u0a35\u0a48 \u0a30\u0a39\u0a48 \u0a38\u0a4b \u0a17\u0a28\u0a48 \u0a07\u0a70\u0a26\u0a4d\u0a30 \u0a38\u0a4b \u0a30\u0a70\u0a15 \u0965\u0a67\u0a6c\u0a6f\u0965","original":"\u0a1c\u0a4b\u0a1c\u0a28\u0a41\u0a28\u0a3f\u0a30\u0a26\u0a3e\u0a35\u0a48\u0a30\u0a39\u0a48\u0a38\u0a4b\u0a17\u0a28\u0a48\u0a07\u0a70\u0a26\u0a4d\u0a30\u0a38\u0a4b\u0a30\u0a70\u0a15\u0965\u0a67\u0a6c\u0a6f\u0965","melody_id":1,"author_id":7,"hymn":3563,"page":1373,"line":11,"section":"Salok Bhagat Kabeer (Verses Of Saint Kabeer)","search":"\u0a1c\u0a1c\u0a28\u0a30\u0a38\u0a17\u0a72\u0a38\u0a30","language_id":54,"translation":{"id":992461,"scripture_id":58381,"text":"That humble being who does not brag, looks upon the gods and the poor alike. ||169||","language_id":13,"language":{"id":13,"language":"English","code":"en-US","script":"latn","direction":1,"accuracy":99}},"transliteration":{"id":1284361,"scripture_id":58381,"text":"j\u014d jan nirad\u0101vai rahai s\u014d ganai indr s\u014d rank .169.","language_id":69,"language":{"id":69,"language":"Latin","code":null,"script":"latn","direction":1,"accuracy":99}},"melody":{"id":1,"melody":"None","gurmukhi":"","description":"There is no melody or mood associated with this line, which may be because it is the preamble to the hymn, or is not meant to be read in any particular melody or mood"},"author":{"id":7,"author":"Saint Kabir","gurmukhi":"\u0a2d\u0a17\u0a24 \u0a15\u0a2c\u0a40\u0a30","description":"Saint Kabir [1440 - 1518] was a Muslim mystic born in Varanasi in India, whose 541 hymns are included in the Guru Granth Sahib. His writings about God are full of love and devotion, very direct and striking in appeal.<br\/><br\/>The birth of Kabir remains to this day shrouded in mystery and legend. Authorities disagree on both when he was born and who his parents were. One legend proclaims a divine virginal birth. His mother was reputed to have been of the Brahman caste and to have become pregnant after a visit to a Hindu shrine.<br\/><br\/>Because she was unwed, she abandoned Kabir, who was found and adopted by a Muslim weaver. That his early life began as a Muslim there is no doubt, although he later became influenced by the Hindu ascetic, Ramananda, who he accepted as his Guru."},"language":{"id":54,"language":"Gurmukhi","code":"pa","script":"guru","direction":1,"accuracy":99}},{"id":58382,"text":"\u0a15\u0a2c\u0a40\u0a30 \u0a2a\u0a3e\u0a32\u0a3f \u0a38\u0a2e\u0a41\u0a39\u0a3e \u0a38\u0a30\u0a35\u0a30\u0a41 \u0a2d\u0a30\u0a3e \u0a2a\u0a40 \u0a28 \u0a38\u0a15\u0a48 \u0a15\u0a4b\u0a08 \u0a28\u0a40\u0a30\u0a41 \u0965","original":"\u0a15\u0a2c\u0a40\u0a30\u0a2a\u0a3e\u0a32\u0a3f\u0a38\u0a2e\u0a41\u0a39\u0a3e\u0a38\u0a30\u0a35\u0a30\u0a41\u0a2d\u0a30\u0a3e\u0a2a\u0a40\u0a28\u0a38\u0a15\u0a48\u0a15\u0a4b\u0a08\u0a28\u0a40\u0a30\u0a41\u0965","melody_id":1,"author_id":7,"hymn":3563,"page":1373,"line":12,"section":"Salok Bhagat Kabeer (Verses Of Saint Kabeer)","search":"\u0a15\u0a2a\u0a38\u0a38\u0a2d\u0a2a\u0a28\u0a38\u0a15\u0a28","language_id":54,"translation":{"id":992478,"scripture_id":58382,"text":"Kabeer, the pool is filled to overflowing, but no one can drink the water from it.","language_id":13,"language":{"id":13,"language":"English","code":"en-US","script":"latn","direction":1,"accuracy":99}},"transliteration":{"id":1284383,"scripture_id":58382,"text":"kab\u012br p\u0101l samuh\u0101 saravar bhar\u0101 p\u012b n sakai k\u014d\u012b n\u012br .","language_id":69,"language":{"id":69,"language":"Latin","code":null,"script":"latn","direction":1,"accuracy":99}},"melody":{"id":1,"melody":"None","gurmukhi":"","description":"There is no melody or mood associated with this line, which may be because it is the preamble to the hymn, or is not meant to be read in any particular melody or mood"},"author":{"id":7,"author":"Saint Kabir","gurmukhi":"\u0a2d\u0a17\u0a24 \u0a15\u0a2c\u0a40\u0a30","description":"Saint Kabir [1440 - 1518] was a Muslim mystic born in Varanasi in India, whose 541 hymns are included in the Guru Granth Sahib. His writings about God are full of love and devotion, very direct and striking in appeal.<br\/><br\/>The birth of Kabir remains to this day shrouded in mystery and legend. Authorities disagree on both when he was born and who his parents were. One legend proclaims a divine virginal birth. His mother was reputed to have been of the Brahman caste and to have become pregnant after a visit to a Hindu shrine.<br\/><br\/>Because she was unwed, she abandoned Kabir, who was found and adopted by a Muslim weaver. That his early life began as a Muslim there is no doubt, although he later became influenced by the Hindu ascetic, Ramananda, who he accepted as his Guru."},"language":{"id":54,"language":"Gurmukhi","code":"pa","script":"guru","direction":1,"accuracy":99}},{"id":58383,"text":"\u0a2d\u0a3e\u0a17 \u0a2c\u0a21\u0a47 \u0a24\u0a48 \u0a2a\u0a3e\u0a07\u0a13 \u0a24\u0a42\u0a70 \u0a2d\u0a30\u0a3f \u0a2d\u0a30\u0a3f \u0a2a\u0a40\u0a09 \u0a15\u0a2c\u0a40\u0a30 \u0965\u0a67\u0a6d\u0a66\u0965","original":"\u0a2d\u0a3e\u0a17\u0a2c\u0a21\u0a47\u0a24\u0a48\u0a2a\u0a3e\u0a07\u0a13\u0a24\u0a42\u0a70\u0a2d\u0a30\u0a3f\u0a2d\u0a30\u0a3f\u0a2a\u0a40\u0a09\u0a15\u0a2c\u0a40\u0a30\u0965\u0a67\u0a6d\u0a66\u0965","melody_id":1,"author_id":7,"hymn":3563,"page":1373,"line":12,"section":"Salok Bhagat Kabeer (Verses Of Saint Kabeer)","search":"\u0a2d\u0a2c\u0a24\u0a2a\u0a24\u0a2d\u0a2d\u0a2a\u0a15","language_id":54,"translation":{"id":992495,"scripture_id":58383,"text":"By great good fortune, you have found it; drink it in handfuls, O Kabeer. ||170||","language_id":13,"language":{"id":13,"language":"English","code":"en-US","script":"latn","direction":1,"accuracy":99}},"transliteration":{"id":1284405,"scripture_id":58383,"text":"bh\u0101g bad\u0113 tai p\u0101i\u014d t\u016bn bhar bhar p\u012bu kab\u012br .170.","language_id":69,"language":{"id":69,"language":"Latin","code":null,"script":"latn","direction":1,"accuracy":99}},"melody":{"id":1,"melody":"None","gurmukhi":"","description":"There is no melody or mood associated with this line, which may be because it is the preamble to the hymn, or is not meant to be read in any particular melody or mood"},"author":{"id":7,"author":"Saint Kabir","gurmukhi":"\u0a2d\u0a17\u0a24 \u0a15\u0a2c\u0a40\u0a30","description":"Saint Kabir [1440 - 1518] was a Muslim mystic born in Varanasi in India, whose 541 hymns are included in the Guru Granth Sahib. His writings about God are full of love and devotion, very direct and striking in appeal.<br\/><br\/>The birth of Kabir remains to this day shrouded in mystery and legend. Authorities disagree on both when he was born and who his parents were. One legend proclaims a divine virginal birth. His mother was reputed to have been of the Brahman caste and to have become pregnant after a visit to a Hindu shrine.<br\/><br\/>Because she was unwed, she abandoned Kabir, who was found and adopted by a Muslim weaver. That his early life began as a Muslim there is no doubt, although he later became influenced by the Hindu ascetic, Ramananda, who he accepted as his Guru."},"language":{"id":54,"language":"Gurmukhi","code":"pa","script":"guru","direction":1,"accuracy":99}},{"id":58384,"text":"\u0a15\u0a2c\u0a40\u0a30 \u0a2a\u0a30\u0a2d\u0a3e\u0a24\u0a47 \u0a24\u0a3e\u0a30\u0a47 \u0a16\u0a3f\u0a38\u0a39\u0a3f \u0a24\u0a3f\u0a09 \u0a07\u0a39\u0a41 \u0a16\u0a3f\u0a38\u0a48 \u0a38\u0a30\u0a40\u0a30\u0a41 \u0965","original":"\u0a15\u0a2c\u0a40\u0a30\u0a2a\u0a30\u0a2d\u0a3e\u0a24\u0a47\u0a24\u0a3e\u0a30\u0a47\u0a16\u0a3f\u0a38\u0a39\u0a3f\u0a24\u0a3f\u0a09\u0a07\u0a39\u0a41\u0a16\u0a3f\u0a38\u0a48\u0a38\u0a30\u0a40\u0a30\u0a41\u0965","melody_id":1,"author_id":7,"hymn":3563,"page":1373,"line":13,"section":"Salok Bhagat Kabeer (Verses Of Saint Kabeer)","search":"\u0a15\u0a2a\u0a24\u0a16\u0a24\u0a72\u0a16\u0a38","language_id":54,"translation":{"id":992512,"scripture_id":58384,"text":"Kabeer, just as the stars disappear at dawn, so shall this body disappear.","language_id":13,"language":{"id":13,"language":"English","code":"en-US","script":"latn","direction":1,"accuracy":99}},"transliteration":{"id":1284427,"scripture_id":58384,"text":"kab\u012br parabh\u0101t\u0113 t\u0101r\u0113 khisah tiu ih khisai sar\u012br .","language_id":69,"language":{"id":69,"language":"Latin","code":null,"script":"latn","direction":1,"accuracy":99}},"melody":{"id":1,"melody":"None","gurmukhi":"","description":"There is no melody or mood associated with this line, which may be because it is the preamble to the hymn, or is not meant to be read in any particular melody or mood"},"author":{"id":7,"author":"Saint Kabir","gurmukhi":"\u0a2d\u0a17\u0a24 \u0a15\u0a2c\u0a40\u0a30","description":"Saint Kabir [1440 - 1518] was a Muslim mystic born in Varanasi in India, whose 541 hymns are included in the Guru Granth Sahib. His writings about God are full of love and devotion, very direct and striking in appeal.<br\/><br\/>The birth of Kabir remains to this day shrouded in mystery and legend. Authorities disagree on both when he was born and who his parents were. One legend proclaims a divine virginal birth. His mother was reputed to have been of the Brahman caste and to have become pregnant after a visit to a Hindu shrine.<br\/><br\/>Because she was unwed, she abandoned Kabir, who was found and adopted by a Muslim weaver. That his early life began as a Muslim there is no doubt, although he later became influenced by the Hindu ascetic, Ramananda, who he accepted as his Guru."},"language":{"id":54,"language":"Gurmukhi","code":"pa","script":"guru","direction":1,"accuracy":99}},{"id":58385,"text":"\u0a0f \u0a26\u0a41\u0a07 \u0a05\u0a16\u0a30 \u0a28\u0a3e \u0a16\u0a3f\u0a38\u0a39\u0a3f \u0a38\u0a4b \u0a17\u0a39\u0a3f \u0a30\u0a39\u0a3f\u0a13 \u0a15\u0a2c\u0a40\u0a30\u0a41 \u0965\u0a67\u0a6d\u0a67\u0965","original":"\u0a0f\u0a26\u0a41\u0a07\u0a05\u0a16\u0a30\u0a28\u0a3e\u0a16\u0a3f\u0a38\u0a39\u0a3f\u0a38\u0a4b\u0a17\u0a39\u0a3f\u0a30\u0a39\u0a3f\u0a13\u0a15\u0a2c\u0a40\u0a30\u0a41\u0965\u0a67\u0a6d\u0a67\u0965","melody_id":1,"author_id":7,"hymn":3563,"page":1373,"line":13,"section":"Salok Bhagat Kabeer (Verses Of Saint Kabeer)","search":"\u0a72\u0a26\u0a05\u0a28\u0a16\u0a38\u0a17\u0a30\u0a15","language_id":54,"translation":{"id":992529,"scripture_id":58385,"text":"Only the letters of God's Name do not disappear; Kabeer holds these tight. ||171||","language_id":13,"language":{"id":13,"language":"English","code":"en-US","script":"latn","direction":1,"accuracy":99}},"transliteration":{"id":1284449,"scripture_id":58385,"text":"\u0113 dui akhar n\u0101 khisah s\u014d gah rahi\u014d kab\u012br .171.","language_id":69,"language":{"id":69,"language":"Latin","code":null,"script":"latn","direction":1,"accuracy":99}},"melody":{"id":1,"melody":"None","gurmukhi":"","description":"There is no melody or mood associated with this line, which may be because it is the preamble to the hymn, or is not meant to be read in any particular melody or mood"},"author":{"id":7,"author":"Saint Kabir","gurmukhi":"\u0a2d\u0a17\u0a24 \u0a15\u0a2c\u0a40\u0a30","description":"Saint Kabir [1440 - 1518] was a Muslim mystic born in Varanasi in India, whose 541 hymns are included in the Guru Granth Sahib. His writings about God are full of love and devotion, very direct and striking in appeal.<br\/><br\/>The birth of Kabir remains to this day shrouded in mystery and legend. Authorities disagree on both when he was born and who his parents were. One legend proclaims a divine virginal birth. His mother was reputed to have been of the Brahman caste and to have become pregnant after a visit to a Hindu shrine.<br\/><br\/>Because she was unwed, she abandoned Kabir, who was found and adopted by a Muslim weaver. That his early life began as a Muslim there is no doubt, although he later became influenced by the Hindu ascetic, Ramananda, who he accepted as his Guru."},"language":{"id":54,"language":"Gurmukhi","code":"pa","script":"guru","direction":1,"accuracy":99}},{"id":58386,"text":"\u0a15\u0a2c\u0a40\u0a30 \u0a15\u0a4b\u0a20\u0a40 \u0a15\u0a3e\u0a20 \u0a15\u0a40 \u0a26\u0a39 \u0a26\u0a3f\u0a38\u0a3f \u0a32\u0a3e\u0a17\u0a40 \u0a06\u0a17\u0a3f \u0965","original":"\u0a15\u0a2c\u0a40\u0a30\u0a15\u0a4b\u0a20\u0a40\u0a15\u0a3e\u0a20\u0a15\u0a40\u0a26\u0a39\u0a26\u0a3f\u0a38\u0a3f\u0a32\u0a3e\u0a17\u0a40\u0a06\u0a17\u0a3f\u0965","melody_id":1,"author_id":7,"hymn":3563,"page":1373,"line":14,"section":"Salok Bhagat Kabeer (Verses Of Saint Kabeer)","search":"\u0a15\u0a15\u0a15\u0a15\u0a26\u0a26\u0a32\u0a05","language_id":54,"translation":{"id":992546,"scripture_id":58386,"text":"Kabeer, the wooden house is burning on all sides.","language_id":13,"language":{"id":13,"language":"English","code":"en-US","script":"latn","direction":1,"accuracy":99}},"transliteration":{"id":1284471,"scripture_id":58386,"text":"kab\u012br k\u014dth\u012b k\u0101th k\u012b dah dis l\u0101g\u012b \u0101g .","language_id":69,"language":{"id":69,"language":"Latin","code":null,"script":"latn","direction":1,"accuracy":99}},"melody":{"id":1,"melody":"None","gurmukhi":"","description":"There is no melody or mood associated with this line, which may be because it is the preamble to the hymn, or is not meant to be read in any particular melody or mood"},"author":{"id":7,"author":"Saint Kabir","gurmukhi":"\u0a2d\u0a17\u0a24 \u0a15\u0a2c\u0a40\u0a30","description":"Saint Kabir [1440 - 1518] was a Muslim mystic born in Varanasi in India, whose 541 hymns are included in the Guru Granth Sahib. His writings about God are full of love and devotion, very direct and striking in appeal.<br\/><br\/>The birth of Kabir remains to this day shrouded in mystery and legend. Authorities disagree on both when he was born and who his parents were. One legend proclaims a divine virginal birth. His mother was reputed to have been of the Brahman caste and to have become pregnant after a visit to a Hindu shrine.<br\/><br\/>Because she was unwed, she abandoned Kabir, who was found and adopted by a Muslim weaver. That his early life began as a Muslim there is no doubt, although he later became influenced by the Hindu ascetic, Ramananda, who he accepted as his Guru."},"language":{"id":54,"language":"Gurmukhi","code":"pa","script":"guru","direction":1,"accuracy":99}},{"id":58387,"text":"\u0a2a\u0a70\u0a21\u0a3f\u0a24 \u0a2a\u0a70\u0a21\u0a3f\u0a24 \u0a1c\u0a32\u0a3f \u0a2e\u0a42\u0a0f \u0a2e\u0a42\u0a30\u0a16 \u0a09\u0a2c\u0a30\u0a47 \u0a2d\u0a3e\u0a17\u0a3f \u0965\u0a67\u0a6d\u0a68\u0965","original":"\u0a2a\u0a70\u0a21\u0a3f\u0a24\u0a2a\u0a70\u0a21\u0a3f\u0a24\u0a1c\u0a32\u0a3f\u0a2e\u0a42\u0a0f\u0a2e\u0a42\u0a30\u0a16\u0a09\u0a2c\u0a30\u0a47\u0a2d\u0a3e\u0a17\u0a3f\u0965\u0a67\u0a6d\u0a68\u0965","melody_id":1,"author_id":7,"hymn":3563,"page":1373,"line":14,"section":"Salok Bhagat Kabeer (Verses Of Saint Kabeer)","search":"\u0a2a\u0a2a\u0a1c\u0a2e\u0a2e\u0a73\u0a2d","language_id":54,"translation":{"id":992563,"scripture_id":58387,"text":"The Pandits, the religious scholars, have been burnt to death, while the illiterate ones run to safety. ||172||","language_id":13,"language":{"id":13,"language":"English","code":"en-US","script":"latn","direction":1,"accuracy":99}},"transliteration":{"id":1284493,"scripture_id":58387,"text":"pandit pandit jal m\u016b\u0113 m\u016brakh ubar\u0113 bh\u0101g .172.","language_id":69,"language":{"id":69,"language":"Latin","code":null,"script":"latn","direction":1,"accuracy":99}},"melody":{"id":1,"melody":"None","gurmukhi":"","description":"There is no melody or mood associated with this line, which may be because it is the preamble to the hymn, or is not meant to be read in any particular melody or mood"},"author":{"id":7,"author":"Saint Kabir","gurmukhi":"\u0a2d\u0a17\u0a24 \u0a15\u0a2c\u0a40\u0a30","description":"Saint Kabir [1440 - 1518] was a Muslim mystic born in Varanasi in India, whose 541 hymns are included in the Guru Granth Sahib. His writings about God are full of love and devotion, very direct and striking in appeal.<br\/><br\/>The birth of Kabir remains to this day shrouded in mystery and legend. Authorities disagree on both when he was born and who his parents were. One legend proclaims a divine virginal birth. His mother was reputed to have been of the Brahman caste and to have become pregnant after a visit to a Hindu shrine.<br\/><br\/>Because she was unwed, she abandoned Kabir, who was found and adopted by a Muslim weaver. That his early life began as a Muslim there is no doubt, although he later became influenced by the Hindu ascetic, Ramananda, who he accepted as his Guru."},"language":{"id":54,"language":"Gurmukhi","code":"pa","script":"guru","direction":1,"accuracy":99}},{"id":58388,"text":"\u0a15\u0a2c\u0a40\u0a30 \u0a38\u0a70\u0a38\u0a3e \u0a26\u0a42\u0a30\u0a3f \u0a15\u0a30\u0a41 \u0a15\u0a3e\u0a17\u0a26 \u0a26\u0a47\u0a39 \u0a2c\u0a3f\u0a39\u0a3e\u0a07 \u0965","original":"\u0a15\u0a2c\u0a40\u0a30\u0a38\u0a70\u0a38\u0a3e\u0a26\u0a42\u0a30\u0a3f\u0a15\u0a30\u0a41\u0a15\u0a3e\u0a17\u0a26\u0a26\u0a47\u0a39\u0a2c\u0a3f\u0a39\u0a3e\u0a07\u0965","melody_id":1,"author_id":7,"hymn":3563,"page":1373,"line":15,"section":"Salok Bhagat Kabeer (Verses Of Saint Kabeer)","search":"\u0a15\u0a38\u0a26\u0a15\u0a15\u0a26\u0a2c","language_id":54,"translation":{"id":992580,"scripture_id":58388,"text":"Kabeer, give up your skepticism; let your papers float away.","language_id":13,"language":{"id":13,"language":"English","code":"en-US","script":"latn","direction":1,"accuracy":99}},"transliteration":{"id":1284515,"scripture_id":58388,"text":"kab\u012br sans\u0101 d\u016br kar k\u0101gad d\u0113h bih\u0101i .","language_id":69,"language":{"id":69,"language":"Latin","code":null,"script":"latn","direction":1,"accuracy":99}},"melody":{"id":1,"melody":"None","gurmukhi":"","description":"There is no melody or mood associated with this line, which may be because it is the preamble to the hymn, or is not meant to be read in any particular melody or mood"},"author":{"id":7,"author":"Saint Kabir","gurmukhi":"\u0a2d\u0a17\u0a24 \u0a15\u0a2c\u0a40\u0a30","description":"Saint Kabir [1440 - 1518] was a Muslim mystic born in Varanasi in India, whose 541 hymns are included in the Guru Granth Sahib. His writings about God are full of love and devotion, very direct and striking in appeal.<br\/><br\/>The birth of Kabir remains to this day shrouded in mystery and legend. Authorities disagree on both when he was born and who his parents were. One legend proclaims a divine virginal birth. His mother was reputed to have been of the Brahman caste and to have become pregnant after a visit to a Hindu shrine.<br\/><br\/>Because she was unwed, she abandoned Kabir, who was found and adopted by a Muslim weaver. That his early life began as a Muslim there is no doubt, although he later became influenced by the Hindu ascetic, Ramananda, who he accepted as his Guru."},"language":{"id":54,"language":"Gurmukhi","code":"pa","script":"guru","direction":1,"accuracy":99}},{"id":58389,"text":"\u0a2c\u0a3e\u0a35\u0a28 \u0a05\u0a16\u0a30 \u0a38\u0a4b\u0a27\u0a3f \u0a15\u0a48 \u0a39\u0a30\u0a3f \u0a1a\u0a30\u0a28\u0a40 \u0a1a\u0a3f\u0a24\u0a41 \u0a32\u0a3e\u0a07 \u0965\u0a67\u0a6d\u0a69\u0965","original":"\u0a2c\u0a3e\u0a35\u0a28\u0a05\u0a16\u0a30\u0a38\u0a4b\u0a27\u0a3f\u0a15\u0a48\u0a39\u0a30\u0a3f\u0a1a\u0a30\u0a28\u0a40\u0a1a\u0a3f\u0a24\u0a41\u0a32\u0a3e\u0a07\u0965\u0a67\u0a6d\u0a69\u0965","melody_id":1,"author_id":7,"hymn":3563,"page":1373,"line":15,"section":"Salok Bhagat Kabeer (Verses Of Saint Kabeer)","search":"\u0a2c\u0a05\u0a38\u0a15\u0a39\u0a1a\u0a1a\u0a32","language_id":54,"translation":{"id":992597,"scripture_id":58389,"text":"Find the essence of the letters of the alphabet, and focus your consciousness on the Lord. ||173||","language_id":13,"language":{"id":13,"language":"English","code":"en-US","script":"latn","direction":1,"accuracy":99}},"transliteration":{"id":1284537,"scripture_id":58389,"text":"b\u0101van akhar s\u014ddh kai har charan\u012b chit l\u0101i .173.","language_id":69,"language":{"id":69,"language":"Latin","code":null,"script":"latn","direction":1,"accuracy":99}},"melody":{"id":1,"melody":"None","gurmukhi":"","description":"There is no melody or mood associated with this line, which may be because it is the preamble to the hymn, or is not meant to be read in any particular melody or mood"},"author":{"id":7,"author":"Saint Kabir","gurmukhi":"\u0a2d\u0a17\u0a24 \u0a15\u0a2c\u0a40\u0a30","description":"Saint Kabir [1440 - 1518] was a Muslim mystic born in Varanasi in India, whose 541 hymns are included in the Guru Granth Sahib. His writings about God are full of love and devotion, very direct and striking in appeal.<br\/><br\/>The birth of Kabir remains to this day shrouded in mystery and legend. Authorities disagree on both when he was born and who his parents were. One legend proclaims a divine virginal birth. His mother was reputed to have been of the Brahman caste and to have become pregnant after a visit to a Hindu shrine.<br\/><br\/>Because she was unwed, she abandoned Kabir, who was found and adopted by a Muslim weaver. That his early life began as a Muslim there is no doubt, although he later became influenced by the Hindu ascetic, Ramananda, who he accepted as his Guru."},"language":{"id":54,"language":"Gurmukhi","code":"pa","script":"guru","direction":1,"accuracy":99}},{"id":58390,"text":"\u0a15\u0a2c\u0a40\u0a30 \u0a38\u0a70\u0a24\u0a41 \u0a28 \u0a1b\u0a3e\u0a21\u0a48 \u0a38\u0a70\u0a24\u0a08 \u0a1c\u0a09 \u0a15\u0a4b\u0a1f\u0a3f\u0a15 \u0a2e\u0a3f\u0a32\u0a39\u0a3f \u0a05\u0a38\u0a70\u0a24 \u0965","original":"\u0a15\u0a2c\u0a40\u0a30\u0a38\u0a70\u0a24\u0a41\u0a28\u0a1b\u0a3e\u0a21\u0a48\u0a38\u0a70\u0a24\u0a08\u0a1c\u0a09\u0a15\u0a4b\u0a1f\u0a3f\u0a15\u0a2e\u0a3f\u0a32\u0a39\u0a3f\u0a05\u0a38\u0a70\u0a24\u0965","melody_id":1,"author_id":7,"hymn":3563,"page":1373,"line":16,"section":"Salok Bhagat Kabeer (Verses Of Saint Kabeer)","search":"\u0a15\u0a38\u0a28\u0a1b\u0a38\u0a1c\u0a15\u0a2e\u0a05","language_id":54,"translation":{"id":992614,"scripture_id":58390,"text":"Kabeer, the Saint does not forsake his Saintly nature, even though he meets with millions of evil-doers.","language_id":13,"language":{"id":13,"language":"English","code":"en-US","script":"latn","direction":1,"accuracy":99}},"transliteration":{"id":1284559,"scripture_id":58390,"text":"kab\u012br sant n sh\u0101dai santa\u012b jau k\u014dtik milah asant .","language_id":69,"language":{"id":69,"language":"Latin","code":null,"script":"latn","direction":1,"accuracy":99}},"melody":{"id":1,"melody":"None","gurmukhi":"","description":"There is no melody or mood associated with this line, which may be because it is the preamble to the hymn, or is not meant to be read in any particular melody or mood"},"author":{"id":7,"author":"Saint Kabir","gurmukhi":"\u0a2d\u0a17\u0a24 \u0a15\u0a2c\u0a40\u0a30","description":"Saint Kabir [1440 - 1518] was a Muslim mystic born in Varanasi in India, whose 541 hymns are included in the Guru Granth Sahib. His writings about God are full of love and devotion, very direct and striking in appeal.<br\/><br\/>The birth of Kabir remains to this day shrouded in mystery and legend. Authorities disagree on both when he was born and who his parents were. One legend proclaims a divine virginal birth. His mother was reputed to have been of the Brahman caste and to have become pregnant after a visit to a Hindu shrine.<br\/><br\/>Because she was unwed, she abandoned Kabir, who was found and adopted by a Muslim weaver. That his early life began as a Muslim there is no doubt, although he later became influenced by the Hindu ascetic, Ramananda, who he accepted as his Guru."},"language":{"id":54,"language":"Gurmukhi","code":"pa","script":"guru","direction":1,"accuracy":99}},{"id":58391,"text":"\u0a2e\u0a32\u0a3f\u0a06\u0a17\u0a30\u0a41 \u0a2d\u0a41\u0a2f\u0a70\u0a17\u0a2e \u0a2c\u0a47\u0a22\u0a3f\u0a13 \u0a24 \u0a38\u0a40\u0a24\u0a32\u0a24\u0a3e \u0a28 \u0a24\u0a1c\u0a70\u0a24 \u0965\u0a67\u0a6d\u0a6a\u0965","original":"\u0a2e\u0a32\u0a3f\u0a06\u0a17\u0a30\u0a41\u0a2d\u0a41\u0a2f\u0a70\u0a17\u0a2e\u0a2c\u0a47\u0a22\u0a3f\u0a13\u0a24\u0a38\u0a40\u0a24\u0a32\u0a24\u0a3e\u0a28\u0a24\u0a1c\u0a70\u0a24\u0965\u0a67\u0a6d\u0a6a\u0965","melody_id":1,"author_id":7,"hymn":3563,"page":1373,"line":17,"section":"Salok Bhagat Kabeer (Verses Of Saint Kabeer)","search":"\u0a2e\u0a2d\u0a2c\u0a24\u0a38\u0a28\u0a24","language_id":54,"translation":{"id":992631,"scripture_id":58391,"text":"Even when sandalwood is surrounded by snakes, it does not give up its cooling fragrance. ||174||","language_id":13,"language":{"id":13,"language":"English","code":"en-US","script":"latn","direction":1,"accuracy":99}},"transliteration":{"id":1284581,"scripture_id":58391,"text":"mali\u0101gar bhuyangam b\u0113dhi\u014d t s\u012btalat\u0101 n tajant .174.","language_id":69,"language":{"id":69,"language":"Latin","code":null,"script":"latn","direction":1,"accuracy":99}},"melody":{"id":1,"melody":"None","gurmukhi":"","description":"There is no melody or mood associated with this line, which may be because it is the preamble to the hymn, or is not meant to be read in any particular melody or mood"},"author":{"id":7,"author":"Saint Kabir","gurmukhi":"\u0a2d\u0a17\u0a24 \u0a15\u0a2c\u0a40\u0a30","description":"Saint Kabir [1440 - 1518] was a Muslim mystic born in Varanasi in India, whose 541 hymns are included in the Guru Granth Sahib. His writings about God are full of love and devotion, very direct and striking in appeal.<br\/><br\/>The birth of Kabir remains to this day shrouded in mystery and legend. Authorities disagree on both when he was born and who his parents were. One legend proclaims a divine virginal birth. His mother was reputed to have been of the Brahman caste and to have become pregnant after a visit to a Hindu shrine.<br\/><br\/>Because she was unwed, she abandoned Kabir, who was found and adopted by a Muslim weaver. That his early life began as a Muslim there is no doubt, although he later became influenced by the Hindu ascetic, Ramananda, who he accepted as his Guru."},"language":{"id":54,"language":"Gurmukhi","code":"pa","script":"guru","direction":1,"accuracy":99}},{"id":58392,"text":"\u0a15\u0a2c\u0a40\u0a30 \u0a2e\u0a28\u0a41 \u0a38\u0a40\u0a24\u0a32\u0a41 \u0a2d\u0a07\u0a06 \u0a2a\u0a3e\u0a07\u0a06 \u0a2c\u0a4d\u0a30\u0a39\u0a2e \u0a17\u0a3f\u0a06\u0a28\u0a41 \u0965","original":"\u0a15\u0a2c\u0a40\u0a30\u0a2e\u0a28\u0a41\u0a38\u0a40\u0a24\u0a32\u0a41\u0a2d\u0a07\u0a06\u0a2a\u0a3e\u0a07\u0a06\u0a2c\u0a4d\u0a30\u0a39\u0a2e\u0a17\u0a3f\u0a06\u0a28\u0a41\u0965","melody_id":1,"author_id":7,"hymn":3563,"page":1373,"line":17,"section":"Salok Bhagat Kabeer (Verses Of Saint Kabeer)","search":"\u0a15\u0a2e\u0a38\u0a2d\u0a2a\u0a2c\u0a17","language_id":54,"translation":{"id":992648,"scripture_id":58392,"text":"Kabeer, my mind is cooled and soothed; I have become God-conscious.","language_id":13,"language":{"id":13,"language":"English","code":"en-US","script":"latn","direction":1,"accuracy":99}},"transliteration":{"id":1284603,"scripture_id":58392,"text":"kab\u012br man s\u012btal bhai\u0101 p\u0101i\u0101 braham gi\u0101n .","language_id":69,"language":{"id":69,"language":"Latin","code":null,"script":"latn","direction":1,"accuracy":99}},"melody":{"id":1,"melody":"None","gurmukhi":"","description":"There is no melody or mood associated with this line, which may be because it is the preamble to the hymn, or is not meant to be read in any particular melody or mood"},"author":{"id":7,"author":"Saint Kabir","gurmukhi":"\u0a2d\u0a17\u0a24 \u0a15\u0a2c\u0a40\u0a30","description":"Saint Kabir [1440 - 1518] was a Muslim mystic born in Varanasi in India, whose 541 hymns are included in the Guru Granth Sahib. His writings about God are full of love and devotion, very direct and striking in appeal.<br\/><br\/>The birth of Kabir remains to this day shrouded in mystery and legend. Authorities disagree on both when he was born and who his parents were. One legend proclaims a divine virginal birth. His mother was reputed to have been of the Brahman caste and to have become pregnant after a visit to a Hindu shrine.<br\/><br\/>Because she was unwed, she abandoned Kabir, who was found and adopted by a Muslim weaver. That his early life began as a Muslim there is no doubt, although he later became influenced by the Hindu ascetic, Ramananda, who he accepted as his Guru."},"language":{"id":54,"language":"Gurmukhi","code":"pa","script":"guru","direction":1,"accuracy":99}},{"id":58393,"text":"\u0a1c\u0a3f\u0a28\u0a3f \u0a1c\u0a41\u0a06\u0a32\u0a3e \u0a1c\u0a17\u0a41 \u0a1c\u0a3e\u0a30\u0a3f\u0a06 \u0a38\u0a41 \u0a1c\u0a28 \u0a15\u0a47 \u0a09\u0a26\u0a15 \u0a38\u0a2e\u0a3e\u0a28\u0a3f \u0965\u0a67\u0a6d\u0a6b\u0965","original":"\u0a1c\u0a3f\u0a28\u0a3f\u0a1c\u0a41\u0a06\u0a32\u0a3e\u0a1c\u0a17\u0a41\u0a1c\u0a3e\u0a30\u0a3f\u0a06\u0a38\u0a41\u0a1c\u0a28\u0a15\u0a47\u0a09\u0a26\u0a15\u0a38\u0a2e\u0a3e\u0a28\u0a3f\u0965\u0a67\u0a6d\u0a6b\u0965","melody_id":1,"author_id":7,"hymn":3563,"page":1373,"line":18,"section":"Salok Bhagat Kabeer (Verses Of Saint Kabeer)","search":"\u0a1c\u0a1c\u0a1c\u0a1c\u0a38\u0a1c\u0a15\u0a73\u0a38","language_id":54,"translation":{"id":992665,"scripture_id":58393,"text":"The fire which has burnt the world is like water to the Lord's humble servant. ||175||","language_id":13,"language":{"id":13,"language":"English","code":"en-US","script":"latn","direction":1,"accuracy":99}},"transliteration":{"id":1284625,"scripture_id":58393,"text":"jin ju\u0101l\u0101 jag j\u0101ri\u0101 s jan k\u0113 udak sam\u0101n .175.","language_id":69,"language":{"id":69,"language":"Latin","code":null,"script":"latn","direction":1,"accuracy":99}},"melody":{"id":1,"melody":"None","gurmukhi":"","description":"There is no melody or mood associated with this line, which may be because it is the preamble to the hymn, or is not meant to be read in any particular melody or mood"},"author":{"id":7,"author":"Saint Kabir","gurmukhi":"\u0a2d\u0a17\u0a24 \u0a15\u0a2c\u0a40\u0a30","description":"Saint Kabir [1440 - 1518] was a Muslim mystic born in Varanasi in India, whose 541 hymns are included in the Guru Granth Sahib. His writings about God are full of love and devotion, very direct and striking in appeal.<br\/><br\/>The birth of Kabir remains to this day shrouded in mystery and legend. Authorities disagree on both when he was born and who his parents were. One legend proclaims a divine virginal birth. His mother was reputed to have been of the Brahman caste and to have become pregnant after a visit to a Hindu shrine.<br\/><br\/>Because she was unwed, she abandoned Kabir, who was found and adopted by a Muslim weaver. That his early life began as a Muslim there is no doubt, although he later became influenced by the Hindu ascetic, Ramananda, who he accepted as his Guru."},"language":{"id":54,"language":"Gurmukhi","code":"pa","script":"guru","direction":1,"accuracy":99}},{"id":58394,"text":"\u0a15\u0a2c\u0a40\u0a30 \u0a38\u0a3e\u0a30\u0a40 \u0a38\u0a3f\u0a30\u0a1c\u0a28\u0a39\u0a3e\u0a30 \u0a15\u0a40 \u0a1c\u0a3e\u0a28\u0a48 \u0a28\u0a3e\u0a39\u0a40 \u0a15\u0a4b\u0a07 \u0965","original":"\u0a15\u0a2c\u0a40\u0a30\u0a38\u0a3e\u0a30\u0a40\u0a38\u0a3f\u0a30\u0a1c\u0a28\u0a39\u0a3e\u0a30\u0a15\u0a40\u0a1c\u0a3e\u0a28\u0a48\u0a28\u0a3e\u0a39\u0a40\u0a15\u0a4b\u0a07\u0965","melody_id":1,"author_id":7,"hymn":3563,"page":1373,"line":18,"section":"Salok Bhagat Kabeer (Verses Of Saint Kabeer)","search":"\u0a15\u0a38\u0a38\u0a15\u0a1c\u0a28\u0a15","language_id":54,"translation":{"id":992682,"scripture_id":58394,"text":"Kabeer, no one knows the Play of the Creator Lord.","language_id":13,"language":{"id":13,"language":"English","code":"en-US","script":"latn","direction":1,"accuracy":99}},"transliteration":{"id":1284647,"scripture_id":58394,"text":"kab\u012br s\u0101r\u012b sirajanah\u0101r k\u012b j\u0101nai n\u0101h\u012b k\u014di .","language_id":69,"language":{"id":69,"language":"Latin","code":null,"script":"latn","direction":1,"accuracy":99}},"melody":{"id":1,"melody":"None","gurmukhi":"","description":"There is no melody or mood associated with this line, which may be because it is the preamble to the hymn, or is not meant to be read in any particular melody or mood"},"author":{"id":7,"author":"Saint Kabir","gurmukhi":"\u0a2d\u0a17\u0a24 \u0a15\u0a2c\u0a40\u0a30","description":"Saint Kabir [1440 - 1518] was a Muslim mystic born in Varanasi in India, whose 541 hymns are included in the Guru Granth Sahib. His writings about God are full of love and devotion, very direct and striking in appeal.<br\/><br\/>The birth of Kabir remains to this day shrouded in mystery and legend. Authorities disagree on both when he was born and who his parents were. One legend proclaims a divine virginal birth. His mother was reputed to have been of the Brahman caste and to have become pregnant after a visit to a Hindu shrine.<br\/><br\/>Because she was unwed, she abandoned Kabir, who was found and adopted by a Muslim weaver. That his early life began as a Muslim there is no doubt, although he later became influenced by the Hindu ascetic, Ramananda, who he accepted as his Guru."},"language":{"id":54,"language":"Gurmukhi","code":"pa","script":"guru","direction":1,"accuracy":99}},{"id":58395,"text":"\u0a15\u0a48 \u0a1c\u0a3e\u0a28\u0a48 \u0a06\u0a2a\u0a28 \u0a27\u0a28\u0a40 \u0a15\u0a48 \u0a26\u0a3e\u0a38\u0a41 \u0a26\u0a40\u0a35\u0a3e\u0a28\u0a40 \u0a39\u0a4b\u0a07 \u0965\u0a67\u0a6d\u0a6c\u0965","original":"\u0a15\u0a48\u0a1c\u0a3e\u0a28\u0a48\u0a06\u0a2a\u0a28\u0a27\u0a28\u0a40\u0a15\u0a48\u0a26\u0a3e\u0a38\u0a41\u0a26\u0a40\u0a35\u0a3e\u0a28\u0a40\u0a39\u0a4b\u0a07\u0965\u0a67\u0a6d\u0a6c\u0965","melody_id":1,"author_id":7,"hymn":3563,"page":1373,"line":19,"section":"Salok Bhagat Kabeer (Verses Of Saint Kabeer)","search":"\u0a15\u0a1c\u0a05\u0a27\u0a15\u0a26\u0a26\u0a39","language_id":54,"translation":{"id":992699,"scripture_id":58395,"text":"Only the Lord Himself and the slaves at His Court understand it. ||176||","language_id":13,"language":{"id":13,"language":"English","code":"en-US","script":"latn","direction":1,"accuracy":99}},"transliteration":{"id":1284669,"scripture_id":58395,"text":"kai j\u0101nai \u0101pan dhan\u012b kai d\u0101s d\u012bv\u0101n\u012b h\u014di .176.","language_id":69,"language":{"id":69,"language":"Latin","code":null,"script":"latn","direction":1,"accuracy":99}},"melody":{"id":1,"melody":"None","gurmukhi":"","description":"There is no melody or mood associated with this line, which may be because it is the preamble to the hymn, or is not meant to be read in any particular melody or mood"},"author":{"id":7,"author":"Saint Kabir","gurmukhi":"\u0a2d\u0a17\u0a24 \u0a15\u0a2c\u0a40\u0a30","description":"Saint Kabir [1440 - 1518] was a Muslim mystic born in Varanasi in India, whose 541 hymns are included in the Guru Granth Sahib. His writings about God are full of love and devotion, very direct and striking in appeal.<br\/><br\/>The birth of Kabir remains to this day shrouded in mystery and legend. Authorities disagree on both when he was born and who his parents were. One legend proclaims a divine virginal birth. His mother was reputed to have been of the Brahman caste and to have become pregnant after a visit to a Hindu shrine.<br\/><br\/>Because she was unwed, she abandoned Kabir, who was found and adopted by a Muslim weaver. That his early life began as a Muslim there is no doubt, although he later became influenced by the Hindu ascetic, Ramananda, who he accepted as his Guru."},"language":{"id":54,"language":"Gurmukhi","code":"pa","script":"guru","direction":1,"accuracy":99}},{"id":58396,"text":"\u0a15\u0a2c\u0a40\u0a30 \u0a2d\u0a32\u0a40 \u0a2d\u0a08 \u0a1c\u0a4b \u0a2d\u0a09 \u0a2a\u0a30\u0a3f\u0a06 \u0a26\u0a3f\u0a38\u0a3e \u0a17\u0a08\u0a02 \u0a38\u0a2d \u0a2d\u0a42\u0a32\u0a3f \u0965","original":"\u0a15\u0a2c\u0a40\u0a30\u0a2d\u0a32\u0a40\u0a2d\u0a08\u0a1c\u0a4b\u0a2d\u0a09\u0a2a\u0a30\u0a3f\u0a06\u0a26\u0a3f\u0a38\u0a3e\u0a17\u0a08\u0a02\u0a38\u0a2d\u0a2d\u0a42\u0a32\u0a3f\u0965","melody_id":1,"author_id":7,"hymn":3563,"page":1373,"line":19,"section":"Salok Bhagat Kabeer (Verses Of Saint Kabeer)","search":"\u0a15\u0a2d\u0a2d\u0a1c\u0a2d\u0a2a\u0a26\u0a17\u0a38\u0a2d","language_id":54,"translation":{"id":992716,"scripture_id":58396,"text":"Kabeer, it is good that I feel the Fear of God; I have forgotten everything else.","language_id":13,"language":{"id":13,"language":"English","code":"en-US","script":"latn","direction":1,"accuracy":99}},"transliteration":{"id":1284691,"scripture_id":58396,"text":"kab\u012br bhal\u012b bha\u012b j\u014d bhau pari\u0101 dis\u0101 ga\u012bnh sabh bh\u016bl .","language_id":69,"language":{"id":69,"language":"Latin","code":null,"script":"latn","direction":1,"accuracy":99}},"melody":{"id":1,"melody":"None","gurmukhi":"","description":"There is no melody or mood associated with this line, which may be because it is the preamble to the hymn, or is not meant to be read in any particular melody or mood"},"author":{"id":7,"author":"Saint Kabir","gurmukhi":"\u0a2d\u0a17\u0a24 \u0a15\u0a2c\u0a40\u0a30","description":"Saint Kabir [1440 - 1518] was a Muslim mystic born in Varanasi in India, whose 541 hymns are included in the Guru Granth Sahib. His writings about God are full of love and devotion, very direct and striking in appeal.<br\/><br\/>The birth of Kabir remains to this day shrouded in mystery and legend. Authorities disagree on both when he was born and who his parents were. One legend proclaims a divine virginal birth. His mother was reputed to have been of the Brahman caste and to have become pregnant after a visit to a Hindu shrine.<br\/><br\/>Because she was unwed, she abandoned Kabir, who was found and adopted by a Muslim weaver. That his early life began as a Muslim there is no doubt, although he later became influenced by the Hindu ascetic, Ramananda, who he accepted as his Guru."},"language":{"id":54,"language":"Gurmukhi","code":"pa","script":"guru","direction":1,"accuracy":99}}]